Workbook

Sheet Liquidacion Supervisores
B3: LIQUIDACION SEPTIEMBRE
R4: =+COUNTIF(R7:R9,"si") -> 3
F5: TIENDA PERFECTA 60% - Se liquida a partir del 60% | I5: VENTAS 20% - Se liquida a partir del 70% | L5: FECHAS CORTAS & DEVOLUCIONES 20% - Se liquida cumpl al 100% | P5: =+SUBTOTAL(9,P7:P9) -> 1120000
B6: LIDER | C6: LLAVE 1 CAPTURA | D6: LLAVE 2 COBERTURA | E6: PROM. LLAVE | F6: VALOR COMISION TP | G6: % CUMPL. TP | H6: VALOR COMISION | I6: VALOR COMISION VENTAS | J6: % VENTAS | K6: VALOR COMISION | L6: VALOR COMISION X FC DV | M6: % FC & DV | N6: VALOR COMISION | O6: Valor Comision | P6: Valor a Pagar | Q6: Comentario | R6: Cumple Llaves
B7: ANYI MAYERLIE ORJUELA | C7: =+VLOOKUP(B7,'TD Supervisores Y Lideres Prom'!$B$44:$D$48,2,FALSE) -> 0.97557689 | D7: =+VLOOKUP(B7,'TD Supervisores Y Lideres Prom'!$B$44:$D$48,3,FALSE) -> 0.98738761 | E7: =+AVERAGE(C7:D7) -> 0.98148225 | F7: =+O7*60% -> 240000 | G7: =+VLOOKUP(B7,'TD Supervisores Y Lideres Prom'!$B$20:$C$24,2,FALSE) -> 0.93861048 | H7: =IF(G7>80%,F7*100%,IF(AND(G7>=60%,G7<=79%),F7*60%,0)) -> 240000 | I7: =+O7*20% -> 80000 | J7: =+VLOOKUP(B7,'TD Supervisores Y Lideres Prom'!$B$20:$D$24,3,FALSE) -> 1.0805537 | K7: =IF(J7=70%,I7*70%,IF(AND(J7>=80%,J7<=90%),I7*80%,IF(AND(J7>=91%,J7<=95%),I7*90%,IF(J7=96%,I7*96%,IF(J7=97%,I7*97%,IF(J7=98%,I7*98%,IF(J7=99%,I7*99%,IF(J7>=100%,I7,0)))))))) -> 80000 | L7: =+O7*20% -> 80000 | M7: =+VLOOKUP(B7,'TD Supervisores Y Lideres Prom'!$B$20:$E$24,4,FALSE) -> 0.89409233 | N7: =+IF(M7=100%,L7,0) -> 0 | O7: 400000 | P7: =IF(R7="SI",SUM(H7,K7,N7),0) -> 320000 | R7: =IF(E7>=60%,"SI","NO") -> SI
B8: OSPINO ARAUJO ALEXANDER | C8: =+VLOOKUP(B8,'TD Supervisores Y Lideres Prom'!$B$44:$D$48,2,FALSE) -> 0.94750086 | D8: =+VLOOKUP(B8,'TD Supervisores Y Lideres Prom'!$B$44:$D$48,3,FALSE) -> 0.96118796 | E8: =+AVERAGE(C8:D8) -> 0.95434441 | F8: =+O8*60% -> 240000 | G8: =+VLOOKUP(B8,'TD Supervisores Y Lideres Prom'!$B$20:$C$24,2,FALSE) -> 0.87800853 | H8: =IF(G8>80%,F8*100%,IF(AND(G8>=60%,G8<=79%),F8*60%,0)) -> 240000 | I8: =+O8*20% -> 80000 | J8: =+VLOOKUP(B8,'TD Supervisores Y Lideres Prom'!$B$20:$D$24,3,FALSE) -> 1.0064851 | K8: =+I8*70% -> 56000 | L8: =+O8*20% -> 80000 | M8: =+VLOOKUP(B8,'TD Supervisores Y Lideres Prom'!$B$20:$E$24,4,FALSE) -> 0.81827385 | N8: =+IF(M8=100%,L8,0) -> 0 | O8: 400000 | P8: =+O8 -> 400000 | Q8: Ingreso el 18 Agosto / Pago pagarantizado Sept | R8: =IF(AND(C8>=70%,D8>=70%),"SI","NO") -> SI
B9: NATHALY AGUILAR | C9: =+VLOOKUP(B9,'TD Supervisores Y Lideres Prom'!$B$44:$D$48,2,FALSE) -> 0.95003768 | D9: =+VLOOKUP(B9,'TD Supervisores Y Lideres Prom'!$B$44:$D$48,3,FALSE) -> 0.95338013 | E9: =+AVERAGE(C9:D9) -> 0.95170891 | F9: =+O9*60% -> 240000 | G9: =+VLOOKUP(B9,'TD Supervisores Y Lideres Prom'!$B$20:$C$24,2,FALSE) -> 0.76785671 | H9: =IF(G9>80%,F9*100%,IF(AND(G9>=60%,G9<=79%),F9*60%,0)) -> 144000 | I9: =+O9*20% -> 80000 | J9: =+VLOOKUP(B9,'TD Supervisores Y Lideres Prom'!$B$20:$D$24,3,FALSE) -> 1.0809023 | K9: =IF(J9=70%,I9*70%,IF(AND(J9>=80%,J9<=90%),I9*80%,IF(AND(J9>=91%,J9<=95%),I9*90%,IF(J9=96%,I9*96%,IF(J9=97%,I9*97%,IF(J9=98%,I9*98%,IF(J9=99%,I9*99%,IF(J9>=100%,I9,0)))))))) -> 80000 | L9: =+O9*20% -> 80000 | M9: =+VLOOKUP(B9,'TD Supervisores Y Lideres Prom'!$B$20:$E$24,4,FALSE) -> 0.72472032 | N9: =+IF(M9=100%,L9,0) -> 0 | O9: 400000 | P9: =+O9 -> 400000 | Q9: Ingreso el 18 Agosto / Pago pagarantizado Sept | R9: =IF(E9>=60%,"SI","NO") -> SI
B10: Total general | F10: =+SUM(F7:F9) -> 720000 | H10: =+SUM(H7:H9) -> 624000 | I10: =+SUM(I7:I9) -> 240000 | K10: =+SUM(K7:K9) -> 216000 | L10: =+SUM(L7:L9) -> 240000 | N10: =+SUM(N7:N9) -> 0 | O10: =+SUM(O7:O9) -> 1200000 | P10: =+SUM(P7:P9) -> 1120000
Q12: CANT. | R12: =+COUNTIF(R16:R28,"si") -> 13
F14: TIENDA PERFECTA 60% - Se liquida a partir del 60% | I14: VENTAS 20% - Se liquida a partir del 70% | L14: FECHAS CORTAS & DEVOLUCIONES 20% - Se liquida cumpl al 100% | P14: =+SUBTOTAL(9,P16:P28) -> 3033748
B15: SUPERVISOR | C15: LLAVE 1 CAPTURA | D15: LLAVE 2 COBERTURA | E15: PROM. LLAVE | F15: VALOR COMISION TP | G15: % CUMPL. TP | H15: VALOR COMISION | I15: VALOR COMISION VENTAS | J15: % VENTAS | K15: VALOR COMISION | L15: VALOR COMISION X FC DV | M15: % FC & DV | N15: VALOR COMISION | O15: Valor Comision | P15: Valor a Pagar | Q15: Comentario | R15: Cumple Llaves
B16: GIL MARTINEZ JENNIFER STEFANNIE | C16: =+VLOOKUP(B16,'TD Supervisores Y Lideres Prom'!$B$27:$D$41,2,FALSE) -> 0.94895833 | D16: =+VLOOKUP(B16,'TD Supervisores Y Lideres Prom'!$B$27:$D$41,3,FALSE) -> 0.9828125 | E16: =+AVERAGE(C16:D16) -> 0.96588542 | F16: =+O16*60% -> 180000 | G16: =+VLOOKUP(B16,'TD Supervisores Y Lideres Prom'!$B$3:$C$17,2,FALSE) -> 0.92841435 | H16: =IF(G16>80%,F16*100%,IF(AND(G16>=60%,G16<=79%),F16*60%,0)) -> 180000 | I16: =+O16*20% -> 60000 | J16: =+VLOOKUP(B16,'TD Supervisores Y Lideres Prom'!$B$3:$D$17,3,FALSE) -> 1.076402 | K16: =IF(J16=70%,I16*70%,IF(AND(J16>=80%,J16<=90%),I16*80%,IF(AND(J16>=91%,J16<=95%),I16*90%,IF(J16=96%,I16*96%,IF(J16=97%,I16*97%,IF(J16=98%,I16*98%,IF(J16=99%,I16*99%,IF(J16>=100%,I16,0)))))))) -> 60000 | L16: =+O16*20% -> 60000 | M16: =+VLOOKUP(B16,'TD Supervisores Y Lideres Prom'!$B$3:$E$17,4,FALSE) -> 0.8703125 | N16: =+IF(M16=100%,L16,0) -> 0 | O16: 300000 | P16: =IF(R16="SI",SUM(H16,K16,N16),0) -> 240000 | R16: =IF(E16>=60%,"SI","NO") -> SI
B17: MELISA MARTINEZ | C17: =+VLOOKUP(B17,'TD Supervisores Y Lideres Prom'!$B$27:$D$41,2,FALSE) -> 0.97192982 | D17: =+VLOOKUP(B17,'TD Supervisores Y Lideres Prom'!$B$27:$D$41,3,FALSE) -> 1 | E17: =+AVERAGE(C17:D17) -> 0.98596491 | F17: =+O17*60% -> 180000 | G17: =+VLOOKUP(B17,'TD Supervisores Y Lideres Prom'!$B$3:$C$17,2,FALSE) -> 0.9237104 | H17: =IF(G17>80%,F17*100%,IF(AND(G17>=60%,G17<=79%),F17*60%,0)) -> 180000 | I17: =+O17*20% -> 60000 | J17: =+VLOOKUP(B17,'TD Supervisores Y Lideres Prom'!$B$3:$D$17,3,FALSE) -> 1.016199 | K17: =IF(J17=70%,I17*70%,IF(AND(J17>=80%,J17<=90%),I17*80%,IF(AND(J17>=91%,J17<=95%),I17*90%,IF(J17=96%,I17*96%,IF(J17=97%,I17*97%,IF(J17=98%,I17*98%,IF(J17=99%,I17*99%,IF(J17>=100%,I17,0)))))))) -> 60000 | L17: =+O17*20% -> 60000 | M17: =+VLOOKUP(B17,'TD Supervisores Y Lideres Prom'!$B$3:$E$17,4,FALSE) -> 1 | N17: =+IF(M17=100%,L17,0) -> 60000 | O17: 300000 | P17: =IF(R17="SI",SUM(H17,K17,N17),0) -> 300000 | R17: =IF(E17>=60%,"SI","NO") -> SI
B18: SUSANA SILVA MENDOZA | C18: =+VLOOKUP(B18,'TD Supervisores Y Lideres Prom'!$B$27:$D$41,2,FALSE) -> 0.95833333 | D18: =+VLOOKUP(B18,'TD Supervisores Y Lideres Prom'!$B$27:$D$41,3,FALSE) -> 0.96785714 | E18: =+AVERAGE(C18:D18) -> 0.96309524 | F18: =+O18*60% -> 180000 | G18: =+VLOOKUP(B18,'TD Supervisores Y Lideres Prom'!$B$3:$C$17,2,FALSE) -> 0.91865079 | H18: =IF(G18>80%,F18*100%,IF(AND(G18>=60%,G18<=79%),F18*60%,0)) -> 180000 | I18: =+O18*20% -> 60000 | J18: =+VLOOKUP(B18,'TD Supervisores Y Lideres Prom'!$B$3:$D$17,3,FALSE) -> 1.2615379 | K18: =IF(J18=70%,I18*70%,IF(AND(J18>=80%,J18<=90%),I18*80%,IF(AND(J18>=91%,J18<=95%),I18*90%,IF(J18=96%,I18*96%,IF(J18=97%,I18*97%,IF(J18=98%,I18*98%,IF(J18=99%,I18*99%,IF(J18>=100%,I18,0)))))))) -> 60000 | L18: =+O18*20% -> 60000 | M18: =+VLOOKUP(B18,'TD Supervisores Y Lideres Prom'!$B$3:$E$17,4,FALSE) -> 0.91964286 | N18: =+IF(M18=100%,L18,0) -> 0 | O18: 300000 | P18: =IF(R18="SI",SUM(H18,K18,N18),0) -> 240000 | R18: =IF(E18>=60%,"SI","NO") -> SI
B19: JUAN PABLO GIL ALMANZA | C19: =+VLOOKUP(B19,'TD Supervisores Y Lideres Prom'!$B$27:$D$41,2,FALSE) -> 0.99652778 | D19: =+VLOOKUP(B19,'TD Supervisores Y Lideres Prom'!$B$27:$D$41,3,FALSE) -> 1 | E19: =+AVERAGE(C19:D19) -> 0.99826389 | F19: =+O19*60% -> 180000 | G19: =+VLOOKUP(B19,'TD Supervisores Y Lideres Prom'!$B$3:$C$17,2,FALSE) -> 0.98833912 | H19: =IF(G19>80%,F19*100%,IF(AND(G19>=60%,G19<=79%),F19*60%,0)) -> 180000 | I19: =+O19*20% -> 60000 | J19: =+VLOOKUP(B19,'TD Supervisores Y Lideres Prom'!$B$3:$D$17,3,FALSE) -> 1.0212204 | K19: =IF(J19=70%,I19*70%,IF(AND(J19>=80%,J19<=90%),I19*80%,IF(AND(J19>=91%,J19<=95%),I19*90%,IF(J19=96%,I19*96%,IF(J19=97%,I19*97%,IF(J19=98%,I19*98%,IF(J19=99%,I19*99%,IF(J19>=100%,I19,0)))))))) -> 60000 | L19: =+O19*20% -> 60000 | M19: 0.97 | N19: =+IF(M19=100%,L19,0) -> 0 | O19: 300000 | P19: =IF(R19="SI",SUM(H19,K19,N19),0) -> 240000 | R19: =IF(E19>=60%,"SI","NO") -> SI
B20: PIÑEROS MONTAÑA LAURA ESTEPHANIA | C20: =+VLOOKUP(B20,'TD Supervisores Y Lideres Prom'!$B$27:$D$41,2,FALSE) -> 1 | D20: =+VLOOKUP(B20,'TD Supervisores Y Lideres Prom'!$B$27:$D$41,3,FALSE) -> 1 | E20: =+AVERAGE(C20:D20) -> 1 | F20: =+O20*60% -> 180000 | G20: =+VLOOKUP(B20,'TD Supervisores Y Lideres Prom'!$B$3:$C$17,2,FALSE) -> 0.97677962 | H20: =IF(G20>80%,F20*100%,IF(AND(G20>=60%,G20<=79%),F20*60%,0)) -> 180000 | I20: =+O20*20% -> 60000 | J20: =+VLOOKUP(B20,'TD Supervisores Y Lideres Prom'!$B$3:$D$17,3,FALSE) -> 1.0511249 | K20: =IF(J20=70%,I20*70%,IF(AND(J20>=80%,J20<=90%),I20*80%,IF(AND(J20>=91%,J20<=95%),I20*90%,IF(J20=96%,I20*96%,IF(J20=97%,I20*97%,IF(J20=98%,I20*98%,IF(J20=99%,I20*99%,IF(J20>=100%,I20,0)))))))) -> 60000 | L20: =+O20*20% -> 60000 | M20: =+VLOOKUP(B20,'TD Supervisores Y Lideres Prom'!$B$3:$E$17,4,FALSE) -> 0.85294118 | N20: =+IF(M20=100%,L20,0) -> 0 | O20: 300000 | P20: =IF(R20="SI",SUM(H20,K20,N20),0) -> 240000 | R20: =IF(E20>=60%,"SI","NO") -> SI
B21: MEJÍA BLANDÓN ASTRID KARINA | C21: =+VLOOKUP(B21,'TD Supervisores Y Lideres Prom'!$B$27:$D$41,2,FALSE) -> 0.91190853 | D21: =+VLOOKUP(B21,'TD Supervisores Y Lideres Prom'!$B$27:$D$41,3,FALSE) -> 0.9335258 | E21: =+AVERAGE(C21:D21) -> 0.92271716 | F21: =+O21*60% -> 180000 | G21: =+VLOOKUP(B21,'TD Supervisores Y Lideres Prom'!$B$3:$C$17,2,FALSE) -> 0.83148024 | H21: =IF(G21>80%,F21*100%,IF(AND(G21>=60%,G21<=79%),F21*60%,0)) -> 180000 | I21: =+O21*20% -> 60000 | J21: =+VLOOKUP(B21,'TD Supervisores Y Lideres Prom'!$B$3:$D$17,3,FALSE) -> 1.059624 | K21: =IF(J21=70%,I21*70%,IF(AND(J21>=80%,J21<=90%),I21*80%,IF(AND(J21>=91%,J21<=95%),I21*90%,IF(J21=96%,I21*96%,IF(J21=97%,I21*97%,IF(J21=98%,I21*98%,IF(J21=99%,I21*99%,IF(J21>=100%,I21,0)))))))) -> 60000 | L21: =+O21*20% -> 60000 | M21: =+VLOOKUP(B21,'TD Supervisores Y Lideres Prom'!$B$3:$E$17,4,FALSE) -> 0.85312654 | N21: =+IF(M21=100%,L21,0) -> 0 | O21: 300000 | P21: =IF(R21="SI",SUM(H21,K21,N21),0) -> 240000 | R21: =IF(E21>=60%,"SI","NO") -> SI
B22: PEREZ ZAGARRA AUGUSTO EDUARDO | C22: =+VLOOKUP(B22,'TD Supervisores Y Lideres Prom'!$B$27:$D$41,2,FALSE) -> 0.94542531 | D22: =+VLOOKUP(B22,'TD Supervisores Y Lideres Prom'!$B$27:$D$41,3,FALSE) -> 0.94385675 | E22: =+AVERAGE(C22:D22) -> 0.94464103 | F22: =+O22*60% -> 180000 | G22: =+VLOOKUP(B22,'TD Supervisores Y Lideres Prom'!$B$3:$C$17,2,FALSE) -> 0.81614188 | H22: =IF(G22>80%,F22*100%,IF(AND(G22>=60%,G22<=79%),F22*60%,0)) -> 180000 | I22: =+O22*20% -> 60000 | J22: 1 | K22: =IF(J22=70%,I22*70%,IF(AND(J22>=80%,J22<=90%),I22*80%,IF(AND(J22>=91%,J22<=95%),I22*90%,IF(J22=96%,I22*96%,IF(J22=97%,I22*97%,IF(J22=98%,I22*98%,IF(J22=99%,I22*99%,IF(J22>=100%,I22,0)))))))) -> 60000 | L22: =+O22*20% -> 60000 | M22: =+VLOOKUP(B22,'TD Supervisores Y Lideres Prom'!$B$3:$E$17,4,FALSE) -> 0.51912281 | N22: =+IF(M22=100%,L22,0) -> 0 | O22: 300000 | P22: =IF(R22="SI",SUM(H22,K22,N22),0) -> 240000 | R22: =IF(E22>=60%,"SI","NO") -> SI
B23: GONZALEZ BARRANTES EDWIN JESSID | C23: =+VLOOKUP(B23,'TD Supervisores Y Lideres Prom'!$B$27:$D$41,2,FALSE) -> 0.97476478 | D23: =+VLOOKUP(B23,'TD Supervisores Y Lideres Prom'!$B$27:$D$41,3,FALSE) -> 0.96919845 | E23: =+AVERAGE(C23:D23) -> 0.97198161 | F23: =+O23*60% -> 180000 | G23: =+VLOOKUP(B23,'TD Supervisores Y Lideres Prom'!$B$3:$C$17,2,FALSE) -> 0.89632471 | H23: =IF(G23>80%,F23*100%,IF(AND(G23>=60%,G23<=79%),F23*60%,0)) -> 180000 | I23: =+O23*20% -> 60000 | J23: =+VLOOKUP(B23,'TD Supervisores Y Lideres Prom'!$B$3:$D$17,3,FALSE) -> 1.0926129 | K23: =IF(J23=70%,I23*70%,IF(AND(J23>=80%,J23<=90%),I23*80%,IF(AND(J23>=91%,J23<=95%),I23*90%,IF(J23=96%,I23*96%,IF(J23=97%,I23*97%,IF(J23=98%,I23*98%,IF(J23=99%,I23*99%,IF(J23>=100%,I23,0)))))))) -> 60000 | L23: =+O23*20% -> 60000 | M23: 0.98 | N23: =+IF(M23=100%,L23,0) -> 0 | O23: 300000 | P23: =IF(R23="SI",SUM(H23,K23,N23),0) -> 240000 | R23: =IF(E23>=60%,"SI","NO") -> SI
B24: CAMPUZANO IRLET ANDREA | C24: =+VLOOKUP(B24,'TD Supervisores Y Lideres Prom'!$B$27:$D$41,2,FALSE) -> 0.96400401 | D24: =+VLOOKUP(B24,'TD Supervisores Y Lideres Prom'!$B$27:$D$41,3,FALSE) -> 0.96911765 | E24: =+AVERAGE(C24:D24) -> 0.96656083 | F24: =+O24*60% -> 180000 | G24: =+VLOOKUP(B24,'TD Supervisores Y Lideres Prom'!$B$3:$C$17,2,FALSE) -> 0.88866958 | H24: =IF(G24>80%,F24*100%,IF(AND(G24>=60%,G24<=79%),F24*60%,0)) -> 180000 | I24: =+O24*20% -> 60000 | J24: =+VLOOKUP(B24,'TD Supervisores Y Lideres Prom'!$B$3:$D$17,3,FALSE) -> 1.0799646 | K24: =IF(J24=70%,I24*70%,IF(AND(J24>=80%,J24<=90%),I24*80%,IF(AND(J24>=91%,J24<=95%),I24*90%,IF(J24=96%,I24*96%,IF(J24=97%,I24*97%,IF(J24=98%,I24*98%,IF(J24=99%,I24*99%,IF(J24>=100%,I24,0)))))))) -> 60000 | L24: =+O24*20% -> 60000 | M24: =+VLOOKUP(B24,'TD Supervisores Y Lideres Prom'!$B$3:$E$17,4,FALSE) -> 0.62376337 | N24: =+IF(M24=100%,L24,0) -> 0 | O24: 300000 | P24: =IF(R24="SI",SUM(H24,K24,N24),0) -> 240000 | R24: =IF(E24>=60%,"SI","NO") -> SI
B25: SÁNCHEZ ZAMBRANO LEIDY NICOLE VANESSA | C25: =+VLOOKUP(B25,'TD Supervisores Y Lideres Prom'!$B$27:$D$41,2,FALSE) -> 0.96398525 | D25: =+VLOOKUP(B25,'TD Supervisores Y Lideres Prom'!$B$27:$D$41,3,FALSE) -> 0.98823529 | E25: =+AVERAGE(C25:D25) -> 0.97611027 | F25: =+O25*60% -> 180000 | G25: =+VLOOKUP(B25,'TD Supervisores Y Lideres Prom'!$B$3:$C$17,2,FALSE) -> 0.93358847 | H25: =IF(G25>80%,F25*100%,IF(AND(G25>=60%,G25<=79%),F25*60%,0)) -> 180000 | I25: =+O25*20% -> 60000 | J25: =+VLOOKUP(B25,'TD Supervisores Y Lideres Prom'!$B$3:$D$17,3,FALSE) -> 0.96246619 | K25: =+I25*J25 -> 57747.971 | L25: =+O25*20% -> 60000 | M25: 0.81 | N25: =+IF(M25=100%,L25,0) -> 0 | O25: 300000 | P25: =IF(R25="SI",SUM(H25,K25,N25),0) -> 237747.97 | R25: =IF(E25>=60%,"SI","NO") -> SI
B26: OSSA TABARES JAZMIN BERNARDA | C26: =+VLOOKUP(B26,'TD Supervisores Y Lideres Prom'!$B$27:$D$41,2,FALSE) -> 0.96939988 | D26: =+VLOOKUP(B26,'TD Supervisores Y Lideres Prom'!$B$27:$D$41,3,FALSE) -> 0.97192513 | E26: =+AVERAGE(C26:D26) -> 0.97066251 | F26: =+O26*60% -> 180000 | G26: =+VLOOKUP(B26,'TD Supervisores Y Lideres Prom'!$B$3:$C$17,2,FALSE) -> 0.91319671 | H26: =IF(G26>80%,F26*100%,IF(AND(G26>=60%,G26<=79%),F26*60%,0)) -> 180000 | I26: =+O26*20% -> 60000 | J26: =+VLOOKUP(B26,'TD Supervisores Y Lideres Prom'!$B$3:$D$17,3,FALSE) -> 1.0183031 | K26: =IF(J26=70%,I26*70%,IF(AND(J26>=80%,J26<=90%),I26*80%,IF(AND(J26>=91%,J26<=95%),I26*90%,IF(J26=96%,I26*96%,IF(J26=97%,I26*97%,IF(J26=98%,I26*98%,IF(J26=99%,I26*99%,IF(J26>=100%,I26,0)))))))) -> 60000 | L26: =+O26*20% -> 60000 | M26: =+VLOOKUP(B26,'TD Supervisores Y Lideres Prom'!$B$3:$E$17,4,FALSE) -> 0.84581105 | N26: =+IF(M26=100%,L26,0) -> 0 | O26: 300000 | P26: =IF(R26="SI",SUM(H26,K26,N26),0) -> 240000 | R26: =IF(E26>=60%,"SI","NO") -> SI
B27: BOLAÑOS QUEVEDO ALEXIS | C27: =+VLOOKUP(B27,'TD Supervisores Y Lideres Prom'!$B$27:$D$41,2,FALSE) -> 0.94921105 | D27: =+VLOOKUP(B27,'TD Supervisores Y Lideres Prom'!$B$27:$D$41,3,FALSE) -> 0.94707429 | E27: =+AVERAGE(C27:D27) -> 0.94814267 | F27: =+O27*60% -> 180000 | G27: =+VLOOKUP(B27,'TD Supervisores Y Lideres Prom'!$B$3:$C$17,2,FALSE) -> 0.72334255 | H27: =IF(G27>80%,F27*100%,IF(AND(G27>=60%,G27<=79%),F27*60%,0)) -> 108000 | I27: =+O27*20% -> 60000 | J27: =+VLOOKUP(B27,'TD Supervisores Y Lideres Prom'!$B$3:$D$17,3,FALSE) -> 1.1272195 | K27: =IF(J27=70%,I27*70%,IF(AND(J27>=80%,J27<=90%),I27*80%,IF(AND(J27>=91%,J27<=95%),I27*90%,IF(J27=96%,I27*96%,IF(J27=97%,I27*97%,IF(J27=98%,I27*98%,IF(J27=99%,I27*99%,IF(J27>=100%,I27,0)))))))) -> 60000 | L27: =+O27*20% -> 60000 | M27: =+VLOOKUP(B27,'TD Supervisores Y Lideres Prom'!$B$3:$E$17,4,FALSE) -> 0.77506575 | N27: =+IF(M27=100%,L27,0) -> 0 | O27: 300000 | P27: =IF(R27="SI",SUM(H27,K27,N27),0) -> 168000 | R27: =IF(E27>=60%,"SI","NO") -> SI
B28: MARTINEZ VARGAS CHRISTAN RICARDO | C28: =+VLOOKUP(B28,'TD Supervisores Y Lideres Prom'!$B$27:$D$41,2,FALSE) -> 0.94012099 | D28: =+VLOOKUP(B28,'TD Supervisores Y Lideres Prom'!$B$27:$D$41,3,FALSE) -> 0.9475802 | E28: =+AVERAGE(C28:D28) -> 0.94385059 | F28: =+O28*60% -> 180000 | G28: =+VLOOKUP(B28,'TD Supervisores Y Lideres Prom'!$B$3:$C$17,2,FALSE) -> 0.71943788 | H28: =IF(G28>80%,F28*100%,IF(AND(G28>=60%,G28<=79%),F28*60%,0)) -> 108000 | I28: =+O28*20% -> 60000 | J28: =+VLOOKUP(B28,'TD Supervisores Y Lideres Prom'!$B$3:$D$17,3,FALSE) -> 1.0353063 | K28: =IF(J28=70%,I28*70%,IF(AND(J28>=80%,J28<=90%),I28*80%,IF(AND(J28>=91%,J28<=95%),I28*90%,IF(J28=96%,I28*96%,IF(J28=97%,I28*97%,IF(J28=98%,I28*98%,IF(J28=99%,I28*99%,IF(J28>=100%,I28,0)))))))) -> 60000 | L28: =+O28*20% -> 60000 | M28: =+VLOOKUP(B28,'TD Supervisores Y Lideres Prom'!$B$3:$E$17,4,FALSE) -> 0.75203408 | N28: =+IF(M28=100%,L28,0) -> 0 | O28: 300000 | P28: =IF(R28="SI",SUM(H28,K28,N28),0) -> 168000 | R28: =IF(E28>=60%,"SI","NO") -> SI
B29: Total general | F29: =+SUM(F16:F28) -> 2340000 | H29: =+SUM(H16:H28) -> 2196000 | I29: =+SUM(I16:I28) -> 780000 | K29: =+SUM(K16:K28) -> 777747.97 | L29: =+SUM(L16:L28) -> 780000 | N29: =+SUM(N16:N28) -> 60000 | O29: =+SUM(O16:O28) -> 3900000 | P29: =+SUM(P16:P28) -> 3033748
F33: TIENDA PERFECTA 60% - Se liquida a partir del 80% | I33: VENTAS 20% - Se liquida a partir del 80% | L33: FECHAS CORTAS & DEVOLUCIONES 20% - Se liquida cumpl al 100% | P33: =+SUBTOTAL(9,P35:P35) -> 320000 | R33: 1
B34: FORMADORA | C34: LLAVE 1 CAPTURA | D34: LLAVE 2 COBERTURA | E34: PROM. LLAVE | F34: VALOR COMISION TP | G34: % CUMPL. TP | H34: VALOR COMISION | I34: VALOR COMISION VENTAS | J34: % VENTAS | K34: VALOR COMISION | L34: VALOR COMISION X FC DV | M34: % FC & DV | N34: VALOR COMISION | O34: Valor Comision | P34: Valor a Pagar | Q34: Comentario | R34: Cumple Llaves
B35: SUSAN JULIETH CASTILLO PARRA | C35: =+C7 -> 0.97557689 | D35: =+D7 -> 0.98738761 | E35: =+E7 -> 0.98148225 | F35: =+F7 -> 240000 | G35: =+G7 -> 0.93861048 | H35: =+H7 -> 240000 | I35: =+I7 -> 80000 | J35: =+J7 -> 1.0805537 | ... N35: =+N7 -> 0 | O35: 250000 | P35: =+N35+K35+H35 -> 320000 | R35: =IF(E35>=60%,"SI","NO") -> SI
B36: Total general | F36: =+SUM(F35:F35) -> 240000 | H36: =+SUM(H35:H35) -> 240000 | I36: =+SUM(I35:I35) -> 80000 | K36: =+SUM(K35:K35) -> 80000 | L36: =+SUM(L35:L35) -> 80000 | N36: =+SUM(N35:N35) -> 0 | O36: =+SUM(O35:O35) -> 250000 | P36: =+SUM(P35:P35) -> 320000

Sheet TD Supervisores Y Lideres Prom
B2: SUPERVISORES
B3: COORDINADOR | C3: % Cumplimiento TP | D3: % Cumplimiento Ventas | E3: % Cumplimiento FC & DV | F3: Valor Comision
B4: GIL MARTINEZ JENNIFER STEFANNIE | C4: 0.92841435 | D4: 1.076402 | E4: 0.8703125 | F4: 300000
B5: MELISA MARTINEZ | C5: 0.9237104 | D5: 1.016199 | E5: 1 | F5: 300000
B6: SUSANA SILVA MENDOZA | C6: 0.91865079 | D6: 1.2615379 | E6: 0.91964286 | F6: 300000
B7: JUAN PABLO GIL ALMANZA | C7: 0.98833912 | D7: 1.0212204 | E7: 0.87326389 | F7: 300000
B8: PIÑEROS MONTAÑA LAURA ESTEPHANIA | C8: 0.97677962 | D8: 1.0511249 | E8: 0.85294118 | F8: 300000
B9: MEJÍA BLANDÓN ASTRID KARINA | C9: 0.83148024 | D9: 1.059624 | E9: 0.85312654 | F9: 300000
B10: PEREZ ZAGARRA AUGUSTO EDUARDO | C10: 0.81614188 | D10: 0.99506478 | E10: 0.51912281 | F10: 300000
B11: GONZALEZ BARRANTES EDWIN JESSID | C11: 0.89632471 | D11: 1.0926129 | E11: 0.83781872 | F11: 300000
B12: CAMPUZANO IRLET ANDREA | C12: 0.88866958 | D12: 1.0799646 | E12: 0.62376337 | F12: 300000
B13: SÁNCHEZ ZAMBRANO LEIDY NICOLE VANESSA | C13: 0.93358847 | D13: 0.96246619 | E13: 0.96532177 | F13: 300000
B14: OSSA TABARES JAZMIN BERNARDA | C14: 0.91319671 | D14: 1.0183031 | E14: 0.84581105 | F14: 300000
B15: BOLAÑOS QUEVEDO ALEXIS | C15: 0.72334255 | D15: 1.1272195 | E15: 0.77506575 | F15: 300000
B16: MARTINEZ VARGAS CHRISTAN RICARDO | C16: 0.71943788 | D16: 1.0353063 | E16: 0.75203408 | F16: 300000
B17: Total general | C17: 0.88882836 | D17: 1.0597394 | E17: 0.84028503 | F17: =+SUM(F4:F16) -> 3900000
B19: LIDERES
B20: COORDINADOR | C20: Promedio de % Cumplimiento TP | D20: Promedio de % Cumplimiento Ventas | E20: Promedio de % Cumplimiento FC & DV | F20: Valor Comision
B21: ANYI MAYERLIE ORJUELA | C21: 0.93861048 | D21: 1.0805537 | E21: 0.89409233 | F21: 400000
B22: OSPINO ARAUJO ALEXANDER | C22: 0.87800853 | D22: 1.0064851 | E22: 0.81827385 | F22: 400000
B23: NATHALY AGUILAR | C23: 0.76785671 | D23: 1.0809023 | E23: 0.72472032 | F23: 400000
B24: Total general | C24: 0.88882836 | D24: 1.0597394 | E24: 0.84028503
B26: SUPERVISORES
B27: COORDINADOR | C27: Promedio de % Cumpl. Captura | D27: Promedio de % Cumplimiento Cobertura
B28: GIL MARTINEZ JENNIFER STEFANNIE | C28: 0.94895833 | D28: 0.9828125
B29: MELISA MARTINEZ | C29: 0.97192982 | D29: 1
B30: SUSANA SILVA MENDOZA | C30: 0.95833333 | D30: 0.96785714
B31: JUAN PABLO GIL ALMANZA | C31: 0.99652778 | D31: 1
B32: PIÑEROS MONTAÑA LAURA ESTEPHANIA | C32: 1 | D32: 1
B33: MEJÍA BLANDÓN ASTRID KARINA | C33: 0.91190853 | D33: 0.9335258
B34: PEREZ ZAGARRA AUGUSTO EDUARDO | C34: 0.94542531 | D34: 0.94385675
B35: GONZALEZ BARRANTES EDWIN JESSID | C35: 0.97476478 | D35: 0.96919845
B36: CAMPUZANO IRLET ANDREA | C36: 0.96400401 | D36: 0.96911765
B37: SÁNCHEZ ZAMBRANO LEIDY NICOLE VANESSA | C37: 0.96398525 | D37: 0.98823529
B38: OSSA TABARES JAZMIN BERNARDA | C38: 0.96939988 | D38: 0.97192513
B39: BOLAÑOS QUEVEDO ALEXIS | C39: 0.94921105 | D39: 0.94707429
... B41: Total general | C41: 0.96277135 | D41: 0.97348947
B43: SUPERVISORES
B44: COORDINADOR | C44: Promedio de % Cumpl. Captura | D44: Promedio de % Cumplimiento Cobertura
B45: ANYI MAYERLIE ORJUELA | C45: 0.97557689 | D45: 0.98738761
B46: OSPINO ARAUJO ALEXANDER | C46: 0.94750086 | D46: 0.96118796
B47: NATHALY AGUILAR | C47: 0.95003768 | D47: 0.95338013
B48: Total general | C48: 0.96277135 | D48: 0.97348947

Sheet Liquidacion Comision Septiembre
Y1: SI | Z1: =+COUNTIF(Y6:Y193,Y1) -> 188 | AA1: GANA REALMENTE | AB1: 187
B2: LIQUIDACION SEPTIEMBRE | Y2: Equipo ganador | Z2: =+Z1/188 -> 1 | AB2: =+AB1/188 -> 0.99468085
H3: LLAVE | J3: LLAVE | M3: 0.6 | Q3: 0.2 | U3: 0.2
G4: 250000 | H4: CAPTURA DE INFORMACION | M4: TIENDA PERFECTA | Q4: VENTAS | U4: DEVOLUCIONES & FECHAS CORTAS | Z4: =+SUBTOTAL(9,Z6:Z193) -> 39099920
B5: Regional | C5: RUTA | D5: Lider Alqueria | E5: Lider | F5: Supervisor | G5: Valor Comision | H5: % Cumpl. Captura | I5: Categoria Efec 60% | J5: % Cumplimiento Cobertura | K5: Categoria Efec 60% | L5: Promedio Llaves | M5: Valor Comision TP | N5: % Cumplimiento TP | O5: Categoria Efec >60% | P5: $ Liquidar | Q5: Valor Comision Ventas | R5: % Cumplimiento Ventas | S5: Categoria Efec | T5: $ Liquidar | U5: Valor Comision FC y Dev | V5: % Cumplimiento FC & DV | W5: Categoria Efec | X5: $ Liquidar | Y5: Corresponde Comision | Z5: Valor total A Pagar Real | AA5: Observaciones
B6: REGIONAL BOGOTA | C6: CTR_1 | D6: PAULA RUBIO | E6: ANYI MAYERLIE ORJUELA | F6: SUSANA SILVA MENDOZA | G6: =IF(L6>=80%,250000,IF(AND(L6>=60%,L6<80%),150000,0)) -> 250000 | H6: =+VLOOKUP(C6,Indicadores!B:C,2,FALSE) -> 1 | I6: =IF(H6>=60%,"Cumple","No Cumple") -> Cumple | J6: =+VLOOKUP(C6,Indicadores!B:F,5,FALSE) -> 1 | K6: =IF(J6>=60%,"Cumple","No Cumple") -> Cumple | L6: =+AVERAGE(H6,J6) -> 1 | M6: =+G6*$M$3 -> 150000 | N6: =+VLOOKUP(C6,Indicadores!B:M,12,FALSE) -> 1 | O6: =IF(N6>=60%,"Cumple","No Cumple") -> Cumple | P6: =IF(N6>80%,M6*100%,IF(AND(N6>=60%,N6<=79%),M6*60%,0)) -> 150000 | Q6: =+$G$6*$Q$3 -> 50000 | R6: =+IFERROR(VLOOKUP(C6,Indicadores!B:N,13,FALSE),0%) -> 1.0926436 | S6: =IF(R6>=70%,"Cumple","No Cumple") -> Cumple | T6: =IF(R6=80%,Q6*70%,IF(AND(R6>=81%,R6<=90%),Q6*80%,IF(AND(R6>=91%,R6<=95%),Q6*90%,IF(R6=96%,Q6*96%,IF(R6=97%,Q6*97%,IF(R6=98%,Q6*98%,IF(R6=99%,Q6*99%,IF(R6>=100%,Q6,0)))))))) -> 50000 | U6: =+G6*$U$3 -> 50000 | V6: =+VLOOKUP(C6,Indicadores!B:S,18,FALSE) -> 1 | W6: =IF(V6>=100%,"Cumple","No Cumple") -> Cumple | X6: =+IF(V6=100%,U6,0) -> 50000 | Y6: =IF(L6>=60%,"SI","NO") -> SI | Z6: =+IF(Y6="SI",P6+T6+X6,0) -> 250000
B7: REGIONAL BOGOTA | C7: CTR_10 | D7: PAULA RUBIO | E7: ANYI MAYERLIE ORJUELA | F7: SUSANA SILVA MENDOZA | G7: =IF(L7>=80%,250000,IF(AND(L7>=60%,L7<80%),150000,0)) -> 250000 | H7: =+VLOOKUP(C7,Indicadores!B:C,2,FALSE) -> 1 | I7: =IF(H7>=60%,"Cumple","No Cumple") -> Cumple | J7: =+VLOOKUP(C7,Indicadores!B:F,5,FALSE) -> 1 | K7: =IF(J7>=60%,"Cumple","No Cumple") -> Cumple | L7: =+AVERAGE(H7,J7) -> 1 | M7: =+G7*$M$3 -> 150000 | N7: =+VLOOKUP(C7,Indicadores!B:M,12,FALSE) -> 1 | O7: =IF(N7>=60%,"Cumple","No Cumple") -> Cumple | P7: =IF(N7>80%,M7*100%,IF(AND(N7>=60%,N7<=79%),M7*60%,0)) -> 150000 | Q7: =+$G$6*$Q$3 -> 50000 | R7: =+IFERROR(VLOOKUP(C7,Indicadores!B:N,13,FALSE),0%) -> 2.6859172 | S7: =IF(R7>=70%,"Cumple","No Cumple") -> Cumple | T7: =IF(R7=80%,Q7*70%,IF(AND(R7>=81%,R7<=90%),Q7*80%,IF(AND(R7>=91%,R7<=95%),Q7*90%,IF(R7=96%,Q7*96%,IF(R7=97%,Q7*97%,IF(R7=98%,Q7*98%,IF(R7=99%,Q7*99%,IF(R7>=100%,Q7,0)))))))) -> 50000 | U7: =+G7*$U$3 -> 50000 | V7: =+VLOOKUP(C7,Indicadores!B:S,18,FALSE) -> 1 | W7: =IF(V7>=100%,"Cumple","No Cumple") -> Cumple | X7: =+IF(V7=100%,U7,0) -> 50000 | Y7: =IF(L7>=60%,"SI","NO") -> SI | Z7: =+IF(Y7="SI",P7+T7+X7,0) -> 250000
B8: REGIONAL BOGOTA | C8: CTR_11 | D8: PAULA RUBIO | E8: ANYI MAYERLIE ORJUELA | F8: SUSANA SILVA MENDOZA | G8: =IF(L8>=80%,250000,IF(AND(L8>=60%,L8<80%),150000,0)) -> 250000 | H8: =+VLOOKUP(C8,Indicadores!B:C,2,FALSE) -> 0.91666667 | I8: =IF(H8>=60%,"Cumple","No Cumple") -> Cumple | J8: =+VLOOKUP(C8,Indicadores!B:F,5,FALSE) -> 0.91666667 | K8: =IF(J8>=60%,"Cumple","No Cumple") -> Cumple | L8: =+AVERAGE(H8,J8) -> 0.91666667 | M8: =+G8*$M$3 -> 150000 | N8: =+VLOOKUP(C8,Indicadores!B:M,12,FALSE) -> 0.94444444 | O8: =IF(N8>=60%,"Cumple","No Cumple") -> Cumple | P8: =IF(N8>80%,M8*100%,IF(AND(N8>=60%,N8<=79%),M8*60%,0)) -> 150000 | Q8: =+$G$6*$Q$3 -> 50000 | R8: =+IFERROR(VLOOKUP(C8,Indicadores!B:N,13,FALSE),0%) -> 1.1306234 | S8: =IF(R8>=70%,"Cumple","No Cumple") -> Cumple | T8: =IF(R8=80%,Q8*70%,IF(AND(R8>=81%,R8<=90%),Q8*80%,IF(AND(R8>=91%,R8<=95%),Q8*90%,IF(R8=96%,Q8*96%,IF(R8=97%,Q8*97%,IF(R8=98%,Q8*98%,IF(R8=99%,Q8*99%,IF(R8>=100%,Q8,0)))))))) -> 50000 | U8: =+G8*$U$3 -> 50000 | V8: =+VLOOKUP(C8,Indicadores!B:S,18,FALSE) -> 0.95833333 | W8: =IF(V8>=100%,"Cumple","No Cumple") -> No Cumple | X8: =+IF(V8=100%,U8,0) -> 0 | Y8: =IF(L8>=60%,"SI","NO") -> SI | Z8: =+IF(Y8="SI",P8+T8+X8,0) -> 200000
B9: REGIONAL BOGOTA | C9: CTR_12 | D9: PAULA RUBIO | E9: ANYI MAYERLIE ORJUELA | F9: SUSANA SILVA MENDOZA | G9: =IF(L9>=80%,250000,IF(AND(L9>=60%,L9<80%),150000,0)) -> 250000 | H9: =+VLOOKUP(C9,Indicadores!B:C,2,FALSE) -> 1 | I9: =IF(H9>=60%,"Cumple","No Cumple") -> Cumple | J9: =+VLOOKUP(C9,Indicadores!B:F,5,FALSE) -> 1 | K9: =IF(J9>=60%,"Cumple","No Cumple") -> Cumple | L9: =+AVERAGE(H9,J9) -> 1 | M9: =+G9*$M$3 -> 150000 | N9: =+VLOOKUP(C9,Indicadores!B:M,12,FALSE) -> 1 | O9: =IF(N9>=60%,"Cumple","No Cumple") -> Cumple | P9: =IF(N9>80%,M9*100%,IF(AND(N9>=60%,N9<=79%),M9*60%,0)) -> 150000 | Q9: =+$G$6*$Q$3 -> 50000 | R9: =+IFERROR(VLOOKUP(C9,Indicadores!B:N,13,FALSE),0%) -> 1.2889294 | S9: =IF(R9>=70%,"Cumple","No Cumple") -> Cumple | T9: =IF(R9=80%,Q9*70%,IF(AND(R9>=81%,R9<=90%),Q9*80%,IF(AND(R9>=91%,R9<=95%),Q9*90%,IF(R9=96%,Q9*96%,IF(R9=97%,Q9*97%,IF(R9=98%,Q9*98%,IF(R9=99%,Q9*99%,IF(R9>=100%,Q9,0)))))))) -> 50000 | U9: =+G9*$U$3 -> 50000 | V9: =+VLOOKUP(C9,Indicadores!B:S,18,FALSE) -> 1 | W9: =IF(V9>=100%,"Cumple","No Cumple") -> Cumple | X9: =+IF(V9=100%,U9,0) -> 50000 | Y9: =IF(L9>=60%,"SI","NO") -> SI | Z9: =+IF(Y9="SI",P9+T9+X9,0) -> 250000
B10: REGIONAL BOGOTA | C10: CTR_13 | D10: ALEJANDRO RODRIGUEZ | E10: ANYI MAYERLIE ORJUELA | F10: SUSANA SILVA MENDOZA | G10: =IF(L10>=80%,250000,IF(AND(L10>=60%,L10<80%),150000,0)) -> 250000 | H10: =+VLOOKUP(C10,Indicadores!B:C,2,FALSE) -> 1 | I10: =IF(H10>=60%,"Cumple","No Cumple") -> Cumple | J10: =+VLOOKUP(C10,Indicadores!B:F,5,FALSE) -> 1 | K10: =IF(J10>=60%,"Cumple","No Cumple") -> Cumple | L10: =+AVERAGE(H10,J10) -> 1 | M10: =+G10*$M$3 -> 150000 | N10: =+VLOOKUP(C10,Indicadores!B:M,12,FALSE) -> 1 | O10: =IF(N10>=60%,"Cumple","No Cumple") -> Cumple | P10: =IF(N10>80%,M10*100%,IF(AND(N10>=60%,N10<=79%),M10*60%,0)) -> 150000 | Q10: =+$G$6*$Q$3 -> 50000 | R10: =+IFERROR(VLOOKUP(C10,Indicadores!B:N,13,FALSE),0%) -> 1.1378459 | S10: =IF(R10>=70%,"Cumple","No Cumple") -> Cumple | T10: =IF(R10=80%,Q10*70%,IF(AND(R10>=81%,R10<=90%),Q10*80%,IF(AND(R10>=91%,R10<=95%),Q10*90%,IF(R10=96%,Q10*96%,IF(R10=97%,Q10*97%,IF(R10=98%,Q10*98%,IF(R10=99%,Q10*99%,IF(R10>=100%,Q10,0)))))))) -> 50000 | U10: =+G10*$U$3 -> 50000 | V10: =+VLOOKUP(C10,Indicadores!B:S,18,FALSE) -> 1 | W10: =IF(V10>=100%,"Cumple","No Cumple") -> Cumple | X10: =+IF(V10=100%,U10,0) -> 50000 | Y10: =IF(L10>=60%,"SI","NO") -> SI | Z10: =+IF(Y10="SI",P10+T10+X10,0) -> 250000
B11: REGIONAL BOGOTA | C11: CTR_14 | D11: PAULA RUBIO | E11: ANYI MAYERLIE ORJUELA | F11: SUSANA SILVA MENDOZA | G11: =IF(L11>=80%,250000,IF(AND(L11>=60%,L11<80%),150000,0)) -> 250000 | H11: =+VLOOKUP(C11,Indicadores!B:C,2,FALSE) -> 1 | I11: =IF(H11>=60%,"Cumple","No Cumple") -> Cumple | J11: =+VLOOKUP(C11,Indicadores!B:F,5,FALSE) -> 1 | K11: =IF(J11>=60%,"Cumple","No Cumple") -> Cumple | L11: =+AVERAGE(H11,J11) -> 1 | M11: =+G11*$M$3 -> 150000 | N11: =+VLOOKUP(C11,Indicadores!B:M,12,FALSE) -> 0.88888889 | O11: =IF(N11>=60%,"Cumple","No Cumple") -> Cumple | P11: =IF(N11>80%,M11*100%,IF(AND(N11>=60%,N11<=79%),M11*60%,0)) -> 150000 | Q11: =+$G$6*$Q$3 -> 50000 | R11: =+IFERROR(VLOOKUP(C11,Indicadores!B:N,13,FALSE),0%) -> 1.1051651 | S11: =IF(R11>=70%,"Cumple","No Cumple") -> Cumple | T11: =IF(R11=80%,Q11*70%,IF(AND(R11>=81%,R11<=90%),Q11*80%,IF(AND(R11>=91%,R11<=95%),Q11*90%,IF(R11=96%,Q11*96%,IF(R11=97%,Q11*97%,IF(R11=98%,Q11*98%,IF(R11=99%,Q11*99%,IF(R11>=100%,Q11,0)))))))) -> 50000 | U11: =+G11*$U$3 -> 50000 | V11: =+VLOOKUP(C11,Indicadores!B:S,18,FALSE) -> 0.5 | W11: =IF(V11>=100%,"Cumple","No Cumple") -> No Cumple | X11: =+IF(V11=100%,U11,0) -> 0 | Y11: =IF(L11>=60%,"SI","NO") -> SI | Z11: =+IF(Y11="SI",P11+T11+X11,0) -> 200000
B12: REGIONAL BOGOTA | C12: CTR_15 | D12: PAULA RUBIO | E12: ANYI MAYERLIE ORJUELA | F12: SUSANA SILVA MENDOZA | G12: =IF(L12>=80%,250000,IF(AND(L12>=60%,L12<80%),150000,0)) -> 250000 | H12: =+VLOOKUP(C12,Indicadores!B:C,2,FALSE) -> 1 | I12: =IF(H12>=60%,"Cumple","No Cumple") -> Cumple | J12: =+VLOOKUP(C12,Indicadores!B:F,5,FALSE) -> 1 | K12: =IF(J12>=60%,"Cumple","No Cumple") -> Cumple | L12: =+AVERAGE(H12,J12) -> 1 | M12: =+G12*$M$3 -> 150000 | N12: =+VLOOKUP(C12,Indicadores!B:M,12,FALSE) -> 0.95555556 | O12: =IF(N12>=60%,"Cumple","No Cumple") -> Cumple | P12: =IF(N12>80%,M12*100%,IF(AND(N12>=60%,N12<=79%),M12*60%,0)) -> 150000 | Q12: =+$G$6*$Q$3 -> 50000 | R12: =+IFERROR(VLOOKUP(C12,Indicadores!B:N,13,FALSE),0%) -> 1.1243968 | S12: =IF(R12>=70%,"Cumple","No Cumple") -> Cumple | T12: =IF(R12=80%,Q12*70%,IF(AND(R12>=81%,R12<=90%),Q12*80%,IF(AND(R12>=91%,R12<=95%),Q12*90%,IF(R12=96%,Q12*96%,IF(R12=97%,Q12*97%,IF(R12=98%,Q12*98%,IF(R12=99%,Q12*99%,IF(R12>=100%,Q12,0)))))))) -> 50000 | U12: =+G12*$U$3 -> 50000 | V12: =+VLOOKUP(C12,Indicadores!B:S,18,FALSE) -> 0.5 | W12: =IF(V12>=100%,"Cumple","No Cumple") -> No Cumple | X12: =+IF(V12=100%,U12,0) -> 0 | Y12: =IF(L12>=60%,"SI","NO") -> SI | Z12: =+IF(Y12="SI",P12+T12+X12,0) -> 200000
B13: REGIONAL BOGOTA | C13: CTR_16 | D13: PAULA RUBIO | E13: ANYI MAYERLIE ORJUELA | F13: SUSANA SILVA MENDOZA | G13: =IF(L13>=80%,250000,IF(AND(L13>=60%,L13<80%),150000,0)) -> 250000 | H13: =+VLOOKUP(C13,Indicadores!B:C,2,FALSE) -> 1 | I13: =IF(H13>=60%,"Cumple","No Cumple") -> Cumple | J13: =+VLOOKUP(C13,Indicadores!B:F,5,FALSE) -> 1 | K13: =IF(J13>=60%,"Cumple","No Cumple") -> Cumple | L13: =+AVERAGE(H13,J13) -> 1 | M13: =+G13*$M$3 -> 150000 | N13: =+VLOOKUP(C13,Indicadores!B:M,12,FALSE) -> 1 | O13: =IF(N13>=60%,"Cumple","No Cumple") -> Cumple | P13: =IF(N13>80%,M13*100%,IF(AND(N13>=60%,N13<=79%),M13*60%,0)) -> 150000 | Q13: =+$G$6*$Q$3 -> 50000 | R13: =+IFERROR(VLOOKUP(C13,Indicadores!B:N,13,FALSE),0%) -> 1.183968 | S13: =IF(R13>=70%,"Cumple","No Cumple") -> Cumple | T13: =IF(R13=80%,Q13*70%,IF(AND(R13>=81%,R13<=90%),Q13*80%,IF(AND(R13>=91%,R13<=95%),Q13*90%,IF(R13=96%,Q13*96%,IF(R13=97%,Q13*97%,IF(R13=98%,Q13*98%,IF(R13=99%,Q13*99%,IF(R13>=100%,Q13,0)))))))) -> 50000 | U13: =+G13*$U$3 -> 50000 | V13: =+VLOOKUP(C13,Indicadores!B:S,18,FALSE) -> 1 | W13: =IF(V13>=100%,"Cumple","No Cumple") -> Cumple | X13: =+IF(V13=100%,U13,0) -> 50000 | Y13: =IF(L13>=60%,"SI","NO") -> SI | Z13: =+IF(Y13="SI",P13+T13+X13,0) -> 250000
B14: REGIONAL BOGOTA | C14: CTR_2 | D14: FANNY FERNANDEZ | E14: ANYI MAYERLIE ORJUELA | F14: GIL MARTINEZ JENNIFER STEFANNIE | G14: =IF(L14>=80%,250000,IF(AND(L14>=60%,L14<80%),150000,0)) -> 250000 | H14: =+VLOOKUP(C14,Indicadores!B:C,2,FALSE) -> 1 | I14: =IF(H14>=60%,"Cumple","No Cumple") -> Cumple | J14: =+VLOOKUP(C14,Indicadores!B:F,5,FALSE) -> 1 | K14: =IF(J14>=60%,"Cumple","No Cumple") -> Cumple | L14: =+AVERAGE(H14,J14) -> 1 | M14: =+G14*$M$3 -> 150000 | N14: =+VLOOKUP(C14,Indicadores!B:M,12,FALSE) -> 1 | O14: =IF(N14>=60%,"Cumple","No Cumple") -> Cumple | P14: =IF(N14>80%,M14*100%,IF(AND(N14>=60%,N14<=79%),M14*60%,0)) -> 150000 | Q14: =+$G$6*$Q$3 -> 50000 | R14: =+IFERROR(VLOOKUP(C14,Indicadores!B:N,13,FALSE),0%) -> 1.1922166 | S14: =IF(R14>=70%,"Cumple","No Cumple") -> Cumple | T14: =IF(R14=80%,Q14*70%,IF(AND(R14>=81%,R14<=90%),Q14*80%,IF(AND(R14>=91%,R14<=95%),Q14*90%,IF(R14=96%,Q14*96%,IF(R14=97%,Q14*97%,IF(R14=98%,Q14*98%,IF(R14=99%,Q14*99%,IF(R14>=100%,Q14,0)))))))) -> 50000 | U14: =+G14*$U$3 -> 50000 | V14: =+VLOOKUP(C14,Indicadores!B:S,18,FALSE) -> 1 | W14: =IF(V14>=100%,"Cumple","No Cumple") -> Cumple | X14: =+IF(V14=100%,U14,0) -> 50000 | Y14: =IF(L14>=60%,"SI","NO") -> SI | Z14: =+IF(Y14="SI",P14+T14+X14,0) -> 250000
B15: REGIONAL BOGOTA | C15: CTR_3 | D15: FANNY FERNANDEZ | E15: ANYI MAYERLIE ORJUELA | F15: GIL MARTINEZ JENNIFER STEFANNIE | G15: =IF(L15>=80%,250000,IF(AND(L15>=60%,L15<80%),150000,0)) -> 150000 | H15: =+VLOOKUP(C15,Indicadores!B:C,2,FALSE) -> 0.33333333 | I15: =IF(H15>=60%,"Cumple","No Cumple") -> No Cumple | J15: =+VLOOKUP(C15,Indicadores!B:F,5,FALSE) -> 1 | K15: =IF(J15>=60%,"Cumple","No Cumple") -> Cumple | L15: =+AVERAGE(H15,J15) -> 0.66666667 | M15: =+G15*$M$3 -> 90000 | N15: =+VLOOKUP(C15,Indicadores!B:M,12,FALSE) -> 0.66666667 | O15: =IF(N15>=60%,"Cumple","No Cumple") -> Cumple | P15: =IF(N15>80%,M15*100%,IF(AND(N15>=60%,N15<=79%),M15*60%,0)) -> 54000 | Q15: =+$G$6*$Q$3 -> 50000 | R15: 1.1922 | S15: =IF(R15>=70%,"Cumple","No Cumple") -> Cumple | T15: =IF(R15=80%,Q15*70%,IF(AND(R15>=81%,R15<=90%),Q15*80%,IF(AND(R15>=91%,R15<=95%),Q15*90%,IF(R15=96%,Q15*96%,IF(R15=97%,Q15*97%,IF(R15=98%,Q15*98%,IF(R15=99%,Q15*99%,IF(R15>=100%,Q15,0)))))))) -> 50000 | U15: =+G15*$U$3 -> 30000 | V15: =+VLOOKUP(C15,Indicadores!B:S,18,FALSE) -> 1 | W15: =IF(V15>=100%,"Cumple","No Cumple") -> Cumple | X15: =+IF(V15=100%,U15,0) -> 30000 | Y15: =IF(L15>=60%,"SI","NO") -> SI | Z15: =+IF(Y15="SI",P15+T15+X15,0) -> 134000
B16: REGIONAL BOGOTA | C16: CTR_4 | D16: CAMILO RINCON | E16: ANYI MAYERLIE ORJUELA | F16: SUSANA SILVA MENDOZA | G16: =IF(L16>=80%,250000,IF(AND(L16>=60%,L16<80%),150000,0)) -> 250000 | H16: =+VLOOKUP(C16,Indicadores!B:C,2,FALSE) -> 1 | I16: =IF(H16>=60%,"Cumple","No Cumple") -> Cumple | J16: =+VLOOKUP(C16,Indicadores!B:F,5,FALSE) -> 1 | K16: =IF(J16>=60%,"Cumple","No Cumple") -> Cumple | L16: =+AVERAGE(H16,J16) -> 1 | M16: =+G16*$M$3 -> 150000 | N16: =+VLOOKUP(C16,Indicadores!B:M,12,FALSE) -> 0.58333333 | O16: =IF(N16>=60%,"Cumple","No Cumple") -> No Cumple | P16: =IF(N16>80%,M16*100%,IF(AND(N16>=60%,N16<=79%),M16*60%,0)) -> 0 | Q16: =+$G$6*$Q$3 -> 50000 | R16: =+IFERROR(VLOOKUP(C16,Indicadores!B:N,13,FALSE),0%) -> 1.5777985 | S16: =IF(R16>=70%,"Cumple","No Cumple") -> Cumple | T16: =IF(R16=80%,Q16*70%,IF(AND(R16>=81%,R16<=90%),Q16*80%,IF(AND(R16>=91%,R16<=95%),Q16*90%,IF(R16=96%,Q16*96%,IF(R16=97%,Q16*97%,IF(R16=98%,Q16*98%,IF(R16=99%,Q16*99%,IF(R16>=100%,Q16,0)))))))) -> 50000 | U16: =+G16*$U$3 -> 50000 | V16: =+VLOOKUP(C16,Indicadores!B:S,18,FALSE) -> 1 | W16: =IF(V16>=100%,"Cumple","No Cumple") -> Cumple | X16: =+IF(V16=100%,U16,0) -> 50000 | Y16: =IF(L16>=60%,"SI","NO") -> SI | Z16: =+IF(Y16="SI",P16+T16+X16,0) -> 100000
B17: REGIONAL BOGOTA | C17: CTR_5 | D17: CAMILO RINCON | E17: ANYI MAYERLIE ORJUELA | F17: SUSANA SILVA MENDOZA | G17: =IF(L17>=80%,250000,IF(AND(L17>=60%,L17<80%),150000,0)) -> 250000 | H17: =+VLOOKUP(C17,Indicadores!B:C,2,FALSE) -> 0.66666667 | I17: =IF(H17>=60%,"Cumple","No Cumple") -> Cumple | J17: =+VLOOKUP(C17,Indicadores!B:F,5,FALSE) -> 1 | K17: =IF(J17>=60%,"Cumple","No Cumple") -> Cumple | L17: =+AVERAGE(H17,J17) -> 0.83333333 | M17: =+G17*$M$3 -> 150000 | N17: =+VLOOKUP(C17,Indicadores!B:M,12,FALSE) -> 0.66666667 | O17: =IF(N17>=60%,"Cumple","No Cumple") -> Cumple | P17: =IF(N17>80%,M17*100%,IF(AND(N17>=60%,N17<=79%),M17*60%,0)) -> 90000 | Q17: =+$G$6*$Q$3 -> 50000 | R17: 1.5778 | S17: =IF(R17>=70%,"Cumple","No Cumple") -> Cumple | T17: =IF(R17=80%,Q17*70%,IF(AND(R17>=81%,R17<=90%),Q17*80%,IF(AND(R17>=91%,R17<=95%),Q17*90%,IF(R17=96%,Q17*96%,IF(R17=97%,Q17*97%,IF(R17=98%,Q17*98%,IF(R17=99%,Q17*99%,IF(R17>=100%,Q17,0)))))))) -> 50000 | U17: =+G17*$U$3 -> 50000 | V17: =+VLOOKUP(C17,Indicadores!B:S,18,FALSE) -> 1 | W17: =IF(V17>=100%,"Cumple","No Cumple") -> Cumple | X17: =+IF(V17=100%,U17,0) -> 50000 | Y17: =IF(L17>=60%,"SI","NO") -> SI | Z17: =+IF(Y17="SI",P17+T17+X17,0) -> 190000
B18: REGIONAL BOGOTA | C18: CTR_6 | D18: PAULA RUBIO | E18: ANYI MAYERLIE ORJUELA | F18: SUSANA SILVA MENDOZA | G18: =IF(L18>=80%,250000,IF(AND(L18>=60%,L18<80%),150000,0)) -> 250000 | H18: =+VLOOKUP(C18,Indicadores!B:C,2,FALSE) -> 1 | I18: =IF(H18>=60%,"Cumple","No Cumple") -> Cumple | J18: =+VLOOKUP(C18,Indicadores!B:F,5,FALSE) -> 0.8 | K18: =IF(J18>=60%,"Cumple","No Cumple") -> Cumple | L18: =+AVERAGE(H18,J18) -> 0.9 | M18: =+G18*$M$3 -> 150000 | N18: =+VLOOKUP(C18,Indicadores!B:M,12,FALSE) -> 0.93333333 | O18: =IF(N18>=60%,"Cumple","No Cumple") -> Cumple | P18: =IF(N18>80%,M18*100%,IF(AND(N18>=60%,N18<=79%),M18*60%,0)) -> 150000 | Q18: =+$G$6*$Q$3 -> 50000 | R18: =+IFERROR(VLOOKUP(C18,Indicadores!B:N,13,FALSE),0%) -> 0.98928991 | S18: =IF(R18>=70%,"Cumple","No Cumple") -> Cumple | T18: =IF(R18=80%,Q18*70%,IF(AND(R18>=81%,R18<=90%),Q18*80%,IF(AND(R18>=91%,R18<=95%),Q18*90%,IF(R18=96%,Q18*96%,IF(R18=97%,Q18*97%,IF(R18>=98%,Q18*98%,IF(R18=99%,Q18*99%,IF(R18>=100%,Q18,0)))))))) -> 49000 | U18: =+G18*$U$3 -> 50000 | V18: =+VLOOKUP(C18,Indicadores!B:S,18,FALSE) -> 1 | W18: =IF(V18>=100%,"Cumple","No Cumple") -> Cumple | X18: =+IF(V18=100%,U18,0) -> 50000 | Y18: =IF(L18>=60%,"SI","NO") -> SI | Z18: =+IF(Y18="SI",P18+T18+X18,0) -> 249000
B19: REGIONAL BOGOTA | C19: CTR_7 | D19: ALEJANDRO RODRIGUEZ | E19: ANYI MAYERLIE ORJUELA | F19: SUSANA SILVA MENDOZA | G19: =IF(L19>=80%,250000,IF(AND(L19>=60%,L19<80%),150000,0)) -> 250000 | H19: =+VLOOKUP(C19,Indicadores!B:C,2,FALSE) -> 1 | I19: =IF(H19>=60%,"Cumple","No Cumple") -> Cumple | J19: =+VLOOKUP(C19,Indicadores!B:F,5,FALSE) -> 1 | K19: =IF(J19>=60%,"Cumple","No Cumple") -> Cumple | L19: =+AVERAGE(H19,J19) -> 1 | M19: =+G19*$M$3 -> 150000 | N19: =+VLOOKUP(C19,Indicadores!B:M,12,FALSE) -> 1 | O19: =IF(N19>=60%,"Cumple","No Cumple") -> Cumple | P19: =IF(N19>80%,M19*100%,IF(AND(N19>=60%,N19<=79%),M19*60%,0)) -> 150000 | Q19: =+$G$6*$Q$3 -> 50000 | R19: =+IFERROR(VLOOKUP(C19,Indicadores!B:N,13,FALSE),0%) -> 1.0011239 | S19: =IF(R19>=70%,"Cumple","No Cumple") -> Cumple | T19: =IF(R19=80%,Q19*70%,IF(AND(R19>=81%,R19<=90%),Q19*80%,IF(AND(R19>=91%,R19<=95%),Q19*90%,IF(R19=96%,Q19*96%,IF(R19=97%,Q19*97%,IF(R19=98%,Q19*98%,IF(R19=99%,Q19*99%,IF(R19>=100%,Q19,0)))))))) -> 50000 | U19: =+G19*$U$3 -> 50000 | V19: =+VLOOKUP(C19,Indicadores!B:S,18,FALSE) -> 1 | W19: =IF(V19>=100%,"Cumple","No Cumple") -> Cumple | X19: =+IF(V19=100%,U19,0) -> 50000 | Y19: =IF(L19>=60%,"SI","NO") -> SI | Z19: =+IF(Y19="SI",P19+T19+X19,0) -> 250000
B20: REGIONAL BOGOTA | C20: CTR_8 | D20: CAMILO RINCON | E20: ANYI MAYERLIE ORJUELA | F20: SUSANA SILVA MENDOZA | G20: =IF(L20>=80%,250000,IF(AND(L20>=60%,L20<80%),150000,0)) -> 250000 | H20: =+VLOOKUP(C20,Indicadores!B:C,2,FALSE) -> 0.83333333 | I20: =IF(H20>=60%,"Cumple","No Cumple") -> Cumple | J20: =+VLOOKUP(C20,Indicadores!B:F,5,FALSE) -> 0.83333333 | K20: =IF(J20>=60%,"Cumple","No Cumple") -> Cumple | L20: =+AVERAGE(H20,J20) -> 0.83333333 | M20: =+G20*$M$3 -> 150000 | N20: =+VLOOKUP(C20,Indicadores!B:M,12,FALSE) -> 0.88888889 | O20: =IF(N20>=60%,"Cumple","No Cumple") -> Cumple | P20: =IF(N20>80%,M20*100%,IF(AND(N20>=60%,N20<=79%),M20*60%,0)) -> 150000 | Q20: =+$G$6*$Q$3 -> 50000 | R20: =+IFERROR(VLOOKUP(C20,Indicadores!B:N,13,FALSE),0%) -> 1.0138425 | S20: =IF(R20>=70%,"Cumple","No Cumple") -> Cumple | T20: =IF(R20=80%,Q20*70%,IF(AND(R20>=81%,R20<=90%),Q20*80%,IF(AND(R20>=91%,R20<=95%),Q20*90%,IF(R20=96%,Q20*96%,IF(R20=97%,Q20*97%,IF(R20=98%,Q20*98%,IF(R20=99%,Q20*99%,IF(R20>=100%,Q20,0)))))))) -> 50000 | U20: =+G20*$U$3 -> 50000 | V20: =+VLOOKUP(C20,Indicadores!B:S,18,FALSE) -> 0.91666667 | W20: =IF(V20>=100%,"Cumple","No Cumple") -> No Cumple | X20: =+IF(V20=100%,U20,0) -> 0 | Y20: =IF(L20>=60%,"SI","NO") -> SI | Z20: =+IF(Y20="SI",P20+T20+X20,0) -> 200000
B21: REGIONAL BOGOTA | C21: CTR_9 | D21: ALEJANDRO RODRIGUEZ | E21: ANYI MAYERLIE ORJUELA | F21: SUSANA SILVA MENDOZA | G21: =IF(L21>=80%,250000,IF(AND(L21>=60%,L21<80%),150000,0)) -> 250000 | H21: =+VLOOKUP(C21,Indicadores!B:C,2,FALSE) -> 1 | I21: =IF(H21>=60%,"Cumple","No Cumple") -> Cumple | J21: =+VLOOKUP(C21,Indicadores!B:F,5,FALSE) -> 1 | K21: =IF(J21>=60%,"Cumple","No Cumple") -> Cumple | L21: =+AVERAGE(H21,J21) -> 1 | M21: =+G21*$M$3 -> 150000 | N21: =+VLOOKUP(C21,Indicadores!B:M,12,FALSE) -> 1 | O21: =IF(N21>=60%,"Cumple","No Cumple") -> Cumple | P21: =IF(N21>80%,M21*100%,IF(AND(N21>=60%,N21<=79%),M21*60%,0)) -> 150000 | Q21: =+$G$6*$Q$3 -> 50000 | R21: =+IFERROR(VLOOKUP(C21,Indicadores!B:N,13,FALSE),0%) -> 0.75218714 | S21: =IF(R21>=80%,"Cumple","No Cumple") -> No Cumple | T21: =IF(R21>=70%,Q21*70%,IF(AND(R21>=81%,R21<=90%),Q21*80%,IF(AND(R21>=91%,R21<=95%),Q21*90%,IF(R21=96%,Q21*96%,IF(R21=97%,Q21*97%,IF(R21=98%,Q21*98%,IF(R21=99%,Q21*99%,IF(R21>=100%,Q21,0)))))))) -> 35000 | U21: =+G21*$U$3 -> 50000 | V21: =+VLOOKUP(C21,Indicadores!B:S,18,FALSE) -> 1 | W21: =IF(V21>=100%,"Cumple","No Cumple") -> Cumple | X21: =+IF(V21=100%,U21,0) -> 50000 | Y21: =IF(L21>=60%,"SI","NO") -> SI | Z21: =+IF(Y21="SI",P21+T21+X21,0) -> 235000
B22: REGIONAL BOGOTA | C22: SOR_1 | D22: ALEJANDRO RODRIGUEZ | E22: ANYI MAYERLIE ORJUELA | F22: JUAN PABLO GIL ALMANZA | G22: =IF(L22>=80%,250000,IF(AND(L22>=60%,L22<80%),150000,0)) -> 250000 | H22: =+VLOOKUP(C22,Indicadores!B:C,2,FALSE) -> 1 | I22: =IF(H22>=60%,"Cumple","No Cumple") -> Cumple | J22: =+VLOOKUP(C22,Indicadores!B:F,5,FALSE) -> 1 | K22: =IF(J22>=60%,"Cumple","No Cumple") -> Cumple | L22: =+AVERAGE(H22,J22) -> 1 | M22: =+G22*$M$3 -> 150000 | N22: =+VLOOKUP(C22,Indicadores!B:M,12,FALSE) -> 1 | O22: =IF(N22>=60%,"Cumple","No Cumple") -> Cumple | P22: =IF(N22>80%,M22*100%,IF(AND(N22>=60%,N22<=79%),M22*60%,0)) -> 150000 | Q22: =+$G$6*$Q$3 -> 50000 | R22: =+IFERROR(VLOOKUP(C22,Indicadores!B:N,13,FALSE),0%) -> 1.1783685 | S22: =IF(R22>=70%,"Cumple","No Cumple") -> Cumple | T22: =IF(R22=80%,Q22*70%,IF(AND(R22>=81%,R22<=90%),Q22*80%,IF(AND(R22>=91%,R22<=95%),Q22*90%,IF(R22=96%,Q22*96%,IF(R22=97%,Q22*97%,IF(R22=98%,Q22*98%,IF(R22=99%,Q22*99%,IF(R22>=100%,Q22,0)))))))) -> 50000 | U22: =+G22*$U$3 -> 50000 | V22: =+VLOOKUP(C22,Indicadores!B:S,18,FALSE) -> 1 | W22: =IF(V22>=100%,"Cumple","No Cumple") -> Cumple | X22: =+IF(V22=100%,U22,0) -> 50000 | Y22: =IF(L22>=60%,"SI","NO") -> SI | Z22: =+IF(Y22="SI",P22+T22+X22,0) -> 250000
B23: REGIONAL BOGOTA | C23: SOR_10 | D23: ALEJANDRO RODRIGUEZ | E23: ANYI MAYERLIE ORJUELA | F23: JUAN PABLO GIL ALMANZA | G23: =IF(L23>=80%,250000,IF(AND(L23>=60%,L23<80%),150000,0)) -> 250000 | H23: =+VLOOKUP(C23,Indicadores!B:C,2,FALSE) -> 1 | I23: =IF(H23>=60%,"Cumple","No Cumple") -> Cumple | J23: =+VLOOKUP(C23,Indicadores!B:F,5,FALSE) -> 1 | K23: =IF(J23>=60%,"Cumple","No Cumple") -> Cumple | L23: =+AVERAGE(H23,J23) -> 1 | M23: =+G23*$M$3 -> 150000 | N23: =+VLOOKUP(C23,Indicadores!B:M,12,FALSE) -> 0.875 | O23: =IF(N23>=60%,"Cumple","No Cumple") -> Cumple | P23: =IF(N23>80%,M23*100%,IF(AND(N23>=60%,N23<=79%),M23*60%,0)) -> 150000 | Q23: =+$G$6*$Q$3 -> 50000 | R23: =+IFERROR(VLOOKUP(C23,Indicadores!B:N,13,FALSE),0%) -> 1.0265769 | S23: =IF(R23>=70%,"Cumple","No Cumple") -> Cumple | T23: =IF(R23=80%,Q23*70%,IF(AND(R23>=81%,R23<=90%),Q23*80%,IF(AND(R23>=91%,R23<=95%),Q23*90%,IF(R23=96%,Q23*96%,IF(R23=97%,Q23*97%,IF(R23=98%,Q23*98%,IF(R23=99%,Q23*99%,IF(R23>=100%,Q23,0)))))))) -> 50000 | U23: =+G23*$U$3 -> 50000 | V23: =+VLOOKUP(C23,Indicadores!B:S,18,FALSE) -> 1 | W23: =IF(V23>=100%,"Cumple","No Cumple") -> Cumple | X23: =+IF(V23=100%,U23,0) -> 50000 | Y23: =IF(L23>=60%,"SI","NO") -> SI | Z23: =+IF(Y23="SI",P23+T23+X23,0) -> 250000
B24: REGIONAL BOGOTA | C24: SOR_11 | D24: ALEJANDRO RODRIGUEZ | E24: ANYI MAYERLIE ORJUELA | F24: JUAN PABLO GIL ALMANZA | G24: =IF(L24>=80%,250000,IF(AND(L24>=60%,L24<80%),150000,0)) -> 250000 | H24: =+VLOOKUP(C24,Indicadores!B:C,2,FALSE) -> 1 | I24: =IF(H24>=60%,"Cumple","No Cumple") -> Cumple | J24: =+VLOOKUP(C24,Indicadores!B:F,5,FALSE) -> 1 | K24: =IF(J24>=60%,"Cumple","No Cumple") -> Cumple | L24: =+AVERAGE(H24,J24) -> 1 | M24: =+G24*$M$3 -> 150000 | N24: =+VLOOKUP(C24,Indicadores!B:M,12,FALSE) -> 0.97916667 | O24: =IF(N24>=60%,"Cumple","No Cumple") -> Cumple | P24: =IF(N24>80%,M24*100%,IF(AND(N24>=60%,N24<=79%),M24*60%,0)) -> 150000 | Q24: =+$G$6*$Q$3 -> 50000 | R24: =+IFERROR(VLOOKUP(C24,Indicadores!B:N,13,FALSE),0%) -> 0.93665487 | S24: =IF(R24>=70%,"Cumple","No Cumple") -> Cumple | T24: =IF(R24=80%,Q24*70%,IF(AND(R24>=81%,R24<=90%),Q24*80%,IF(AND(R24>=91%,R24<=95%),Q24*90%,IF(R24=96%,Q24*96%,IF(R24=97%,Q24*97%,IF(R24=98%,Q24*98%,IF(R24=99%,Q24*99%,IF(R24>=100%,Q24,0)))))))) -> 45000 | U24: =+G24*$U$3 -> 50000 | V24: =+VLOOKUP(C24,Indicadores!B:S,18,FALSE) -> 1 | W24: =IF(V24>=100%,"Cumple","No Cumple") -> Cumple | X24: =+IF(V24=100%,U24,0) -> 50000 | Y24: =IF(L24>=60%,"SI","NO") -> SI | Z24: =+IF(Y24="SI",P24+T24+X24,0) -> 245000
B25: REGIONAL BOGOTA | C25: SOR_12 | D25: PAULA RUBIO | E25: ANYI MAYERLIE ORJUELA | F25: JUAN PABLO GIL ALMANZA | G25: =IF(L25>=80%,250000,IF(AND(L25>=60%,L25<80%),150000,0)) -> 250000 | H25: =+VLOOKUP(C25,Indicadores!B:C,2,FALSE) -> 1 | I25: =IF(H25>=60%,"Cumple","No Cumple") -> Cumple | J25: =+VLOOKUP(C25,Indicadores!B:F,5,FALSE) -> 1 | K25: =IF(J25>=60%,"Cumple","No Cumple") -> Cumple | L25: =+AVERAGE(H25,J25) -> 1 | M25: =+G25*$M$3 -> 150000 | N25: =+VLOOKUP(C25,Indicadores!B:M,12,FALSE) -> 1 | O25: =IF(N25>=60%,"Cumple","No Cumple") -> Cumple | P25: =IF(N25>80%,M25*100%,IF(AND(N25>=60%,N25<=79%),M25*60%,0)) -> 150000 | Q25: =+$G$6*$Q$3 -> 50000 | R25: =+IFERROR(VLOOKUP(C25,Indicadores!B:N,13,FALSE),0%) -> 1.0490627 | S25: =IF(R25>=70%,"Cumple","No Cumple") -> Cumple | T25: =IF(R25=80%,Q25*70%,IF(AND(R25>=81%,R25<=90%),Q25*80%,IF(AND(R25>=91%,R25<=95%),Q25*90%,IF(R25=96%,Q25*96%,IF(R25=97%,Q25*97%,IF(R25=98%,Q25*98%,IF(R25=99%,Q25*99%,IF(R25>=100%,Q25,0)))))))) -> 50000 | U25: =+G25*$U$3 -> 50000 | V25: =+VLOOKUP(C25,Indicadores!B:S,18,FALSE) -> 1 | W25: =IF(V25>=100%,"Cumple","No Cumple") -> Cumple | X25: =+IF(V25=100%,U25,0) -> 50000 | Y25: =IF(L25>=60%,"SI","NO") -> SI | Z25: =+IF(Y25="SI",P25+T25+X25,0) -> 250000
B26: REGIONAL BOGOTA | C26: SOR_13 | D26: ALEJANDRO RODRIGUEZ | E26: ANYI MAYERLIE ORJUELA | F26: JUAN PABLO GIL ALMANZA | G26: =IF(L26>=80%,250000,IF(AND(L26>=60%,L26<80%),150000,0)) -> 250000 | H26: =+VLOOKUP(C26,Indicadores!B:C,2,FALSE) -> 1 | I26: =IF(H26>=60%,"Cumple","No Cumple") -> Cumple | J26: =+VLOOKUP(C26,Indicadores!B:F,5,FALSE) -> 1 | K26: =IF(J26>=60%,"Cumple","No Cumple") -> Cumple | L26: =+AVERAGE(H26,J26) -> 1 | M26: =+G26*$M$3 -> 150000 | N26: =+VLOOKUP(C26,Indicadores!B:M,12,FALSE) -> 0.97777778 | O26: =IF(N26>=60%,"Cumple","No Cumple") -> Cumple | P26: =IF(N26>80%,M26*100%,IF(AND(N26>=60%,N26<=79%),M26*60%,0)) -> 150000 | Q26: =+$G$6*$Q$3 -> 50000 | R26: =+IFERROR(VLOOKUP(C26,Indicadores!B:N,13,FALSE),0%) -> 1.1133674 | S26: =IF(R26>=70%,"Cumple","No Cumple") -> Cumple | T26: =IF(R26=80%,Q26*70%,IF(AND(R26>=81%,R26<=90%),Q26*80%,IF(AND(R26>=91%,R26<=95%),Q26*90%,IF(R26=96%,Q26*96%,IF(R26=97%,Q26*97%,IF(R26=98%,Q26*98%,IF(R26=99%,Q26*99%,IF(R26>=100%,Q26,0)))))))) -> 50000 | U26: =+G26*$U$3 -> 50000 | V26: =+VLOOKUP(C26,Indicadores!B:S,18,FALSE) -> 0.5 | W26: =IF(V26>=100%,"Cumple","No Cumple") -> No Cumple | X26: =+IF(V26=100%,U26,0) -> 0 | Y26: =IF(L26>=60%,"SI","NO") -> SI | Z26: =+IF(Y26="SI",P26+T26+X26,0) -> 200000
B27: REGIONAL BOGOTA | C27: SOR_14 | D27: ALEJANDRO RODRIGUEZ | E27: ANYI MAYERLIE ORJUELA | F27: JUAN PABLO GIL ALMANZA | G27: =IF(L27>=80%,250000,IF(AND(L27>=60%,L27<80%),150000,0)) -> 250000 | H27: =+VLOOKUP(C27,Indicadores!B:C,2,FALSE) -> 1 | I27: =IF(H27>=60%,"Cumple","No Cumple") -> Cumple | J27: =+VLOOKUP(C27,Indicadores!B:F,5,FALSE) -> 1 | K27: =IF(J27>=60%,"Cumple","No Cumple") -> Cumple | L27: =+AVERAGE(H27,J27) -> 1 | M27: =+G27*$M$3 -> 150000 | N27: =+VLOOKUP(C27,Indicadores!B:M,12,FALSE) -> 1 | O27: =IF(N27>=60%,"Cumple","No Cumple") -> Cumple | P27: =IF(N27>80%,M27*100%,IF(AND(N27>=60%,N27<=79%),M27*60%,0)) -> 150000 | Q27: =+$G$6*$Q$3 -> 50000 | R27: 0.9 | S27: =IF(R27>=70%,"Cumple","No Cumple") -> Cumple | T27: =IF(R27=80%,Q27*70%,IF(AND(R27>=81%,R27<=90%),Q27*80%,IF(AND(R27>=91%,R27<=95%),Q27*90%,IF(R27=96%,Q27*96%,IF(R27=97%,Q27*97%,IF(R27>=98%,Q27*98%,IF(R27=99%,Q27*99%,IF(R27>=100%,Q27,0)))))))) -> 40000 | U27: =+G27*$U$3 -> 50000 | V27: =+VLOOKUP(C27,Indicadores!B:S,18,FALSE) -> 0.5 | W27: =IF(V27>=100%,"Cumple","No Cumple") -> No Cumple | X27: =+IF(V27=100%,U27,0) -> 0 | Y27: =IF(L27>=60%,"SI","NO") -> SI | Z27: =+IF(Y27="SI",P27+T27+X27,0) -> 190000
B28: REGIONAL BOGOTA | C28: SOR_15 | D28: ALEJANDRO RODRIGUEZ | E28: ANYI MAYERLIE ORJUELA | F28: JUAN PABLO GIL ALMANZA | G28: =IF(L28>=80%,250000,IF(AND(L28>=60%,L28<80%),150000,0)) -> 250000 | H28: =+VLOOKUP(C28,Indicadores!B:C,2,FALSE) -> 0.94444444 | I28: =IF(H28>=60%,"Cumple","No Cumple") -> Cumple | J28: =+VLOOKUP(C28,Indicadores!B:F,5,FALSE) -> 1 | K28: =IF(J28>=60%,"Cumple","No Cumple") -> Cumple | L28: =+AVERAGE(H28,J28) -> 0.97222222 | M28: =+G28*$M$3 -> 150000 | N28: =+VLOOKUP(C28,Indicadores!B:M,12,FALSE) -> 0.98148148 | O28: =IF(N28>=60%,"Cumple","No Cumple") -> Cumple | P28: =IF(N28>80%,M28*100%,IF(AND(N28>=60%,N28<=79%),M28*60%,0)) -> 150000 | Q28: =+$G$6*$Q$3 -> 50000 | R28: =+IFERROR(VLOOKUP(C28,Indicadores!B:N,13,FALSE),0%) -> 1.0407577 | S28: =IF(R28>=70%,"Cumple","No Cumple") -> Cumple | T28: =IF(R28=80%,Q28*70%,IF(AND(R28>=81%,R28<=90%),Q28*80%,IF(AND(R28>=91%,R28<=95%),Q28*90%,IF(R28=96%,Q28*96%,IF(R28=97%,Q28*97%,IF(R28=98%,Q28*98%,IF(R28=99%,Q28*99%,IF(R28>=100%,Q28,0)))))))) -> 50000 | U28: =+G28*$U$3 -> 50000 | V28: =+VLOOKUP(C28,Indicadores!B:S,18,FALSE) -> 0.97222222 | W28: =IF(V28>=100%,"Cumple","No Cumple") -> No Cumple | X28: =+IF(V28=100%,U28,0) -> 0 | Y28: =IF(L28>=60%,"SI","NO") -> SI | Z28: =+IF(Y28="SI",P28+T28+X28,0) -> 200000
B29: REGIONAL BOGOTA | C29: SOR_16 | D29: ALEJANDRO RODRIGUEZ | E29: ANYI MAYERLIE ORJUELA | F29: JUAN PABLO GIL ALMANZA | G29: =IF(L29>=80%,250000,IF(AND(L29>=60%,L29<80%),150000,0)) -> 250000 | H29: =+VLOOKUP(C29,Indicadores!B:C,2,FALSE) -> 1 | I29: =IF(H29>=60%,"Cumple","No Cumple") -> Cumple | J29: =+VLOOKUP(C29,Indicadores!B:F,5,FALSE) -> 1 | K29: =IF(J29>=60%,"Cumple","No Cumple") -> Cumple | L29: =+AVERAGE(H29,J29) -> 1 | M29: =+G29*$M$3 -> 150000 | N29: =+VLOOKUP(C29,Indicadores!B:M,12,FALSE) -> 1 | O29: =IF(N29>=60%,"Cumple","No Cumple") -> Cumple | P29: =IF(N29>80%,M29*100%,IF(AND(N29>=60%,N29<=79%),M29*60%,0)) -> 150000 | Q29: =+$G$6*$Q$3 -> 50000 | R29: =+IFERROR(VLOOKUP(C29,Indicadores!B:N,13,FALSE),0%) -> 0.98077537 | S29: =IF(R29>=70%,"Cumple","No Cumple") -> Cumple | T29: =IF(R29=80%,Q29*70%,IF(AND(R29>=81%,R29<=90%),Q29*80%,IF(AND(R29>=91%,R29<=95%),Q29*90%,IF(R29=96%,Q29*96%,IF(R29=97%,Q29*97%,IF(R29>=98%,Q29*98%,IF(R29=99%,Q29*99%,IF(R29>=100%,Q29,0)))))))) -> 49000 | U29: =+G29*$U$3 -> 50000 | V29: =+VLOOKUP(C29,Indicadores!B:S,18,FALSE) -> 1 | W29: =IF(V29>=100%,"Cumple","No Cumple") -> Cumple | X29: =+IF(V29=100%,U29,0) -> 50000 | Y29: =IF(L29>=60%,"SI","NO") -> SI | Z29: =+IF(Y29="SI",P29+T29+X29,0) -> 249000
B30: REGIONAL BOGOTA | C30: SOR_2 | D30: ALEJANDRO RODRIGUEZ | E30: ANYI MAYERLIE ORJUELA | F30: JUAN PABLO GIL ALMANZA | G30: =IF(L30>=80%,250000,IF(AND(L30>=60%,L30<80%),150000,0)) -> 250000 | H30: =+VLOOKUP(C30,Indicadores!B:C,2,FALSE) -> 1 | I30: =IF(H30>=60%,"Cumple","No Cumple") -> Cumple | J30: =+VLOOKUP(C30,Indicadores!B:F,5,FALSE) -> 1 | K30: =IF(J30>=60%,"Cumple","No Cumple") -> Cumple | L30: =+AVERAGE(H30,J30) -> 1 | M30: =+G30*$M$3 -> 150000 | N30: =+VLOOKUP(C30,Indicadores!B:M,12,FALSE) -> 1 | O30: =IF(N30>=60%,"Cumple","No Cumple") -> Cumple | P30: =IF(N30>80%,M30*100%,IF(AND(N30>=60%,N30<=79%),M30*60%,0)) -> 150000 | Q30: =+$G$6*$Q$3 -> 50000 | R30: =+IFERROR(VLOOKUP(C30,Indicadores!B:N,13,FALSE),0%) -> 0.63770592 | S30: =IF(R30>=80%,"Cumple","No Cumple") -> No Cumple | T30: =IF(R30>=70%,Q30*70%,IF(AND(R30>=81%,R30<=90%),Q30*80%,IF(AND(R30>=91%,R30<=95%),Q30*90%,IF(R30=96%,Q30*96%,IF(R30=97%,Q30*97%,IF(R30=98%,Q30*98%,IF(R30=99%,Q30*99%,IF(R30>=100%,Q30,0)))))))) -> 0 | U30: =+G30*$U$3 -> 50000 | V30: =+VLOOKUP(C30,Indicadores!B:S,18,FALSE) -> 0.5 | W30: =IF(V30>=100%,"Cumple","No Cumple") -> No Cumple | X30: =+IF(V30=100%,U30,0) -> 0 | Y30: =IF(L30>=60%,"SI","NO") -> SI | Z30: =+IF(Y30="SI",P30+T30+X30,0) -> 150000
B31: REGIONAL BOGOTA | C31: SOR_3 | D31: ALEJANDRO RODRIGUEZ | E31: ANYI MAYERLIE ORJUELA | F31: JUAN PABLO GIL ALMANZA | G31: =IF(L31>=80%,250000,IF(AND(L31>=60%,L31<80%),150000,0)) -> 250000 | H31: =+VLOOKUP(C31,Indicadores!B:C,2,FALSE) -> 1 | I31: =IF(H31>=60%,"Cumple","No Cumple") -> Cumple | J31: =+VLOOKUP(C31,Indicadores!B:F,5,FALSE) -> 1 | K31: =IF(J31>=60%,"Cumple","No Cumple") -> Cumple | L31: =+AVERAGE(H31,J31) -> 1 | M31: =+G31*$M$3 -> 150000 | N31: =+VLOOKUP(C31,Indicadores!B:M,12,FALSE) -> 1 | O31: =IF(N31>=60%,"Cumple","No Cumple") -> Cumple | P31: =IF(N31>80%,M31*100%,IF(AND(N31>=60%,N31<=79%),M31*60%,0)) -> 150000 | Q31: =+$G$6*$Q$3 -> 50000 | R31: =+IFERROR(VLOOKUP(C31,Indicadores!B:N,13,FALSE),0%) -> 0.92267607 | S31: =IF(R31>=70%,"Cumple","No Cumple") -> Cumple | T31: =IF(R31=80%,Q31*70%,IF(AND(R31>=81%,R31<=90%),Q31*80%,IF(AND(R31>=91%,R31<=95%),Q31*90%,IF(R31=96%,Q31*96%,IF(R31=97%,Q31*97%,IF(R31=98%,Q31*98%,IF(R31=99%,Q31*99%,IF(R31>=100%,Q31,0)))))))) -> 45000 | U31: =+G31*$U$3 -> 50000 | V31: =+VLOOKUP(C31,Indicadores!B:S,18,FALSE) -> 1 | W31: =IF(V31>=100%,"Cumple","No Cumple") -> Cumple | X31: =+IF(V31=100%,U31,0) -> 50000 | Y31: =IF(L31>=60%,"SI","NO") -> SI | Z31: =+IF(Y31="SI",P31+T31+X31,0) -> 245000
B32: REGIONAL BOGOTA | C32: SOR_4 | D32: ALEJANDRO RODRIGUEZ | E32: ANYI MAYERLIE ORJUELA | F32: JUAN PABLO GIL ALMANZA | G32: =IF(L32>=80%,250000,IF(AND(L32>=60%,L32<80%),150000,0)) -> 250000 | H32: =+VLOOKUP(C32,Indicadores!B:C,2,FALSE) -> 1 | I32: =IF(H32>=60%,"Cumple","No Cumple") -> Cumple | J32: =+VLOOKUP(C32,Indicadores!B:F,5,FALSE) -> 1 | K32: =IF(J32>=60%,"Cumple","No Cumple") -> Cumple | L32: =+AVERAGE(H32,J32) -> 1 | M32: =+G32*$M$3 -> 150000 | N32: =+VLOOKUP(C32,Indicadores!B:M,12,FALSE) -> 1 | O32: =IF(N32>=60%,"Cumple","No Cumple") -> Cumple | P32: =IF(N32>80%,M32*100%,IF(AND(N32>=60%,N32<=79%),M32*60%,0)) -> 150000 | Q32: =+$G$6*$Q$3 -> 50000 | R32: =+IFERROR(VLOOKUP(C32,Indicadores!B:N,13,FALSE),0%) -> 1.0741337 | S32: =IF(R32>=70%,"Cumple","No Cumple") -> Cumple | T32: =IF(R32=80%,Q32*70%,IF(AND(R32>=81%,R32<=90%),Q32*80%,IF(AND(R32>=91%,R32<=95%),Q32*90%,IF(R32=96%,Q32*96%,IF(R32=97%,Q32*97%,IF(R32=98%,Q32*98%,IF(R32=99%,Q32*99%,IF(R32>=100%,Q32,0)))))))) -> 50000 | U32: =+G32*$U$3 -> 50000 | V32: =+VLOOKUP(C32,Indicadores!B:S,18,FALSE) -> 1 | W32: =IF(V32>=100%,"Cumple","No Cumple") -> Cumple | X32: =+IF(V32=100%,U32,0) -> 50000 | Y32: =IF(L32>=60%,"SI","NO") -> SI | Z32: =+IF(Y32="SI",P32+T32+X32,0) -> 250000
B33: REGIONAL BOGOTA | C33: SOR_5 | D33: ALEJANDRO RODRIGUEZ | E33: ANYI MAYERLIE ORJUELA | F33: JUAN PABLO GIL ALMANZA | G33: =IF(L33>=80%,250000,IF(AND(L33>=60%,L33<80%),150000,0)) -> 250000 | H33: =+VLOOKUP(C33,Indicadores!B:C,2,FALSE) -> 1 | I33: =IF(H33>=60%,"Cumple","No Cumple") -> Cumple | J33: =+VLOOKUP(C33,Indicadores!B:F,5,FALSE) -> 1 | K33: =IF(J33>=60%,"Cumple","No Cumple") -> Cumple | L33: =+AVERAGE(H33,J33) -> 1 | M33: =+G33*$M$3 -> 150000 | N33: =+VLOOKUP(C33,Indicadores!B:M,12,FALSE) -> 1 | O33: =IF(N33>=60%,"Cumple","No Cumple") -> Cumple | P33: =IF(N33>80%,M33*100%,IF(AND(N33>=60%,N33<=79%),M33*60%,0)) -> 150000 | Q33: =+$G$6*$Q$3 -> 50000 | R33: =+IFERROR(VLOOKUP(C33,Indicadores!B:N,13,FALSE),0%) -> 1.114458 | S33: =IF(R33>=70%,"Cumple","No Cumple") -> Cumple | T33: =IF(R33=80%,Q33*70%,IF(AND(R33>=81%,R33<=90%),Q33*80%,IF(AND(R33>=91%,R33<=95%),Q33*90%,IF(R33=96%,Q33*96%,IF(R33=97%,Q33*97%,IF(R33=98%,Q33*98%,IF(R33=99%,Q33*99%,IF(R33>=100%,Q33,0)))))))) -> 50000 | U33: =+G33*$U$3 -> 50000 | V33: =+VLOOKUP(C33,Indicadores!B:S,18,FALSE) -> 1 | W33: =IF(V33>=100%,"Cumple","No Cumple") -> Cumple | X33: =+IF(V33=100%,U33,0) -> 50000 | Y33: =IF(L33>=60%,"SI","NO") -> SI | Z33: =+IF(Y33="SI",P33+T33+X33,0) -> 250000
B34: REGIONAL BOGOTA | C34: SOR_6 | D34: ALEJANDRO RODRIGUEZ | E34: ANYI MAYERLIE ORJUELA | F34: JUAN PABLO GIL ALMANZA | G34: =IF(L34>=80%,250000,IF(AND(L34>=60%,L34<80%),150000,0)) -> 250000 | H34: =+VLOOKUP(C34,Indicadores!B:C,2,FALSE) -> 1 | I34: =IF(H34>=60%,"Cumple","No Cumple") -> Cumple | J34: =+VLOOKUP(C34,Indicadores!B:F,5,FALSE) -> 1 | K34: =IF(J34>=60%,"Cumple","No Cumple") -> Cumple | L34: =+AVERAGE(H34,J34) -> 1 | M34: =+G34*$M$3 -> 150000 | N34: =+VLOOKUP(C34,Indicadores!B:M,12,FALSE) -> 1 | O34: =IF(N34>=60%,"Cumple","No Cumple") -> Cumple | P34: =IF(N34>80%,M34*100%,IF(AND(N34>=60%,N34<=79%),M34*60%,0)) -> 150000 | Q34: =+$G$6*$Q$3 -> 50000 | R34: =+IFERROR(VLOOKUP(C34,Indicadores!B:N,13,FALSE),0%) -> 0.97915641 | S34: =IF(R34>=70%,"Cumple","No Cumple") -> Cumple | T34: =IF(R34=80%,Q34*70%,IF(AND(R34>=81%,R34<=90%),Q34*80%,IF(AND(R34>=91%,R34<=95%),Q34*90%,IF(R34=96%,Q34*96%,IF(R34>=97%,Q34*97%,IF(R34>=98%,Q34*98%,IF(R34=99%,Q34*99%,IF(R34>=100%,Q34,0)))))))) -> 48500 | U34: =+G34*$U$3 -> 50000 | V34: =+VLOOKUP(C34,Indicadores!B:S,18,FALSE) -> 1 | W34: =IF(V34>=100%,"Cumple","No Cumple") -> Cumple | X34: =+IF(V34=100%,U34,0) -> 50000 | Y34: =IF(L34>=60%,"SI","NO") -> SI | Z34: =+IF(Y34="SI",P34+T34+X34,0) -> 248500
B35: REGIONAL BOGOTA | C35: SOR_7 | D35: ALEJANDRO RODRIGUEZ | E35: ANYI MAYERLIE ORJUELA | F35: JUAN PABLO GIL ALMANZA | G35: =IF(L35>=80%,250000,IF(AND(L35>=60%,L35<80%),150000,0)) -> 250000 | H35: =+VLOOKUP(C35,Indicadores!B:C,2,FALSE) -> 1 | I35: =IF(H35>=60%,"Cumple","No Cumple") -> Cumple | J35: =+VLOOKUP(C35,Indicadores!B:F,5,FALSE) -> 1 | K35: =IF(J35>=60%,"Cumple","No Cumple") -> Cumple | L35: =+AVERAGE(H35,J35) -> 1 | M35: =+G35*$M$3 -> 150000 | N35: =+VLOOKUP(C35,Indicadores!B:M,12,FALSE) -> 1 | O35: =IF(N35>=60%,"Cumple","No Cumple") -> Cumple | P35: =IF(N35>80%,M35*100%,IF(AND(N35>=60%,N35<=79%),M35*60%,0)) -> 150000 | Q35: =+$G$6*$Q$3 -> 50000 | R35: =+IFERROR(VLOOKUP(C35,Indicadores!B:N,13,FALSE),0%) -> 1.0518477 | S35: =IF(R35>=70%,"Cumple","No Cumple") -> Cumple | T35: =IF(R35=80%,Q35*70%,IF(AND(R35>=81%,R35<=90%),Q35*80%,IF(AND(R35>=91%,R35<=95%),Q35*90%,IF(R35=96%,Q35*96%,IF(R35=97%,Q35*97%,IF(R35=98%,Q35*98%,IF(R35=99%,Q35*99%,IF(R35>=100%,Q35,0)))))))) -> 50000 | U35: =+G35*$U$3 -> 50000 | V35: =+VLOOKUP(C35,Indicadores!B:S,18,FALSE) -> 0.5 | W35: =IF(V35>=100%,"Cumple","No Cumple") -> No Cumple | X35: =+IF(V35=100%,U35,0) -> 0 | Y35: =IF(L35>=60%,"SI","NO") -> SI | Z35: =+IF(Y35="SI",P35+T35+X35,0) -> 200000
B36: REGIONAL BOGOTA | C36: SOR_8 | D36: ALEJANDRO RODRIGUEZ | E36: ANYI MAYERLIE ORJUELA | F36: JUAN PABLO GIL ALMANZA | G36: =IF(L36>=80%,250000,IF(AND(L36>=60%,L36<80%),150000,0)) -> 250000 | H36: =+VLOOKUP(C36,Indicadores!B:C,2,FALSE) -> 1 | I36: =IF(H36>=60%,"Cumple","No Cumple") -> Cumple | J36: =+VLOOKUP(C36,Indicadores!B:F,5,FALSE) -> 1 | K36: =IF(J36>=60%,"Cumple","No Cumple") -> Cumple | L36: =+AVERAGE(H36,J36) -> 1 | M36: =+G36*$M$3 -> 150000 | N36: =+VLOOKUP(C36,Indicadores!B:M,12,FALSE) -> 1 | O36: =IF(N36>=60%,"Cumple","No Cumple") -> Cumple | P36: =IF(N36>80%,M36*100%,IF(AND(N36>=60%,N36<=79%),M36*60%,0)) -> 150000 | Q36: =+$G$6*$Q$3 -> 50000 | R36: =+IFERROR(VLOOKUP(C36,Indicadores!B:N,13,FALSE),0%) -> 1.1790921 | S36: =IF(R36>=70%,"Cumple","No Cumple") -> Cumple | T36: =IF(R36=80%,Q36*70%,IF(AND(R36>=81%,R36<=90%),Q36*80%,IF(AND(R36>=91%,R36<=95%),Q36*90%,IF(R36=96%,Q36*96%,IF(R36=97%,Q36*97%,IF(R36=98%,Q36*98%,IF(R36=99%,Q36*99%,IF(R36>=100%,Q36,0)))))))) -> 50000 | U36: =+G36*$U$3 -> 50000 | V36: =+VLOOKUP(C36,Indicadores!B:S,18,FALSE) -> 1 | W36: =IF(V36>=100%,"Cumple","No Cumple") -> Cumple | X36: =+IF(V36=100%,U36,0) -> 50000 | Y36: =IF(L36>=60%,"SI","NO") -> SI | Z36: =+IF(Y36="SI",P36+T36+X36,0) -> 250000
B37: REGIONAL BOGOTA | C37: SOR_9 | D37: ALEJANDRO RODRIGUEZ | E37: ANYI MAYERLIE ORJUELA | F37: JUAN PABLO GIL ALMANZA | G37: =IF(L37>=80%,250000,IF(AND(L37>=60%,L37<80%),150000,0)) -> 250000 | H37: =+VLOOKUP(C37,Indicadores!B:C,2,FALSE) -> 1 | I37: =IF(H37>=60%,"Cumple","No Cumple") -> Cumple | J37: =+VLOOKUP(C37,Indicadores!B:F,5,FALSE) -> 1 | K37: =IF(J37>=60%,"Cumple","No Cumple") -> Cumple | L37: =+AVERAGE(H37,J37) -> 1 | M37: =+G37*$M$3 -> 150000 | N37: =+VLOOKUP(C37,Indicadores!B:M,12,FALSE) -> 1 | O37: =IF(N37>=60%,"Cumple","No Cumple") -> Cumple | P37: =IF(N37>80%,M37*100%,IF(AND(N37>=60%,N37<=79%),M37*60%,0)) -> 150000 | Q37: =+$G$6*$Q$3 -> 50000 | R37: =+IFERROR(VLOOKUP(C37,Indicadores!B:N,13,FALSE),0%) -> 1.1548936 | S37: =IF(R37>=70%,"Cumple","No Cumple") -> Cumple | T37: =IF(R37=80%,Q37*70%,IF(AND(R37>=81%,R37<=90%),Q37*80%,IF(AND(R37>=91%,R37<=95%),Q37*90%,IF(R37=96%,Q37*96%,IF(R37=97%,Q37*97%,IF(R37=98%,Q37*98%,IF(R37=99%,Q37*99%,IF(R37>=100%,Q37,0)))))))) -> 50000 | U37: =+G37*$U$3 -> 50000 | V37: =+VLOOKUP(C37,Indicadores!B:S,18,FALSE) -> 1 | W37: =IF(V37>=100%,"Cumple","No Cumple") -> Cumple | X37: =+IF(V37=100%,U37,0) -> 50000 | Y37: =IF(L37>=60%,"SI","NO") -> SI | Z37: =+IF(Y37="SI",P37+T37+X37,0) -> 250000
B38: REGIONAL BOGOTA | C38: NOC_1 | D38: PAULA RUBIO | E38: ANYI MAYERLIE ORJUELA | F38: MELISA MARTINEZ | G38: =IF(L38>=80%,250000,IF(AND(L38>=60%,L38<80%),150000,0)) -> 250000 | H38: =+VLOOKUP(C38,Indicadores!B:C,2,FALSE) -> 1 | I38: =IF(H38>=60%,"Cumple","No Cumple") -> Cumple | J38: =+VLOOKUP(C38,Indicadores!B:F,5,FALSE) -> 1 | K38: =IF(J38>=60%,"Cumple","No Cumple") -> Cumple | L38: =+AVERAGE(H38,J38) -> 1 | M38: =+G38*$M$3 -> 150000 | N38: =+VLOOKUP(C38,Indicadores!B:M,12,FALSE) -> 1 | O38: =IF(N38>=60%,"Cumple","No Cumple") -> Cumple | P38: =IF(N38>80%,M38*100%,IF(AND(N38>=60%,N38<=79%),M38*60%,0)) -> 150000 | Q38: =+$G$6*$Q$3 -> 50000 | R38: =+IFERROR(VLOOKUP(C38,Indicadores!B:N,13,FALSE),0%) -> 1.1734626 | S38: =IF(R38>=70%,"Cumple","No Cumple") -> Cumple | T38: =IF(R38=80%,Q38*70%,IF(AND(R38>=81%,R38<=90%),Q38*80%,IF(AND(R38>=91%,R38<=95%),Q38*90%,IF(R38=96%,Q38*96%,IF(R38=97%,Q38*97%,IF(R38=98%,Q38*98%,IF(R38=99%,Q38*99%,IF(R38>=100%,Q38,0)))))))) -> 50000 | U38: =+G38*$U$3 -> 50000 | V38: =+VLOOKUP(C38,Indicadores!B:S,18,FALSE) -> 1 | W38: =IF(V38>=100%,"Cumple","No Cumple") -> Cumple | X38: =+IF(V38=100%,U38,0) -> 50000 | Y38: =IF(L38>=60%,"SI","NO") -> SI | Z38: =+IF(Y38="SI",P38+T38+X38,0) -> 250000
B39: REGIONAL BOGOTA | C39: NOC_10 | D39: PAULA RUBIO | E39: ANYI MAYERLIE ORJUELA | F39: MELISA MARTINEZ | G39: =IF(L39>=80%,250000,IF(AND(L39>=60%,L39<80%),150000,0)) -> 250000 | H39: =+VLOOKUP(C39,Indicadores!B:C,2,FALSE) -> 1 | I39: =IF(H39>=60%,"Cumple","No Cumple") -> Cumple | J39: =+VLOOKUP(C39,Indicadores!B:F,5,FALSE) -> 1 | K39: =IF(J39>=60%,"Cumple","No Cumple") -> Cumple | L39: =+AVERAGE(H39,J39) -> 1 | M39: =+G39*$M$3 -> 150000 | N39: =+VLOOKUP(C39,Indicadores!B:M,12,FALSE) -> 1 | O39: =IF(N39>=60%,"Cumple","No Cumple") -> Cumple | P39: =IF(N39>80%,M39*100%,IF(AND(N39>=60%,N39<=79%),M39*60%,0)) -> 150000 | Q39: =+$G$6*$Q$3 -> 50000 | R39: =+IFERROR(VLOOKUP(C39,Indicadores!B:N,13,FALSE),0%) -> 1.185924 | S39: =IF(R39>=70%,"Cumple","No Cumple") -> Cumple | T39: =IF(R39=80%,Q39*70%,IF(AND(R39>=81%,R39<=90%),Q39*80%,IF(AND(R39>=91%,R39<=95%),Q39*90%,IF(R39=96%,Q39*96%,IF(R39=97%,Q39*97%,IF(R39=98%,Q39*98%,IF(R39=99%,Q39*99%,IF(R39>=100%,Q39,0)))))))) -> 50000 | U39: =+G39*$U$3 -> 50000 | V39: =+VLOOKUP(C39,Indicadores!B:S,18,FALSE) -> 1 | W39: =IF(V39>=100%,"Cumple","No Cumple") -> Cumple | X39: =+IF(V39=100%,U39,0) -> 50000 | Y39: =IF(L39>=60%,"SI","NO") -> SI | Z39: =+IF(Y39="SI",P39+T39+X39,0) -> 250000
B40: REGIONAL BOGOTA | C40: NOC_11 | D40: PAULA RUBIO | E40: ANYI MAYERLIE ORJUELA | F40: MELISA MARTINEZ | G40: =IF(L40>=80%,250000,IF(AND(L40>=60%,L40<80%),150000,0)) -> 250000 | H40: =+VLOOKUP(C40,Indicadores!B:C,2,FALSE) -> 1 | I40: =IF(H40>=60%,"Cumple","No Cumple") -> Cumple | J40: =+VLOOKUP(C40,Indicadores!B:F,5,FALSE) -> 1 | K40: =IF(J40>=60%,"Cumple","No Cumple") -> Cumple | L40: =+AVERAGE(H40,J40) -> 1 | M40: =+G40*$M$3 -> 150000 | N40: =+VLOOKUP(C40,Indicadores!B:M,12,FALSE) -> 0.97619048 | O40: =IF(N40>=60%,"Cumple","No Cumple") -> Cumple | P40: =IF(N40>80%,M40*100%,IF(AND(N40>=60%,N40<=79%),M40*60%,0)) -> 150000 | Q40: =+$G$6*$Q$3 -> 50000 | R40: =+IFERROR(VLOOKUP(C40,Indicadores!B:N,13,FALSE),0%) -> 1.0106447 | S40: =IF(R40>=70%,"Cumple","No Cumple") -> Cumple | T40: =IF(R40=80%,Q40*70%,IF(AND(R40>=81%,R40<=90%),Q40*80%,IF(AND(R40>=91%,R40<=95%),Q40*90%,IF(R40=96%,Q40*96%,IF(R40=97%,Q40*97%,IF(R40=98%,Q40*98%,IF(R40=99%,Q40*99%,IF(R40>=100%,Q40,0)))))))) -> 50000 | U40: =+G40*$U$3 -> 50000 | V40: =+VLOOKUP(C40,Indicadores!B:S,18,FALSE) -> 1 | W40: =IF(V40>=100%,"Cumple","No Cumple") -> Cumple | X40: =+IF(V40=100%,U40,0) -> 50000 | Y40: =IF(L40>=60%,"SI","NO") -> SI | Z40: =+IF(Y40="SI",P40+T40+X40,0) -> 250000
B41: REGIONAL BOGOTA | C41: NOC_12 | D41: PAULA RUBIO | E41: ANYI MAYERLIE ORJUELA | F41: MELISA MARTINEZ | G41: =IF(L41>=80%,250000,IF(AND(L41>=60%,L41<80%),150000,0)) -> 250000 | H41: =+VLOOKUP(C41,Indicadores!B:C,2,FALSE) -> 1 | I41: =IF(H41>=60%,"Cumple","No Cumple") -> Cumple | J41: =+VLOOKUP(C41,Indicadores!B:F,5,FALSE) -> 1 | K41: =IF(J41>=60%,"Cumple","No Cumple") -> Cumple | L41: =+AVERAGE(H41,J41) -> 1 | M41: =+G41*$M$3 -> 150000 | N41: =+VLOOKUP(C41,Indicadores!B:M,12,FALSE) -> 0.9 | O41: =IF(N41>=60%,"Cumple","No Cumple") -> Cumple | P41: =IF(N41>80%,M41*100%,IF(AND(N41>=60%,N41<=79%),M41*60%,0)) -> 150000 | Q41: =+$G$6*$Q$3 -> 50000 | R41: =+IFERROR(VLOOKUP(C41,Indicadores!B:N,13,FALSE),0%) -> 0.88482229 | S41: =IF(R41>=70%,"Cumple","No Cumple") -> Cumple | T41: =IF(R41=80%,Q41*70%,IF(AND(R41>=81%,R41<=90%),Q41*80%,IF(AND(R41>=91%,R41<=95%),Q41*90%,IF(R41=96%,Q41*96%,IF(R41=97%,Q41*97%,IF(R41=98%,Q41*98%,IF(R41=99%,Q41*99%,IF(R41>=100%,Q41,0)))))))) -> 40000 | U41: =+G41*$U$3 -> 50000 | V41: =+VLOOKUP(C41,Indicadores!B:S,18,FALSE) -> 1 | W41: =IF(V41>=100%,"Cumple","No Cumple") -> Cumple | X41: =+IF(V41=100%,U41,0) -> 50000 | Y41: =IF(L41>=60%,"SI","NO") -> SI | Z41: =+IF(Y41="SI",P41+T41+X41,0) -> 240000
B42: REGIONAL BOGOTA | C42: NOC_13 | D42: PAULA RUBIO | E42: ANYI MAYERLIE ORJUELA | F42: MELISA MARTINEZ | G42: =IF(L42>=80%,250000,IF(AND(L42>=60%,L42<80%),150000,0)) -> 250000 | H42: =+VLOOKUP(C42,Indicadores!B:C,2,FALSE) -> 1 | I42: =IF(H42>=60%,"Cumple","No Cumple") -> Cumple | J42: =+VLOOKUP(C42,Indicadores!B:F,5,FALSE) -> 1 | K42: =IF(J42>=60%,"Cumple","No Cumple") -> Cumple | L42: =+AVERAGE(H42,J42) -> 1 | M42: =+G42*$M$3 -> 150000 | N42: =+VLOOKUP(C42,Indicadores!B:M,12,FALSE) -> 0.87878788 | O42: =IF(N42>=60%,"Cumple","No Cumple") -> Cumple | P42: =IF(N42>80%,M42*100%,IF(AND(N42>=60%,N42<=79%),M42*60%,0)) -> 150000 | Q42: =+$G$6*$Q$3 -> 50000 | R42: =+IFERROR(VLOOKUP(C42,Indicadores!B:N,13,FALSE),0%) -> 0.96249278 | S42: =IF(R42>=70%,"Cumple","No Cumple") -> Cumple | T42: =IF(R42=80%,Q42*70%,IF(AND(R42>=81%,R42<=90%),Q42*80%,IF(AND(R42>=91%,R42<=95%),Q42*90%,IF(R42>=96%,Q42*96%,IF(R42>=97%,Q42*97%,IF(R42>=98%,Q42*98%,IF(R42=99%,Q42*99%,IF(R42>=100%,Q42,0)))))))) -> 48000 | U42: =+G42*$U$3 -> 50000 | V42: =+VLOOKUP(C42,Indicadores!B:S,18,FALSE) -> 1 | W42: =IF(V42>=100%,"Cumple","No Cumple") -> Cumple | X42: =+IF(V42=100%,U42,0) -> 50000 | Y42: =IF(L42>=60%,"SI","NO") -> SI | Z42: =+IF(Y42="SI",P42+T42+X42,0) -> 248000
B43: REGIONAL BOGOTA | C43: NOC_14 | D43: PAULA RUBIO | E43: ANYI MAYERLIE ORJUELA | F43: MELISA MARTINEZ | G43: =IF(L43>=80%,250000,IF(AND(L43>=60%,L43<80%),150000,0)) -> 250000 | H43: =+VLOOKUP(C43,Indicadores!B:C,2,FALSE) -> 1 | I43: =IF(H43>=60%,"Cumple","No Cumple") -> Cumple | J43: =+VLOOKUP(C43,Indicadores!B:F,5,FALSE) -> 1 | K43: =IF(J43>=60%,"Cumple","No Cumple") -> Cumple | L43: =+AVERAGE(H43,J43) -> 1 | M43: =+G43*$M$3 -> 150000 | N43: =+VLOOKUP(C43,Indicadores!B:M,12,FALSE) -> 1 | O43: =IF(N43>=60%,"Cumple","No Cumple") -> Cumple | P43: =IF(N43>80%,M43*100%,IF(AND(N43>=60%,N43<=79%),M43*60%,0)) -> 150000 | Q43: =+$G$6*$Q$3 -> 50000 | R43: =+IFERROR(VLOOKUP(C43,Indicadores!B:N,13,FALSE),0%) -> 1.3033164 | S43: =IF(R43>=70%,"Cumple","No Cumple") -> Cumple | T43: =IF(R43=80%,Q43*70%,IF(AND(R43>=81%,R43<=90%),Q43*80%,IF(AND(R43>=91%,R43<=95%),Q43*90%,IF(R43=96%,Q43*96%,IF(R43=97%,Q43*97%,IF(R43=98%,Q43*98%,IF(R43=99%,Q43*99%,IF(R43>=100%,Q43,0)))))))) -> 50000 | U43: =+G43*$U$3 -> 50000 | V43: =+VLOOKUP(C43,Indicadores!B:S,18,FALSE) -> 1 | W43: =IF(V43>=100%,"Cumple","No Cumple") -> Cumple | X43: =+IF(V43=100%,U43,0) -> 50000 | Y43: =IF(L43>=60%,"SI","NO") -> SI | Z43: =+IF(Y43="SI",P43+T43+X43,0) -> 250000
B44: REGIONAL BOGOTA | C44: NOC_15 | D44: ALEJANDRO RODRIGUEZ | E44: ANYI MAYERLIE ORJUELA | F44: MELISA MARTINEZ | G44: =IF(L44>=80%,250000,IF(AND(L44>=60%,L44<80%),150000,0)) -> 250000 | H44: =+VLOOKUP(C44,Indicadores!B:C,2,FALSE) -> 1 | I44: =IF(H44>=60%,"Cumple","No Cumple") -> Cumple | J44: =+VLOOKUP(C44,Indicadores!B:F,5,FALSE) -> 1 | K44: =IF(J44>=60%,"Cumple","No Cumple") -> Cumple | L44: =+AVERAGE(H44,J44) -> 1 | M44: =+G44*$M$3 -> 150000 | N44: =+VLOOKUP(C44,Indicadores!B:M,12,FALSE) -> 0.83333333 | O44: =IF(N44>=60%,"Cumple","No Cumple") -> Cumple | P44: =IF(N44>80%,M44*100%,IF(AND(N44>=60%,N44<=79%),M44*60%,0)) -> 150000 | Q44: =+$G$6*$Q$3 -> 50000 | R44: =+IFERROR(VLOOKUP(C44,Indicadores!B:N,13,FALSE),0%) -> 0.91248682 | S44: =IF(R44>=70%,"Cumple","No Cumple") -> Cumple | T44: =IF(R44=80%,Q44*70%,IF(AND(R44>=81%,R44<=90%),Q44*80%,IF(AND(R44>=91%,R44<=95%),Q44*90%,IF(R44=96%,Q44*96%,IF(R44=97%,Q44*97%,IF(R44=98%,Q44*98%,IF(R44=99%,Q44*99%,IF(R44>=100%,Q44,0)))))))) -> 45000 | U44: =+G44*$U$3 -> 50000 | V44: =+VLOOKUP(C44,Indicadores!B:S,18,FALSE) -> 1 | W44: =IF(V44>=100%,"Cumple","No Cumple") -> Cumple | X44: =+IF(V44=100%,U44,0) -> 50000 | Y44: =IF(L44>=60%,"SI","NO") -> SI | Z44: =+IF(Y44="SI",P44+T44+X44,0) -> 245000
B45: REGIONAL BOGOTA | C45: NOC_16 | D45: PAULA RUBIO | E45: ANYI MAYERLIE ORJUELA | F45: MELISA MARTINEZ | G45: =IF(L45>=80%,250000,IF(AND(L45>=60%,L45<80%),150000,0)) -> 250000 | H45: =+VLOOKUP(C45,Indicadores!B:C,2,FALSE) -> 1 | I45: =IF(H45>=60%,"Cumple","No Cumple") -> Cumple | J45: =+VLOOKUP(C45,Indicadores!B:F,5,FALSE) -> 1 | K45: =IF(J45>=60%,"Cumple","No Cumple") -> Cumple | L45: =+AVERAGE(H45,J45) -> 1 | M45: =+G45*$M$3 -> 150000 | N45: =+VLOOKUP(C45,Indicadores!B:M,12,FALSE) -> 1 | O45: =IF(N45>=60%,"Cumple","No Cumple") -> Cumple | P45: =IF(N45>80%,M45*100%,IF(AND(N45>=60%,N45<=79%),M45*60%,0)) -> 150000 | Q45: =+$G$6*$Q$3 -> 50000 | R45: =+IFERROR(VLOOKUP(C45,Indicadores!B:N,13,FALSE),0%) -> 0.87276123 | S45: =IF(R45>=70%,"Cumple","No Cumple") -> Cumple | T45: =IF(R45=80%,Q45*70%,IF(AND(R45>=81%,R45<=90%),Q45*80%,IF(AND(R45>=91%,R45<=95%),Q45*90%,IF(R45=96%,Q45*96%,IF(R45=97%,Q45*97%,IF(R45=98%,Q45*98%,IF(R45=99%,Q45*99%,IF(R45>=100%,Q45,0)))))))) -> 40000 | U45: =+G45*$U$3 -> 50000 | V45: =+VLOOKUP(C45,Indicadores!B:S,18,FALSE) -> 1 | W45: =IF(V45>=100%,"Cumple","No Cumple") -> Cumple | X45: =+IF(V45=100%,U45,0) -> 50000 | Y45: =IF(L45>=60%,"SI","NO") -> SI | Z45: =+IF(Y45="SI",P45+T45+X45,0) -> 240000
B46: REGIONAL BOGOTA | C46: NOC_2 | D46: PAULA RUBIO | E46: ANYI MAYERLIE ORJUELA | F46: MELISA MARTINEZ | G46: =IF(L46>=80%,250000,IF(AND(L46>=60%,L46<80%),150000,0)) -> 250000 | H46: =+VLOOKUP(C46,Indicadores!B:C,2,FALSE) -> 1 | I46: =IF(H46>=60%,"Cumple","No Cumple") -> Cumple | J46: =+VLOOKUP(C46,Indicadores!B:F,5,FALSE) -> 1 | K46: =IF(J46>=60%,"Cumple","No Cumple") -> Cumple | L46: =+AVERAGE(H46,J46) -> 1 | M46: =+G46*$M$3 -> 150000 | N46: =+VLOOKUP(C46,Indicadores!B:M,12,FALSE) -> 1 | O46: =IF(N46>=60%,"Cumple","No Cumple") -> Cumple | P46: =IF(N46>80%,M46*100%,IF(AND(N46>=60%,N46<=79%),M46*60%,0)) -> 150000 | Q46: =+$G$6*$Q$3 -> 50000 | R46: =+IFERROR(VLOOKUP(C46,Indicadores!B:N,13,FALSE),0%) -> 1.0207812 | S46: =IF(R46>=70%,"Cumple","No Cumple") -> Cumple | T46: =IF(R46=80%,Q46*70%,IF(AND(R46>=81%,R46<=90%),Q46*80%,IF(AND(R46>=91%,R46<=95%),Q46*90%,IF(R46=96%,Q46*96%,IF(R46=97%,Q46*97%,IF(R46=98%,Q46*98%,IF(R46=99%,Q46*99%,IF(R46>=100%,Q46,0)))))))) -> 50000 | U46: =+G46*$U$3 -> 50000 | V46: =+VLOOKUP(C46,Indicadores!B:S,18,FALSE) -> 1 | W46: =IF(V46>=100%,"Cumple","No Cumple") -> Cumple | X46: =+IF(V46=100%,U46,0) -> 50000 | Y46: =IF(L46>=60%,"SI","NO") -> SI | Z46: =+IF(Y46="SI",P46+T46+X46,0) -> 250000
B47: REGIONAL BOGOTA | C47: NOC_3 | D47: PAULA RUBIO | E47: ANYI MAYERLIE ORJUELA | F47: MELISA MARTINEZ | G47: =IF(L47>=80%,250000,IF(AND(L47>=60%,L47<80%),150000,0)) -> 250000 | H47: =+VLOOKUP(C47,Indicadores!B:C,2,FALSE) -> 0.8 | I47: =IF(H47>=60%,"Cumple","No Cumple") -> Cumple | J47: =+VLOOKUP(C47,Indicadores!B:F,5,FALSE) -> 1 | K47: =IF(J47>=60%,"Cumple","No Cumple") -> Cumple | L47: =+AVERAGE(H47,J47) -> 0.9 | M47: =+G47*$M$3 -> 150000 | N47: 0.8 | O47: =IF(N47>=60%,"Cumple","No Cumple") -> Cumple | P47: =IF(N47>=80%,M47*100%,IF(AND(N47>=60%,N47<=79%),M47*60%,0)) -> 150000 | Q47: =+$G$6*$Q$3 -> 50000 | R47: =+IFERROR(VLOOKUP(C47,Indicadores!B:N,13,FALSE),0%) -> 0.98595944 | S47: =IF(R47>=70%,"Cumple","No Cumple") -> Cumple | T47: =IF(R47=80%,Q47*70%,IF(AND(R47>=81%,R47<=90%),Q47*80%,IF(AND(R47>=91%,R47<=95%),Q47*90%,IF(R47=96%,Q47*96%,IF(R47=97%,Q47*97%,IF(R47>=98%,Q47*98%,IF(R47=99%,Q47*99%,IF(R47>=100%,Q47,0)))))))) -> 49000 | U47: =+G47*$U$3 -> 50000 | V47: =+VLOOKUP(C47,Indicadores!B:S,18,FALSE) -> 1 | W47: =IF(V47>=100%,"Cumple","No Cumple") -> Cumple | X47: =+IF(V47=100%,U47,0) -> 50000 | Y47: =IF(L47>=60%,"SI","NO") -> SI | Z47: =+IF(Y47="SI",P47+T47+X47,0) -> 249000
B48: REGIONAL BOGOTA | C48: NOC_4 | D48: PAULA RUBIO | E48: ANYI MAYERLIE ORJUELA | F48: MELISA MARTINEZ | G48: =IF(L48>=80%,250000,IF(AND(L48>=60%,L48<80%),150000,0)) -> 250000 | H48: =+VLOOKUP(C48,Indicadores!B:C,2,FALSE) -> 1 | I48: =IF(H48>=60%,"Cumple","No Cumple") -> Cumple | J48: =+VLOOKUP(C48,Indicadores!B:F,5,FALSE) -> 1 | K48: =IF(J48>=60%,"Cumple","No Cumple") -> Cumple | L48: =+AVERAGE(H48,J48) -> 1 | M48: =+G48*$M$3 -> 150000 | N48: =+VLOOKUP(C48,Indicadores!B:M,12,FALSE) -> 0.97777778 | O48: =IF(N48>=60%,"Cumple","No Cumple") -> Cumple | P48: =IF(N48>80%,M48*100%,IF(AND(N48>=60%,N48<=79%),M48*60%,0)) -> 150000 | Q48: =+$G$6*$Q$3 -> 50000 | R48: =+IFERROR(VLOOKUP(C48,Indicadores!B:N,13,FALSE),0%) -> 0.98320594 | S48: =IF(R48>=70%,"Cumple","No Cumple") -> Cumple | T48: =IF(R48=80%,Q48*70%,IF(AND(R48>=81%,R48<=90%),Q48*80%,IF(AND(R48>=91%,R48<=95%),Q48*90%,IF(R48=96%,Q48*96%,IF(R48=97%,Q48*97%,IF(R48>=98%,Q48*98%,IF(R48=99%,Q48*99%,IF(R48>=100%,Q48,0)))))))) -> 49000 | U48: =+G48*$U$3 -> 50000 | V48: =+VLOOKUP(C48,Indicadores!B:S,18,FALSE) -> 1 | W48: =IF(V48>=100%,"Cumple","No Cumple") -> Cumple | X48: =+IF(V48=100%,U48,0) -> 50000 | Y48: =IF(L48>=60%,"SI","NO") -> SI | Z48: =+IF(Y48="SI",P48+T48+X48,0) -> 249000
B49: REGIONAL BOGOTA | C49: NOC_5 | D49: PAULA RUBIO | E49: ANYI MAYERLIE ORJUELA | F49: MELISA MARTINEZ | G49: =IF(L49>=80%,250000,IF(AND(L49>=60%,L49<80%),150000,0)) -> 250000 | H49: =+VLOOKUP(C49,Indicadores!B:C,2,FALSE) -> 1 | I49: =IF(H49>=60%,"Cumple","No Cumple") -> Cumple | J49: =+VLOOKUP(C49,Indicadores!B:F,5,FALSE) -> 1 | K49: =IF(J49>=60%,"Cumple","No Cumple") -> Cumple | L49: =+AVERAGE(H49,J49) -> 1 | M49: =+G49*$M$3 -> 150000 | N49: =+VLOOKUP(C49,Indicadores!B:M,12,FALSE) -> 1 | O49: =IF(N49>=60%,"Cumple","No Cumple") -> Cumple | P49: =IF(N49>80%,M49*100%,IF(AND(N49>=60%,N49<=79%),M49*60%,0)) -> 150000 | Q49: =+$G$6*$Q$3 -> 50000 | R49: =+IFERROR(VLOOKUP(C49,Indicadores!B:N,13,FALSE),0%) -> 1.0418462 | S49: =IF(R49>=70%,"Cumple","No Cumple") -> Cumple | T49: =IF(R49=80%,Q49*70%,IF(AND(R49>=81%,R49<=90%),Q49*80%,IF(AND(R49>=91%,R49<=95%),Q49*90%,IF(R49=96%,Q49*96%,IF(R49=97%,Q49*97%,IF(R49=98%,Q49*98%,IF(R49=99%,Q49*99%,IF(R49>=100%,Q49,0)))))))) -> 50000 | U49: =+G49*$U$3 -> 50000 | V49: =+VLOOKUP(C49,Indicadores!B:S,18,FALSE) -> 1 | W49: =IF(V49>=100%,"Cumple","No Cumple") -> Cumple | X49: =+IF(V49=100%,U49,0) -> 50000 | Y49: =IF(L49>=60%,"SI","NO") -> SI | Z49: =+IF(Y49="SI",P49+T49+X49,0) -> 250000
B50: REGIONAL BOGOTA | C50: NOC_6 | D50: PAULA RUBIO | E50: ANYI MAYERLIE ORJUELA | F50: MELISA MARTINEZ | G50: =IF(L50>=80%,250000,IF(AND(L50>=60%,L50<80%),150000,0)) -> 250000 | H50: =+VLOOKUP(C50,Indicadores!B:C,2,FALSE) -> 1 | I50: =IF(H50>=60%,"Cumple","No Cumple") -> Cumple | J50: =+VLOOKUP(C50,Indicadores!B:F,5,FALSE) -> 1 | K50: =IF(J50>=60%,"Cumple","No Cumple") -> Cumple | L50: =+AVERAGE(H50,J50) -> 1 | M50: =+G50*$M$3 -> 150000 | N50: =+VLOOKUP(C50,Indicadores!B:M,12,FALSE) -> 1 | O50: =IF(N50>=60%,"Cumple","No Cumple") -> Cumple | P50: =IF(N50>80%,M50*100%,IF(AND(N50>=60%,N50<=79%),M50*60%,0)) -> 150000 | Q50: =+$G$6*$Q$3 -> 50000 | R50: =+IFERROR(VLOOKUP(C50,Indicadores!B:N,13,FALSE),0%) -> 0.89061568 | S50: =IF(R50>=70%,"Cumple","No Cumple") -> Cumple | T50: =IF(R50=80%,Q50*70%,IF(AND(R50>=81%,R50<=90%),Q50*80%,IF(AND(R50>=91%,R50<=95%),Q50*90%,IF(R50=96%,Q50*96%,IF(R50=97%,Q50*97%,IF(R50=98%,Q50*98%,IF(R50=99%,Q50*99%,IF(R50>=100%,Q50,0)))))))) -> 40000 | U50: =+G50*$U$3 -> 50000 | V50: =+VLOOKUP(C50,Indicadores!B:S,18,FALSE) -> 1 | W50: =IF(V50>=100%,"Cumple","No Cumple") -> Cumple | X50: =+IF(V50=100%,U50,0) -> 50000 | Y50: =IF(L50>=60%,"SI","NO") -> SI | Z50: =+IF(Y50="SI",P50+T50+X50,0) -> 240000
B51: REGIONAL BOGOTA | C51: NOC_7 | D51: PAULA RUBIO | E51: ANYI MAYERLIE ORJUELA | F51: MELISA MARTINEZ | G51: =IF(L51>=80%,250000,IF(AND(L51>=60%,L51<80%),150000,0)) -> 250000 | H51: =+VLOOKUP(C51,Indicadores!B:C,2,FALSE) -> 1 | I51: =IF(H51>=60%,"Cumple","No Cumple") -> Cumple | J51: =+VLOOKUP(C51,Indicadores!B:F,5,FALSE) -> 1 | K51: =IF(J51>=60%,"Cumple","No Cumple") -> Cumple | L51: =+AVERAGE(H51,J51) -> 1 | M51: =+G51*$M$3 -> 150000 | N51: =+VLOOKUP(C51,Indicadores!B:M,12,FALSE) -> 0.96296296 | O51: =IF(N51>=60%,"Cumple","No Cumple") -> Cumple | P51: =IF(N51>80%,M51*100%,IF(AND(N51>=60%,N51<=79%),M51*60%,0)) -> 150000 | Q51: =+$G$6*$Q$3 -> 50000 | R51: =+IFERROR(VLOOKUP(C51,Indicadores!B:N,13,FALSE),0%) -> 1.0858986 | S51: =IF(R51>=70%,"Cumple","No Cumple") -> Cumple | T51: =IF(R51=80%,Q51*70%,IF(AND(R51>=81%,R51<=90%),Q51*80%,IF(AND(R51>=91%,R51<=95%),Q51*90%,IF(R51=96%,Q51*96%,IF(R51=97%,Q51*97%,IF(R51=98%,Q51*98%,IF(R51=99%,Q51*99%,IF(R51>=100%,Q51,0)))))))) -> 50000 | U51: =+G51*$U$3 -> 50000 | V51: =+VLOOKUP(C51,Indicadores!B:S,18,FALSE) -> 1 | W51: =IF(V51>=100%,"Cumple","No Cumple") -> Cumple | X51: =+IF(V51=100%,U51,0) -> 50000 | Y51: =IF(L51>=60%,"SI","NO") -> SI | Z51: =+IF(Y51="SI",P51+T51+X51,0) -> 250000
B52: REGIONAL BOGOTA | C52: NOC_8 | D52: PAULA RUBIO | E52: ANYI MAYERLIE ORJUELA | F52: MELISA MARTINEZ | G52: =IF(L52>=80%,250000,IF(AND(L52>=60%,L52<80%),150000,0)) -> 250000 | H52: =+VLOOKUP(C52,Indicadores!B:C,2,FALSE) -> 1 | I52: =IF(H52>=60%,"Cumple","No Cumple") -> Cumple | J52: =+VLOOKUP(C52,Indicadores!B:F,5,FALSE) -> 1 | K52: =IF(J52>=60%,"Cumple","No Cumple") -> Cumple | L52: =+AVERAGE(H52,J52) -> 1 | M52: =+G52*$M$3 -> 150000 | N52: =+VLOOKUP(C52,Indicadores!B:M,12,FALSE) -> 0.93939394 | O52: =IF(N52>=60%,"Cumple","No Cumple") -> Cumple | P52: =IF(N52>80%,M52*100%,IF(AND(N52>=60%,N52<=79%),M52*60%,0)) -> 150000 | Q52: =+$G$6*$Q$3 -> 50000 | R52: =+IFERROR(VLOOKUP(C52,Indicadores!B:N,13,FALSE),0%) -> 1.0893776 | S52: =IF(R52>=70%,"Cumple","No Cumple") -> Cumple | T52: =IF(R52=80%,Q52*70%,IF(AND(R52>=81%,R52<=90%),Q52*80%,IF(AND(R52>=91%,R52<=95%),Q52*90%,IF(R52=96%,Q52*96%,IF(R52=97%,Q52*97%,IF(R52=98%,Q52*98%,IF(R52=99%,Q52*99%,IF(R52>=100%,Q52,0)))))))) -> 50000 | U52: =+G52*$U$3 -> 50000 | V52: =+VLOOKUP(C52,Indicadores!B:S,18,FALSE) -> 1 | W52: =IF(V52>=100%,"Cumple","No Cumple") -> Cumple | X52: =+IF(V52=100%,U52,0) -> 50000 | Y52: =IF(L52>=60%,"SI","NO") -> SI | Z52: =+IF(Y52="SI",P52+T52+X52,0) -> 250000
B53: REGIONAL BOGOTA | C53: NOC_9 | D53: PAULA RUBIO | E53: ANYI MAYERLIE ORJUELA | F53: MELISA MARTINEZ | G53: =IF(L53>=80%,250000,IF(AND(L53>=60%,L53<80%),150000,0)) -> 250000 | H53: =+VLOOKUP(C53,Indicadores!B:C,2,FALSE) -> 1 | I53: =IF(H53>=60%,"Cumple","No Cumple") -> Cumple | J53: =+VLOOKUP(C53,Indicadores!B:F,5,FALSE) -> 1 | K53: =IF(J53>=60%,"Cumple","No Cumple") -> Cumple | L53: =+AVERAGE(H53,J53) -> 1 | M53: =+G53*$M$3 -> 150000 | N53: =+VLOOKUP(C53,Indicadores!B:M,12,FALSE) -> 0.94871795 | O53: =IF(N53>=60%,"Cumple","No Cumple") -> Cumple | P53: =IF(N53>80%,M53*100%,IF(AND(N53>=60%,N53<=79%),M53*60%,0)) -> 150000 | Q53: =+$G$6*$Q$3 -> 50000 | R53: =+IFERROR(VLOOKUP(C53,Indicadores!B:N,13,FALSE),0%) -> 1.0448137 | S53: =IF(R53>=70%,"Cumple","No Cumple") -> Cumple | T53: =IF(R53=80%,Q53*70%,IF(AND(R53>=81%,R53<=90%),Q53*80%,IF(AND(R53>=91%,R53<=95%),Q53*90%,IF(R53=96%,Q53*96%,IF(R53=97%,Q53*97%,IF(R53=98%,Q53*98%,IF(R53=99%,Q53*99%,IF(R53>=100%,Q53,0)))))))) -> 50000 | U53: =+G53*$U$3 -> 50000 | V53: =+VLOOKUP(C53,Indicadores!B:S,18,FALSE) -> 1 | W53: =IF(V53>=100%,"Cumple","No Cumple") -> Cumple | X53: =+IF(V53=100%,U53,0) -> 50000 | Y53: =IF(L53>=60%,"SI","NO") -> SI | Z53: =+IF(Y53="SI",P53+T53+X53,0) -> 250000
B54: REGIONAL ANTIOQUIA | C54: CALDAS_1 | D54: DEISY BERRIO | E54: OSPINO ARAUJO ALEXANDER | F54: MEJÍA BLANDÓN ASTRID KARINA | G54: =IF(L54>=80%,250000,IF(AND(L54>=60%,L54<80%),150000,0)) -> 250000 | H54: =+VLOOKUP(C54,Indicadores!B:C,2,FALSE) -> 1 | I54: =IF(H54>=60%,"Cumple","No Cumple") -> Cumple | J54: =+VLOOKUP(C54,Indicadores!B:F,5,FALSE) -> 1 | K54: =IF(J54>=60%,"Cumple","No Cumple") -> Cumple | L54: =+AVERAGE(H54,J54) -> 1 | M54: =+G54*$M$3 -> 150000 | N54: =+VLOOKUP(C54,Indicadores!B:M,12,FALSE) -> 1 | O54: =IF(N54>=60%,"Cumple","No Cumple") -> Cumple | P54: =IF(N54>80%,M54*100%,IF(AND(N54>=60%,N54<=79%),M54*60%,0)) -> 150000 | Q54: =+$G$6*$Q$3 -> 50000 | R54: =+IFERROR(VLOOKUP(C54,Indicadores!B:N,13,FALSE),0%) -> 1.4124247 | S54: =IF(R54>=70%,"Cumple","No Cumple") -> Cumple | T54: =IF(R54=80%,Q54*70%,IF(AND(R54>=81%,R54<=90%),Q54*80%,IF(AND(R54>=91%,R54<=95%),Q54*90%,IF(R54=96%,Q54*96%,IF(R54=97%,Q54*97%,IF(R54=98%,Q54*98%,IF(R54=99%,Q54*99%,IF(R54>=100%,Q54,0)))))))) -> 50000 | U54: =+G54*$U$3 -> 50000 | V54: =+VLOOKUP(C54,Indicadores!B:S,18,FALSE) -> 1 | W54: =IF(V54>=100%,"Cumple","No Cumple") -> Cumple | X54: =+IF(V54=100%,U54,0) -> 50000 | Y54: =IF(L54>=60%,"SI","NO") -> SI | Z54: =+IF(Y54="SI",P54+T54+X54,0) -> 250000
B55: REGIONAL ANTIOQUIA | C55: ENVIGADO_1 | D55: DEISY BERRIO | E55: OSPINO ARAUJO ALEXANDER | F55: MEJÍA BLANDÓN ASTRID KARINA | G55: =IF(L55>=80%,250000,IF(AND(L55>=60%,L55<80%),150000,0)) -> 250000 | H55: =+VLOOKUP(C55,Indicadores!B:C,2,FALSE) -> 1 | I55: =IF(H55>=60%,"Cumple","No Cumple") -> Cumple | J55: =+VLOOKUP(C55,Indicadores!B:F,5,FALSE) -> 1 | K55: =IF(J55>=60%,"Cumple","No Cumple") -> Cumple | L55: =+AVERAGE(H55,J55) -> 1 | M55: =+G55*$M$3 -> 150000 | N55: =+VLOOKUP(C55,Indicadores!B:M,12,FALSE) -> 0.91666667 | O55: =IF(N55>=60%,"Cumple","No Cumple") -> Cumple | P55: =IF(N55>80%,M55*100%,IF(AND(N55>=60%,N55<=79%),M55*60%,0)) -> 150000 | Q55: =+$G$6*$Q$3 -> 50000 | R55: =+IFERROR(VLOOKUP(C55,Indicadores!B:N,13,FALSE),0%) -> 1.2388963 | S55: =IF(R55>=70%,"Cumple","No Cumple") -> Cumple | T55: =IF(R55=80%,Q55*70%,IF(AND(R55>=81%,R55<=90%),Q55*80%,IF(AND(R55>=91%,R55<=95%),Q55*90%,IF(R55=96%,Q55*96%,IF(R55=97%,Q55*97%,IF(R55=98%,Q55*98%,IF(R55=99%,Q55*99%,IF(R55>=100%,Q55,0)))))))) -> 50000 | U55: =+G55*$U$3 -> 50000 | V55: =+VLOOKUP(C55,Indicadores!B:S,18,FALSE) -> 1 | W55: =IF(V55>=100%,"Cumple","No Cumple") -> Cumple | X55: =+IF(V55=100%,U55,0) -> 50000 | Y55: =IF(L55>=60%,"SI","NO") -> SI | Z55: =+IF(Y55="SI",P55+T55+X55,0) -> 250000
B56: REGIONAL ANTIOQUIA | C56: ENVIGADO_2 | D56: DEISY BERRIO | E56: OSPINO ARAUJO ALEXANDER | F56: MEJÍA BLANDÓN ASTRID KARINA | G56: =IF(L56>=80%,250000,IF(AND(L56>=60%,L56<80%),150000,0)) -> 250000 | H56: =+VLOOKUP(C56,Indicadores!B:C,2,FALSE) -> 1 | I56: =IF(H56>=60%,"Cumple","No Cumple") -> Cumple | J56: =+VLOOKUP(C56,Indicadores!B:F,5,FALSE) -> 1 | K56: =IF(J56>=60%,"Cumple","No Cumple") -> Cumple | L56: =+AVERAGE(H56,J56) -> 1 | M56: =+G56*$M$3 -> 150000 | N56: =+VLOOKUP(C56,Indicadores!B:M,12,FALSE) -> 0.83475783 | O56: =IF(N56>=60%,"Cumple","No Cumple") -> Cumple | P56: =IF(N56>80%,M56*100%,IF(AND(N56>=60%,N56<=79%),M56*60%,0)) -> 150000 | Q56: =+$G$6*$Q$3 -> 50000 | R56: =+IFERROR(VLOOKUP(C56,Indicadores!B:N,13,FALSE),0%) -> 0.97355096 | S56: =IF(R56>=70%,"Cumple","No Cumple") -> Cumple | T56: =IF(R56=80%,Q56*70%,IF(AND(R56>=81%,R56<=90%),Q56*80%,IF(AND(R56>=91%,R56<=95%),Q56*90%,IF(R56=96%,Q56*96%,IF(R56>=97%,Q56*97%,IF(R56>=98%,Q56*98%,IF(R56=99%,Q56*99%,IF(R56>=100%,Q56,0)))))))) -> 48500 | U56: =+G56*$U$3 -> 50000 | V56: =+VLOOKUP(C56,Indicadores!B:S,18,FALSE) -> 0.5 | W56: =IF(V56>=100%,"Cumple","No Cumple") -> No Cumple | X56: =+IF(V56=100%,U56,0) -> 0 | Y56: =IF(L56>=60%,"SI","NO") -> SI | Z56: =+IF(Y56="SI",P56+T56+X56,0) -> 198500
B57: REGIONAL ANTIOQUIA | C57: ENVIGADO_3 | D57: DEISY BERRIO | E57: OSPINO ARAUJO ALEXANDER | F57: MEJÍA BLANDÓN ASTRID KARINA | G57: =IF(L57>=80%,250000,IF(AND(L57>=60%,L57<80%),150000,0)) -> 250000 | H57: =+VLOOKUP(C57,Indicadores!B:C,2,FALSE) -> 0.85714286 | I57: =IF(H57>=60%,"Cumple","No Cumple") -> Cumple | J57: =+VLOOKUP(C57,Indicadores!B:F,5,FALSE) -> 0.85714286 | K57: =IF(J57>=60%,"Cumple","No Cumple") -> Cumple | L57: =+AVERAGE(H57,J57) -> 0.85714286 | M57: =+G57*$M$3 -> 150000 | N57: =+VLOOKUP(C57,Indicadores!B:M,12,FALSE) -> 0.88095238 | O57: =IF(N57>=60%,"Cumple","No Cumple") -> Cumple | P57: =IF(N57>80%,M57*100%,IF(AND(N57>=60%,N57<=79%),M57*60%,0)) -> 150000 | Q57: =+$G$6*$Q$3 -> 50000 | R57: =+IFERROR(VLOOKUP(C57,Indicadores!B:N,13,FALSE),0%) -> 1.0622557 | S57: =IF(R57>=70%,"Cumple","No Cumple") -> Cumple | T57: =IF(R57=80%,Q57*70%,IF(AND(R57>=81%,R57<=90%),Q57*80%,IF(AND(R57>=91%,R57<=95%),Q57*90%,IF(R57=96%,Q57*96%,IF(R57=97%,Q57*97%,IF(R57=98%,Q57*98%,IF(R57=99%,Q57*99%,IF(R57>=100%,Q57,0)))))))) -> 50000 | U57: =+G57*$U$3 -> 50000 | V57: =+VLOOKUP(C57,Indicadores!B:S,18,FALSE) -> 0.92857143 | W57: =IF(V57>=100%,"Cumple","No Cumple") -> No Cumple | X57: =+IF(V57=100%,U57,0) -> 0 | Y57: =IF(L57>=60%,"SI","NO") -> SI | Z57: =+IF(Y57="SI",P57+T57+X57,0) -> 200000
B58: REGIONAL ANTIOQUIA | C58: ITAGUI_1 | D58: DEISY BERRIO | E58: OSPINO ARAUJO ALEXANDER | F58: MEJÍA BLANDÓN ASTRID KARINA | G58: =IF(L58>=80%,250000,IF(AND(L58>=60%,L58<80%),150000,0)) -> 250000 | H58: =+VLOOKUP(C58,Indicadores!B:C,2,FALSE) -> 1 | I58: =IF(H58>=60%,"Cumple","No Cumple") -> Cumple | J58: =+VLOOKUP(C58,Indicadores!B:F,5,FALSE) -> 1 | K58: =IF(J58>=60%,"Cumple","No Cumple") -> Cumple | L58: =+AVERAGE(H58,J58) -> 1 | M58: =+G58*$M$3 -> 150000 | N58: =+VLOOKUP(C58,Indicadores!B:M,12,FALSE) -> 0.58080808 | O58: =IF(N58>=60%,"Cumple","No Cumple") -> No Cumple | P58: =IF(N58>80%,M58*100%,IF(AND(N58>=60%,N58<=79%),M58*60%,0)) -> 0 | Q58: =+$G$6*$Q$3 -> 50000 | R58: =+IFERROR(VLOOKUP(C58,Indicadores!B:N,13,FALSE),0%) -> 1.1909015 | S58: =IF(R58>=70%,"Cumple","No Cumple") -> Cumple | T58: =IF(R58=80%,Q58*70%,IF(AND(R58>=81%,R58<=90%),Q58*80%,IF(AND(R58>=91%,R58<=95%),Q58*90%,IF(R58=96%,Q58*96%,IF(R58=97%,Q58*97%,IF(R58=98%,Q58*98%,IF(R58=99%,Q58*99%,IF(R58>=100%,Q58,0)))))))) -> 50000 | U58: =+G58*$U$3 -> 50000 | V58: =+VLOOKUP(C58,Indicadores!B:S,18,FALSE) -> 1 | W58: =IF(V58>=100%,"Cumple","No Cumple") -> Cumple | X58: =+IF(V58=100%,U58,0) -> 50000 | Y58: =IF(L58>=60%,"SI","NO") -> SI | Z58: =+IF(Y58="SI",P58+T58+X58,0) -> 100000
B59: REGIONAL ANTIOQUIA | C59: MEDELLIN_1 | D59: DEISY BERRIO | E59: OSPINO ARAUJO ALEXANDER | F59: MEJÍA BLANDÓN ASTRID KARINA | G59: =IF(L59>=80%,250000,IF(AND(L59>=60%,L59<80%),150000,0)) -> 250000 | H59: =+VLOOKUP(C59,Indicadores!B:C,2,FALSE) -> 1 | I59: =IF(H59>=60%,"Cumple","No Cumple") -> Cumple | J59: =+VLOOKUP(C59,Indicadores!B:F,5,FALSE) -> 1 | K59: =IF(J59>=60%,"Cumple","No Cumple") -> Cumple | L59: =+AVERAGE(H59,J59) -> 1 | M59: =+G59*$M$3 -> 150000 | N59: =+VLOOKUP(C59,Indicadores!B:M,12,FALSE) -> 0.77777778 | O59: =IF(N59>=60%,"Cumple","No Cumple") -> Cumple | P59: =IF(N59>80%,M59*100%,IF(AND(N59>=60%,N59<=79%),M59*60%,0)) -> 90000 | Q59: =+$G$6*$Q$3 -> 50000 | R59: =+IFERROR(VLOOKUP(C59,Indicadores!B:N,13,FALSE),0%) -> 1.0043917 | S59: =IF(R59>=70%,"Cumple","No Cumple") -> Cumple | T59: =IF(R59=80%,Q59*70%,IF(AND(R59>=81%,R59<=90%),Q59*80%,IF(AND(R59>=91%,R59<=95%),Q59*90%,IF(R59=96%,Q59*96%,IF(R59=97%,Q59*97%,IF(R59=98%,Q59*98%,IF(R59=99%,Q59*99%,IF(R59>=100%,Q59,0)))))))) -> 50000 | U59: =+G59*$U$3 -> 50000 | V59: =+VLOOKUP(C59,Indicadores!B:S,18,FALSE) -> 1 | W59: =IF(V59>=100%,"Cumple","No Cumple") -> Cumple | X59: =+IF(V59=100%,U59,0) -> 50000 | Y59: =IF(L59>=60%,"SI","NO") -> SI | Z59: =+IF(Y59="SI",P59+T59+X59,0) -> 190000
B60: REGIONAL ANTIOQUIA | C60: MEDELLIN_13 | D60: DEISY BERRIO | E60: OSPINO ARAUJO ALEXANDER | F60: MEJÍA BLANDÓN ASTRID KARINA | G60: =IF(L60>=80%,250000,IF(AND(L60>=60%,L60<80%),150000,0)) -> 250000 | H60: =+VLOOKUP(C60,Indicadores!B:C,2,FALSE) -> 0.94871795 | I60: =IF(H60>=60%,"Cumple","No Cumple") -> Cumple | J60: =+VLOOKUP(C60,Indicadores!B:F,5,FALSE) -> 0.92307692 | K60: =IF(J60>=60%,"Cumple","No Cumple") -> Cumple | L60: =+AVERAGE(H60,J60) -> 0.93589744 | M60: =+G60*$M$3 -> 150000 | N60: =+VLOOKUP(C60,Indicadores!B:M,12,FALSE) -> 0.77207977 | O60: =IF(N60>=60%,"Cumple","No Cumple") -> Cumple | P60: =IF(N60>80%,M60*100%,IF(AND(N60>=60%,N60<=79%),M60*60%,0)) -> 90000 | Q60: =+$G$6*$Q$3 -> 50000 | R60: =+IFERROR(VLOOKUP(C60,Indicadores!B:N,13,FALSE),0%) -> 1.0166735 | S60: =IF(R60>=70%,"Cumple","No Cumple") -> Cumple | T60: =IF(R60=80%,Q60*70%,IF(AND(R60>=81%,R60<=90%),Q60*80%,IF(AND(R60>=91%,R60<=95%),Q60*90%,IF(R60=96%,Q60*96%,IF(R60=97%,Q60*97%,IF(R60=98%,Q60*98%,IF(R60=99%,Q60*99%,IF(R60>=100%,Q60,0)))))))) -> 50000 | U60: =+G60*$U$3 -> 50000 | V60: =+VLOOKUP(C60,Indicadores!B:S,18,FALSE) -> 0.46153846 | W60: =IF(V60>=100%,"Cumple","No Cumple") -> No Cumple | X60: =+IF(V60=100%,U60,0) -> 0 | Y60: =IF(L60>=60%,"SI","NO") -> SI | Z60: =+IF(Y60="SI",P60+T60+X60,0) -> 140000
B61: REGIONAL ANTIOQUIA | C61: MEDELLIN_14 | D61: DEISY BERRIO | E61: OSPINO ARAUJO ALEXANDER | F61: MEJÍA BLANDÓN ASTRID KARINA | G61: =IF(L61>=80%,250000,IF(AND(L61>=60%,L61<80%),150000,0)) -> 250000 | H61: =+VLOOKUP(C61,Indicadores!B:C,2,FALSE) -> 0.87878788 | I61: =IF(H61>=60%,"Cumple","No Cumple") -> Cumple | J61: =+VLOOKUP(C61,Indicadores!B:F,5,FALSE) -> 0.90909091 | K61: =IF(J61>=60%,"Cumple","No Cumple") -> Cumple | L61: =+AVERAGE(H61,J61) -> 0.89393939 | M61: =+G61*$M$3 -> 150000 | N61: =+VLOOKUP(C61,Indicadores!B:M,12,FALSE) -> 0.77005348 | O61: =IF(N61>=60%,"Cumple","No Cumple") -> Cumple | P61: =IF(N61>80%,M61*100%,IF(AND(N61>=60%,N61<=79%),M61*60%,0)) -> 90000 | Q61: =+$G$6*$Q$3 -> 50000 | R61: =+IFERROR(VLOOKUP(C61,Indicadores!B:N,13,FALSE),0%) -> 1.0386505 | S61: =IF(R61>=70%,"Cumple","No Cumple") -> Cumple | T61: =IF(R61=80%,Q61*70%,IF(AND(R61>=81%,R61<=90%),Q61*80%,IF(AND(R61>=91%,R61<=95%),Q61*90%,IF(R61=96%,Q61*96%,IF(R61=97%,Q61*97%,IF(R61=98%,Q61*98%,IF(R61=99%,Q61*99%,IF(R61>=100%,Q61,0)))))))) -> 50000 | U61: =+G61*$U$3 -> 50000 | V61: =+VLOOKUP(C61,Indicadores!B:S,18,FALSE) -> 0.81818182 | W61: =IF(V61>=100%,"Cumple","No Cumple") -> No Cumple | X61: =+IF(V61=100%,U61,0) -> 0 | Y61: =IF(L61>=60%,"SI","NO") -> SI | Z61: =+IF(Y61="SI",P61+T61+X61,0) -> 140000
B62: REGIONAL ANTIOQUIA | C62: MEDELLIN_3 | D62: DEISY BERRIO | E62: OSPINO ARAUJO ALEXANDER | F62: MEJÍA BLANDÓN ASTRID KARINA | G62: =IF(L62>=80%,250000,IF(AND(L62>=60%,L62<80%),150000,0)) -> 250000 | H62: =+VLOOKUP(C62,Indicadores!B:C,2,FALSE) -> 0.83333333 | I62: =IF(H62>=60%,"Cumple","No Cumple") -> Cumple | J62: =+VLOOKUP(C62,Indicadores!B:F,5,FALSE) -> 1 | K62: =IF(J62>=60%,"Cumple","No Cumple") -> Cumple | L62: =+AVERAGE(H62,J62) -> 0.91666667 | M62: =+G62*$M$3 -> 150000 | N62: =+VLOOKUP(C62,Indicadores!B:M,12,FALSE) -> 1 | O62: =IF(N62>=60%,"Cumple","No Cumple") -> Cumple | P62: =IF(N62>80%,M62*100%,IF(AND(N62>=60%,N62<=79%),M62*60%,0)) -> 150000 | Q62: =+$G$6*$Q$3 -> 50000 | R62: =+IFERROR(VLOOKUP(C62,Indicadores!B:N,13,FALSE),0%) -> 1.1155377 | S62: =IF(R62>=70%,"Cumple","No Cumple") -> Cumple | T62: =IF(R62=80%,Q62*70%,IF(AND(R62>=81%,R62<=90%),Q62*80%,IF(AND(R62>=91%,R62<=95%),Q62*90%,IF(R62=96%,Q62*96%,IF(R62=97%,Q62*97%,IF(R62=98%,Q62*98%,IF(R62=99%,Q62*99%,IF(R62>=100%,Q62,0)))))))) -> 50000 | U62: =+G62*$U$3 -> 50000 | V62: =+VLOOKUP(C62,Indicadores!B:S,18,FALSE) -> 1 | W62: =IF(V62>=100%,"Cumple","No Cumple") -> Cumple | X62: =+IF(V62=100%,U62,0) -> 50000 | Y62: =IF(L62>=60%,"SI","NO") -> SI | Z62: =+IF(Y62="SI",P62+T62+X62,0) -> 250000
B63: REGIONAL ANTIOQUIA | C63: MEDELLIN_6 | D63: DANIEL OSPINA | E63: OSPINO ARAUJO ALEXANDER | F63: MEJÍA BLANDÓN ASTRID KARINA | G63: =IF(L63>=80%,250000,IF(AND(L63>=60%,L63<80%),150000,0)) -> 150000 | H63: =+VLOOKUP(C63,Indicadores!B:C,2,FALSE) -> 0.81818182 | I63: =IF(H63>=60%,"Cumple","No Cumple") -> Cumple | J63: =+VLOOKUP(C63,Indicadores!B:F,5,FALSE) -> 0.72727273 | K63: =IF(J63>=60%,"Cumple","No Cumple") -> Cumple | L63: =+AVERAGE(H63,J63) -> 0.77272727 | M63: =+G63*$M$3 -> 90000 | N63: =+VLOOKUP(C63,Indicadores!B:M,12,FALSE) -> 0.81144781 | O63: =IF(N63>=60%,"Cumple","No Cumple") -> Cumple | P63: =IF(N63>80%,M63*100%,IF(AND(N63>=60%,N63<=79%),M63*60%,0)) -> 90000 | Q63: =+$G$6*$Q$3 -> 50000 | R63: =+IFERROR(VLOOKUP(C63,Indicadores!B:N,13,FALSE),0%) -> 0.98666315 | S63: =IF(R63>=70%,"Cumple","No Cumple") -> Cumple | T63: =IF(R63=80%,Q63*70%,IF(AND(R63>=81%,R63<=90%),Q63*80%,IF(AND(R63>=91%,R63<=95%),Q63*90%,IF(R63=96%,Q63*96%,IF(R63=97%,Q63*97%,IF(R63>=98%,Q63*98%,IF(R63=99%,Q63*99%,IF(R63>=100%,Q63,0)))))))) -> 49000 | U63: =+G63*$U$3 -> 30000 | V63: =+VLOOKUP(C63,Indicadores!B:S,18,FALSE) -> 0.90909091 | W63: =IF(V63>=100%,"Cumple","No Cumple") -> No Cumple | X63: =+IF(V63=100%,U63,0) -> 0 | Y63: =IF(L63>=60%,"SI","NO") -> SI | Z63: =+IF(Y63="SI",P63+T63+X63,0) -> 139000
B64: REGIONAL ANTIOQUIA | C64: MEDELLIN_7 | D64: DEISY BERRIO | E64: OSPINO ARAUJO ALEXANDER | F64: MEJÍA BLANDÓN ASTRID KARINA | G64: =IF(L64>=80%,250000,IF(AND(L64>=60%,L64<80%),150000,0)) -> 250000 | H64: =+VLOOKUP(C64,Indicadores!B:C,2,FALSE) -> 0.77777778 | I64: =IF(H64>=60%,"Cumple","No Cumple") -> Cumple | J64: =+VLOOKUP(C64,Indicadores!B:F,5,FALSE) -> 1 | K64: =IF(J64>=60%,"Cumple","No Cumple") -> Cumple | L64: =+AVERAGE(H64,J64) -> 0.88888889 | M64: =+G64*$M$3 -> 150000 | N64: =+VLOOKUP(C64,Indicadores!B:M,12,FALSE) -> 1 | O64: =IF(N64>=60%,"Cumple","No Cumple") -> Cumple | P64: =IF(N64>80%,M64*100%,IF(AND(N64>=60%,N64<=79%),M64*60%,0)) -> 150000 | Q64: =+$G$6*$Q$3 -> 50000 | R64: =+IFERROR(VLOOKUP(C64,Indicadores!B:N,13,FALSE),0%) -> 0.99284686 | S64: =IF(R64>=70%,"Cumple","No Cumple") -> Cumple | T64: =IF(R64=80%,Q64*70%,IF(AND(R64>=81%,R64<=90%),Q64*80%,IF(AND(R64>=91%,R64<=95%),Q64*90%,IF(R64=96%,Q64*96%,IF(R64=97%,Q64*97%,IF(R64>=98%,Q64*98%,IF(R64=99%,Q64*99%,IF(R64>=100%,Q64,0)))))))) -> 49000 | U64: =+G64*$U$3 -> 50000 | V64: =+VLOOKUP(C64,Indicadores!B:S,18,FALSE) -> 0.5 | W64: =IF(V64>=100%,"Cumple","No Cumple") -> No Cumple | X64: =+IF(V64=100%,U64,0) -> 0 | Y64: =IF(L64>=60%,"SI","NO") -> SI | Z64: =+IF(Y64="SI",P64+T64+X64,0) -> 199000
B65: REGIONAL ANTIOQUIA | C65: RIONEGRO_1 | D65: DEISY BERRIO | E65: OSPINO ARAUJO ALEXANDER | F65: MEJÍA BLANDÓN ASTRID KARINA | G65: =IF(L65>=80%,250000,IF(AND(L65>=60%,L65<80%),150000,0)) -> 250000 | H65: =+VLOOKUP(C65,Indicadores!B:C,2,FALSE) -> 0.875 | I65: =IF(H65>=60%,"Cumple","No Cumple") -> Cumple | J65: =+VLOOKUP(C65,Indicadores!B:F,5,FALSE) -> 0.875 | K65: =IF(J65>=60%,"Cumple","No Cumple") -> Cumple | L65: =+AVERAGE(H65,J65) -> 0.875 | M65: =+G65*$M$3 -> 150000 | N65: =+VLOOKUP(C65,Indicadores!B:M,12,FALSE) -> 0.55147059 | O65: =IF(N65>=60%,"Cumple","No Cumple") -> No Cumple | P65: =IF(N65>80%,M65*100%,IF(AND(N65>=60%,N65<=79%),M65*60%,0)) -> 0 | Q65: =+$G$6*$Q$3 -> 50000 | R65: =+IFERROR(VLOOKUP(C65,Indicadores!B:N,13,FALSE),0%) -> 1.024128 | S65: =IF(R65>=70%,"Cumple","No Cumple") -> Cumple | T65: =IF(R65=80%,Q65*70%,IF(AND(R65>=81%,R65<=90%),Q65*80%,IF(AND(R65>=91%,R65<=95%),Q65*90%,IF(R65=96%,Q65*96%,IF(R65=97%,Q65*97%,IF(R65=98%,Q65*98%,IF(R65=99%,Q65*99%,IF(R65>=100%,Q65,0)))))))) -> 50000 | U65: =+G65*$U$3 -> 50000 | V65: =+VLOOKUP(C65,Indicadores!B:S,18,FALSE) -> 0.9375 | W65: =IF(V65>=100%,"Cumple","No Cumple") -> No Cumple | X65: =+IF(V65=100%,U65,0) -> 0 | Y65: =IF(L65>=60%,"SI","NO") -> SI | Z65: =+IF(Y65="SI",P65+T65+X65,0) -> 50000
B66: REGIONAL ANTIOQUIA | C66: RIONEGRO_2 | D66: DEISY BERRIO | E66: OSPINO ARAUJO ALEXANDER | F66: MEJÍA BLANDÓN ASTRID KARINA | G66: =IF(L66>=80%,250000,IF(AND(L66>=60%,L66<80%),150000,0)) -> 250000 | H66: =+VLOOKUP(C66,Indicadores!B:C,2,FALSE) -> 1 | I66: =IF(H66>=60%,"Cumple","No Cumple") -> Cumple | J66: =+VLOOKUP(C66,Indicadores!B:F,5,FALSE) -> 1 | K66: =IF(J66>=60%,"Cumple","No Cumple") -> Cumple | L66: =+AVERAGE(H66,J66) -> 1 | M66: =+G66*$M$3 -> 150000 | N66: =+VLOOKUP(C66,Indicadores!B:M,12,FALSE) -> 0.89285714 | O66: =IF(N66>=60%,"Cumple","No Cumple") -> Cumple | P66: =IF(N66>80%,M66*100%,IF(AND(N66>=60%,N66<=79%),M66*60%,0)) -> 150000 | Q66: =+$G$6*$Q$3 -> 50000 | R66: =+IFERROR(VLOOKUP(C66,Indicadores!B:N,13,FALSE),0%) -> 0.87781535 | S66: =IF(R66>=70%,"Cumple","No Cumple") -> Cumple | T66: =IF(R66=80%,Q66*70%,IF(AND(R66>=81%,R66<=90%),Q66*80%,IF(AND(R66>=91%,R66<=95%),Q66*90%,IF(R66=96%,Q66*96%,IF(R66=97%,Q66*97%,IF(R66=98%,Q66*98%,IF(R66=99%,Q66*99%,IF(R66>=100%,Q66,0)))))))) -> 40000 | U66: =+G66*$U$3 -> 50000 | V66: =+VLOOKUP(C66,Indicadores!B:S,18,FALSE) -> 1 | W66: =IF(V66>=100%,"Cumple","No Cumple") -> Cumple | X66: =+IF(V66=100%,U66,0) -> 50000 | Y66: =IF(L66>=60%,"SI","NO") -> SI | Z66: =+IF(Y66="SI",P66+T66+X66,0) -> 240000
B67: REGIONAL ANTIOQUIA | C67: SABANETA_1 | D67: DEISY BERRIO | E67: OSPINO ARAUJO ALEXANDER | F67: MEJÍA BLANDÓN ASTRID KARINA | G67: =IF(L67>=80%,250000,IF(AND(L67>=60%,L67<80%),150000,0)) -> 150000 | H67: =+VLOOKUP(C67,Indicadores!B:C,2,FALSE) -> 0.77777778 | I67: =IF(H67>=60%,"Cumple","No Cumple") -> Cumple | J67: =+VLOOKUP(C67,Indicadores!B:F,5,FALSE) -> 0.77777778 | K67: =IF(J67>=60%,"Cumple","No Cumple") -> Cumple | L67: =+AVERAGE(H67,J67) -> 0.77777778 | M67: =+G67*$M$3 -> 90000 | N67: =+VLOOKUP(C67,Indicadores!B:M,12,FALSE) -> 0.85185185 | O67: =IF(N67>=60%,"Cumple","No Cumple") -> Cumple | P67: =IF(N67>80%,M67*100%,IF(AND(N67>=60%,N67<=79%),M67*60%,0)) -> 90000 | Q67: =+$G$6*$Q$3 -> 50000 | R67: 0.9 | S67: =IF(R67>=70%,"Cumple","No Cumple") -> Cumple | T67: =IF(R67=80%,Q67*70%,IF(AND(R67>=81%,R67<=90%),Q67*80%,IF(AND(R67>=91%,R67<=95%),Q67*90%,IF(R67>=96%,Q67*96%,IF(R67>=97%,Q67*97%,IF(R67>=98%,Q67*98%,IF(R67=99%,Q67*99%,IF(R67>=100%,Q67,0)))))))) -> 40000 | U67: =+G67*$U$3 -> 30000 | V67: =+VLOOKUP(C67,Indicadores!B:S,18,FALSE) -> 0.88888889 | W67: =IF(V67>=100%,"Cumple","No Cumple") -> No Cumple | X67: =+IF(V67=100%,U67,0) -> 0 | Y67: =IF(L67>=60%,"SI","NO") -> SI | Z67: =+IF(Y67="SI",P67+T67+X67,0) -> 130000
B68: REGIONAL ATLANTICO | C68: BARRANQUILLA_1 | D68: KELLY DE LA TORRE | E68: OSPINO ARAUJO ALEXANDER | F68: PEREZ ZAGARRA AUGUSTO EDUARDO | G68: =IF(L68>=80%,250000,IF(AND(L68>=60%,L68<80%),150000,0)) -> 250000 | H68: =+VLOOKUP(C68,Indicadores!B:C,2,FALSE) -> 1 | I68: =IF(H68>=60%,"Cumple","No Cumple") -> Cumple | J68: =+VLOOKUP(C68,Indicadores!B:F,5,FALSE) -> 1 | K68: =IF(J68>=60%,"Cumple","No Cumple") -> Cumple | L68: =+AVERAGE(H68,J68) -> 1 | M68: =+G68*$M$3 -> 150000 | N68: =+VLOOKUP(C68,Indicadores!B:M,12,FALSE) -> 0.93589744 | O68: =IF(N68>=60%,"Cumple","No Cumple") -> Cumple | P68: =IF(N68>80%,M68*100%,IF(AND(N68>=60%,N68<=79%),M68*60%,0)) -> 150000 | Q68: =+$G$6*$Q$3 -> 50000 | R68: =+IFERROR(VLOOKUP(C68,Indicadores!B:N,13,FALSE),0%) -> 1.0046021 | S68: =IF(R68>=70%,"Cumple","No Cumple") -> Cumple | T68: =IF(R68=80%,Q68*70%,IF(AND(R68>=81%,R68<=90%),Q68*80%,IF(AND(R68>=91%,R68<=95%),Q68*90%,IF(R68=96%,Q68*96%,IF(R68=97%,Q68*97%,IF(R68=98%,Q68*98%,IF(R68=99%,Q68*99%,IF(R68>=100%,Q68,0)))))))) -> 50000 | U68: =+G68*$U$3 -> 50000 | V68: =+VLOOKUP(C68,Indicadores!B:S,18,FALSE) -> 0.5 | W68: =IF(V68>=100%,"Cumple","No Cumple") -> No Cumple | X68: =+IF(V68=100%,U68,0) -> 0 | Y68: =IF(L68>=60%,"SI","NO") -> SI | Z68: =+IF(Y68="SI",P68+T68+X68,0) -> 200000
B69: REGIONAL ATLANTICO | C69: BARRANQUILLA_2 | D69: KELLY DE LA TORRE | E69: OSPINO ARAUJO ALEXANDER | F69: PEREZ ZAGARRA AUGUSTO EDUARDO | G69: =IF(L69>=80%,250000,IF(AND(L69>=60%,L69<80%),150000,0)) -> 250000 | H69: =+VLOOKUP(C69,Indicadores!B:C,2,FALSE) -> 1 | I69: =IF(H69>=60%,"Cumple","No Cumple") -> Cumple | J69: =+VLOOKUP(C69,Indicadores!B:F,5,FALSE) -> 1 | K69: =IF(J69>=60%,"Cumple","No Cumple") -> Cumple | L69: =+AVERAGE(H69,J69) -> 1 | M69: =+G69*$M$3 -> 150000 | N69: =+VLOOKUP(C69,Indicadores!B:M,12,FALSE) -> 0.69035088 | O69: =IF(N69>=60%,"Cumple","No Cumple") -> Cumple | P69: =IF(N69>80%,M69*100%,IF(AND(N69>=60%,N69<=79%),M69*60%,0)) -> 90000 | Q69: =+$G$6*$Q$3 -> 50000 | R69: =+IFERROR(VLOOKUP(C69,Indicadores!B:N,13,FALSE),0%) -> 0.99603977 | S69: =IF(R69>=70%,"Cumple","No Cumple") -> Cumple | T69: =IF(R69=80%,Q69*70%,IF(AND(R69>=81%,R69<=90%),Q69*80%,IF(AND(R69>=91%,R69<=95%),Q69*90%,IF(R69=96%,Q69*96%,IF(R69=97%,Q69*97%,IF(R69>=98%,Q69*98%,IF(R69=99%,Q69*99%,IF(R69>=100%,Q69,0)))))))) -> 49000 | U69: =+G69*$U$3 -> 50000 | V69: =+VLOOKUP(C69,Indicadores!B:S,18,FALSE) -> 0.5 | W69: =IF(V69>=100%,"Cumple","No Cumple") -> No Cumple | X69: =+IF(V69=100%,U69,0) -> 0 | Y69: =IF(L69>=60%,"SI","NO") -> SI | Z69: =+IF(Y69="SI",P69+T69+X69,0) -> 139000
B70: REGIONAL ATLANTICO | C70: BARRANQUILLA_3 | D70: KELLY DE LA TORRE | E70: OSPINO ARAUJO ALEXANDER | F70: PEREZ ZAGARRA AUGUSTO EDUARDO | G70: =IF(L70>=80%,250000,IF(AND(L70>=60%,L70<80%),150000,0)) -> 250000 | H70: =+VLOOKUP(C70,Indicadores!B:C,2,FALSE) -> 0.94444444 | I70: =IF(H70>=60%,"Cumple","No Cumple") -> Cumple | J70: =+VLOOKUP(C70,Indicadores!B:F,5,FALSE) -> 0.91666667 | K70: =IF(J70>=60%,"Cumple","No Cumple") -> Cumple | L70: =+AVERAGE(H70,J70) -> 0.93055556 | M70: =+G70*$M$3 -> 150000 | N70: =+VLOOKUP(C70,Indicadores!B:M,12,FALSE) -> 0.94722222 | O70: =IF(N70>=60%,"Cumple","No Cumple") -> Cumple | P70: =IF(N70>80%,M70*100%,IF(AND(N70>=60%,N70<=79%),M70*60%,0)) -> 150000 | Q70: =+$G$6*$Q$3 -> 50000 | R70: =+IFERROR(VLOOKUP(C70,Indicadores!B:N,13,FALSE),0%) -> 1.1022421 | S70: =IF(R70>=70%,"Cumple","No Cumple") -> Cumple | T70: =IF(R70=80%,Q70*70%,IF(AND(R70>=81%,R70<=90%),Q70*80%,IF(AND(R70>=91%,R70<=95%),Q70*90%,IF(R70=96%,Q70*96%,IF(R70=97%,Q70*97%,IF(R70=98%,Q70*98%,IF(R70=99%,Q70*99%,IF(R70>=100%,Q70,0)))))))) -> 50000 | U70: =+G70*$U$3 -> 50000 | V70: =+VLOOKUP(C70,Indicadores!B:S,18,FALSE) -> 0.47916667 | W70: =IF(V70>=100%,"Cumple","No Cumple") -> No Cumple | X70: =+IF(V70=100%,U70,0) -> 0 | Y70: =IF(L70>=60%,"SI","NO") -> SI | Z70: =+IF(Y70="SI",P70+T70+X70,0) -> 200000
B71: REGIONAL ATLANTICO | C71: BARRANQUILLA_4 | D71: KELLY DE LA TORRE | E71: OSPINO ARAUJO ALEXANDER | F71: PEREZ ZAGARRA AUGUSTO EDUARDO | G71: =IF(L71>=80%,250000,IF(AND(L71>=60%,L71<80%),150000,0)) -> 250000 | H71: =+VLOOKUP(C71,Indicadores!B:C,2,FALSE) -> 0.81944444 | I71: =IF(H71>=60%,"Cumple","No Cumple") -> Cumple | J71: =+VLOOKUP(C71,Indicadores!B:F,5,FALSE) -> 0.91666667 | K71: =IF(J71>=60%,"Cumple","No Cumple") -> Cumple | L71: =+AVERAGE(H71,J71) -> 0.86805556 | M71: =+G71*$M$3 -> 150000 | N71: =+VLOOKUP(C71,Indicadores!B:M,12,FALSE) -> 0.89011955 | O71: =IF(N71>=60%,"Cumple","No Cumple") -> Cumple | P71: =IF(N71>80%,M71*100%,IF(AND(N71>=60%,N71<=79%),M71*60%,0)) -> 150000 | Q71: =+$G$6*$Q$3 -> 50000 | R71: =+IFERROR(VLOOKUP(C71,Indicadores!B:N,13,FALSE),0%) -> 0.99107253 | S71: =IF(R71>=70%,"Cumple","No Cumple") -> Cumple | T71: =IF(R71=80%,Q71*70%,IF(AND(R71>=81%,R71<=90%),Q71*80%,IF(AND(R71>=91%,R71<=95%),Q71*90%,IF(R71=96%,Q71*96%,IF(R71=97%,Q71*97%,IF(R71>=98%,Q71*98%,IF(R71=99%,Q71*99%,IF(R71>=100%,Q71,0)))))))) -> 49000 | U71: =+G71*$U$3 -> 50000 | V71: =+VLOOKUP(C71,Indicadores!B:S,18,FALSE) -> 0.4375 | W71: =IF(V71>=100%,"Cumple","No Cumple") -> No Cumple | X71: =+IF(V71=100%,U71,0) -> 0 | Y71: =IF(L71>=60%,"SI","NO") -> SI | Z71: =+IF(Y71="SI",P71+T71+X71,0) -> 199000
B72: REGIONAL ATLANTICO | C72: BARRANQUILLA_5 | D72: KELLY DE LA TORRE | E72: OSPINO ARAUJO ALEXANDER | F72: PEREZ ZAGARRA AUGUSTO EDUARDO | G72: =IF(L72>=80%,250000,IF(AND(L72>=60%,L72<80%),150000,0)) -> 250000 | H72: =+VLOOKUP(C72,Indicadores!B:C,2,FALSE) -> 1 | I72: =IF(H72>=60%,"Cumple","No Cumple") -> Cumple | J72: =+VLOOKUP(C72,Indicadores!B:F,5,FALSE) -> 1 | K72: =IF(J72>=60%,"Cumple","No Cumple") -> Cumple | L72: =+AVERAGE(H72,J72) -> 1 | M72: =+G72*$M$3 -> 150000 | N72: =+VLOOKUP(C72,Indicadores!B:M,12,FALSE) -> 0.86954365 | O72: =IF(N72>=60%,"Cumple","No Cumple") -> Cumple | P72: =IF(N72>80%,M72*100%,IF(AND(N72>=60%,N72<=79%),M72*60%,0)) -> 150000 | Q72: =+$G$6*$Q$3 -> 50000 | R72: =+IFERROR(VLOOKUP(C72,Indicadores!B:N,13,FALSE),0%) -> 0.92235928 | S72: =IF(R72>=70%,"Cumple","No Cumple") -> Cumple | T72: =IF(R72=80%,Q72*70%,IF(AND(R72>=81%,R72<=90%),Q72*80%,IF(AND(R72>=91%,R72<=95%),Q72*90%,IF(R72=96%,Q72*96%,IF(R72=97%,Q72*97%,IF(R72=98%,Q72*98%,IF(R72=99%,Q72*99%,IF(R72>=100%,Q72,0)))))))) -> 45000 | U72: =+G72*$U$3 -> 50000 | V72: =+VLOOKUP(C72,Indicadores!B:S,18,FALSE) -> 1 | W72: =IF(V72>=100%,"Cumple","No Cumple") -> Cumple | X72: =+IF(V72=100%,U72,0) -> 50000 | Y72: =IF(L72>=60%,"SI","NO") -> SI | Z72: =+IF(Y72="SI",P72+T72+X72,0) -> 245000
B73: REGIONAL COSTA PERIFERIA | C73: CARTAGENA_1 | D73: KELLY DE LA TORRE | E73: OSPINO ARAUJO ALEXANDER | F73: PEREZ ZAGARRA AUGUSTO EDUARDO | G73: =IF(L73>=80%,250000,IF(AND(L73>=60%,L73<80%),150000,0)) -> 150000 | H73: =+VLOOKUP(C73,Indicadores!B:C,2,FALSE) -> 0.65333333 | I73: =IF(H73>=60%,"Cumple","No Cumple") -> Cumple | J73: =+VLOOKUP(C73,Indicadores!B:F,5,FALSE) -> 0.64 | K73: =IF(J73>=60%,"Cumple","No Cumple") -> Cumple | L73: =+AVERAGE(H73,J73) -> 0.64666667 | M73: =+G73*$M$3 -> 90000 | N73: =+VLOOKUP(C73,Indicadores!B:M,12,FALSE) -> 0.54077519 | O73: =IF(N73>=60%,"Cumple","No Cumple") -> No Cumple | P73: =IF(N73>80%,M73*100%,IF(AND(N73>=60%,N73<=79%),M73*60%,0)) -> 0 | Q73: =+$G$6*$Q$3 -> 50000 | R73: =+IFERROR(VLOOKUP(C73,Indicadores!B:N,13,FALSE),0%) -> 0.89122277 | S73: =IF(R73>=70%,"Cumple","No Cumple") -> Cumple | T73: =IF(R73=80%,Q73*70%,IF(AND(R73>=81%,R73<=90%),Q73*80%,IF(AND(R73>=91%,R73<=95%),Q73*90%,IF(R73=96%,Q73*96%,IF(R73=97%,Q73*97%,IF(R73=98%,Q73*98%,IF(R73=99%,Q73*99%,IF(R73>=100%,Q73,0)))))))) -> 40000 | U73: =+G73*$U$3 -> 30000 | V73: =+VLOOKUP(C73,Indicadores!B:S,18,FALSE) -> 0.32 | W73: =IF(V73>=100%,"Cumple","No Cumple") -> No Cumple | X73: =+IF(V73=100%,U73,0) -> 0 | Y73: =IF(L73>=60%,"SI","NO") -> SI | Z73: =+IF(Y73="SI",P73+T73+X73,0) -> 40000
B74: REGIONAL COSTA PERIFERIA | C74: CARTAGENA_2 | D74: KELLY DE LA TORRE | E74: OSPINO ARAUJO ALEXANDER | F74: PEREZ ZAGARRA AUGUSTO EDUARDO | G74: =IF(L74>=80%,250000,IF(AND(L74>=60%,L74<80%),150000,0)) -> 250000 | H74: =+VLOOKUP(C74,Indicadores!B:C,2,FALSE) -> 1 | I74: =IF(H74>=60%,"Cumple","No Cumple") -> Cumple | J74: =+VLOOKUP(C74,Indicadores!B:F,5,FALSE) -> 1 | K74: =IF(J74>=60%,"Cumple","No Cumple") -> Cumple | L74: =+AVERAGE(H74,J74) -> 1 | M74: =+G74*$M$3 -> 150000 | N74: =+VLOOKUP(C74,Indicadores!B:M,12,FALSE) -> 0.72463768 | O74: =IF(N74>=60%,"Cumple","No Cumple") -> Cumple | P74: =IF(N74>80%,M74*100%,IF(AND(N74>=60%,N74<=79%),M74*60%,0)) -> 90000 | Q74: =+$G$6*$Q$3 -> 50000 | R74: =+IFERROR(VLOOKUP(C74,Indicadores!B:N,13,FALSE),0%) -> 1.034718 | S74: =IF(R74>=70%,"Cumple","No Cumple") -> Cumple | T74: =IF(R74=80%,Q74*70%,IF(AND(R74>=81%,R74<=90%),Q74*80%,IF(AND(R74>=91%,R74<=95%),Q74*90%,IF(R74=96%,Q74*96%,IF(R74=97%,Q74*97%,IF(R74=98%,Q74*98%,IF(R74=99%,Q74*99%,IF(R74>=100%,Q74,0)))))))) -> 50000 | U74: =+G74*$U$3 -> 50000 | V74: =+VLOOKUP(C74,Indicadores!B:S,18,FALSE) -> 0.5 | W74: =IF(V74>=100%,"Cumple","No Cumple") -> No Cumple | X74: =+IF(V74=100%,U74,0) -> 0 | Y74: =IF(L74>=60%,"SI","NO") -> SI | Z74: =+IF(Y74="SI",P74+T74+X74,0) -> 140000
B75: REGIONAL COSTA PERIFERIA | C75: CARTAGENA_3 | D75: KELLY DE LA TORRE | E75: OSPINO ARAUJO ALEXANDER | F75: PEREZ ZAGARRA AUGUSTO EDUARDO | G75: =IF(L75>=80%,250000,IF(AND(L75>=60%,L75<80%),150000,0)) -> 250000 | H75: =+VLOOKUP(C75,Indicadores!B:C,2,FALSE) -> 1 | I75: =IF(H75>=60%,"Cumple","No Cumple") -> Cumple | J75: =+VLOOKUP(C75,Indicadores!B:F,5,FALSE) -> 0.90909091 | K75: =IF(J75>=60%,"Cumple","No Cumple") -> Cumple | L75: =+AVERAGE(H75,J75) -> 0.95454545 | M75: =+G75*$M$3 -> 150000 | N75: =+VLOOKUP(C75,Indicadores!B:M,12,FALSE) -> 0.72856222 | O75: =IF(N75>=60%,"Cumple","No Cumple") -> Cumple | P75: =IF(N75>80%,M75*100%,IF(AND(N75>=60%,N75<=79%),M75*60%,0)) -> 90000 | Q75: =+$G$6*$Q$3 -> 50000 | R75: =+IFERROR(VLOOKUP(C75,Indicadores!B:N,13,FALSE),0%) -> 0.85339122 | S75: =IF(R75>=70%,"Cumple","No Cumple") -> Cumple | T75: =IF(R75=80%,Q75*70%,IF(AND(R75>=81%,R75<=90%),Q75*80%,IF(AND(R75>=91%,R75<=95%),Q75*90%,IF(R75=96%,Q75*96%,IF(R75=97%,Q75*97%,IF(R75=98%,Q75*98%,IF(R75=99%,Q75*99%,IF(R75>=100%,Q75,0)))))))) -> 40000 | U75: =+G75*$U$3 -> 50000 | V75: =+VLOOKUP(C75,Indicadores!B:S,18,FALSE) -> 0.5 | W75: =IF(V75>=100%,"Cumple","No Cumple") -> No Cumple | X75: =+IF(V75=100%,U75,0) -> 0 | Y75: =IF(L75>=60%,"SI","NO") -> SI | Z75: =+IF(Y75="SI",P75+T75+X75,0) -> 130000
B76: REGIONAL COSTA PERIFERIA | C76: SANTA MARTA_1 | D76: KELLY DE LA TORRE | E76: OSPINO ARAUJO ALEXANDER | F76: PEREZ ZAGARRA AUGUSTO EDUARDO | G76: =IF(L76>=80%,250000,IF(AND(L76>=60%,L76<80%),150000,0)) -> 250000 | H76: =+VLOOKUP(C76,Indicadores!B:C,2,FALSE) -> 1 | I76: =IF(H76>=60%,"Cumple","No Cumple") -> Cumple | J76: =+VLOOKUP(C76,Indicadores!B:F,5,FALSE) -> 1 | K76: =IF(J76>=60%,"Cumple","No Cumple") -> Cumple | L76: =+AVERAGE(H76,J76) -> 1 | M76: =+G76*$M$3 -> 150000 | N76: =+VLOOKUP(C76,Indicadores!B:M,12,FALSE) -> 1 | O76: =IF(N76>=60%,"Cumple","No Cumple") -> Cumple | P76: =IF(N76>80%,M76*100%,IF(AND(N76>=60%,N76<=79%),M76*60%,0)) -> 150000 | Q76: =+$G$6*$Q$3 -> 50000 | R76: =+IFERROR(VLOOKUP(C76,Indicadores!B:N,13,FALSE),0%) -> 1.1574482 | S76: =IF(R76>=70%,"Cumple","No Cumple") -> Cumple | T76: =IF(R76=80%,Q76*70%,IF(AND(R76>=81%,R76<=90%),Q76*80%,IF(AND(R76>=91%,R76<=95%),Q76*90%,IF(R76=96%,Q76*96%,IF(R76=97%,Q76*97%,IF(R76=98%,Q76*98%,IF(R76=99%,Q76*99%,IF(R76>=100%,Q76,0)))))))) -> 50000 | U76: =+G76*$U$3 -> 50000 | V76: =+VLOOKUP(C76,Indicadores!B:S,18,FALSE) -> 0.5 | W76: =IF(V76>=100%,"Cumple","No Cumple") -> No Cumple | X76: =+IF(V76=100%,U76,0) -> 0 | Y76: =IF(L76>=60%,"SI","NO") -> SI | Z76: =+IF(Y76="SI",P76+T76+X76,0) -> 200000
B77: REGIONAL COSTA PERIFERIA | C77: SANTA MARTA_2 | D77: KELLY DE LA TORRE | E77: OSPINO ARAUJO ALEXANDER | F77: PEREZ ZAGARRA AUGUSTO EDUARDO | G77: =IF(L77>=80%,250000,IF(AND(L77>=60%,L77<80%),150000,0)) -> 250000 | H77: =+VLOOKUP(C77,Indicadores!B:C,2,FALSE) -> 0.98245614 | I77: =IF(H77>=60%,"Cumple","No Cumple") -> Cumple | J77: =+VLOOKUP(C77,Indicadores!B:F,5,FALSE) -> 1 | K77: =IF(J77>=60%,"Cumple","No Cumple") -> Cumple | L77: =+AVERAGE(H77,J77) -> 0.99122807 | M77: =+G77*$M$3 -> 150000 | N77: =+VLOOKUP(C77,Indicadores!B:M,12,FALSE) -> 1 | O77: =IF(N77>=60%,"Cumple","No Cumple") -> Cumple | P77: =IF(N77>80%,M77*100%,IF(AND(N77>=60%,N77<=79%),M77*60%,0)) -> 150000 | Q77: =+$G$6*$Q$3 -> 50000 | R77: =+IFERROR(VLOOKUP(C77,Indicadores!B:N,13,FALSE),0%) -> 0.76111264 | S77: =IF(R77>=80%,"Cumple","No Cumple") -> No Cumple | T77: =IF(R77>=70%,Q77*70%,IF(AND(R77>=81%,R77<=90%),Q77*80%,IF(AND(R77>=91%,R77<=95%),Q77*90%,IF(R77=96%,Q77*96%,IF(R77=97%,Q77*97%,IF(R77=98%,Q77*98%,IF(R77=99%,Q77*99%,IF(R77>=100%,Q77,0)))))))) -> 35000 | U77: =+G77*$U$3 -> 50000 | V77: =+VLOOKUP(C77,Indicadores!B:S,18,FALSE) -> 0.47368421 | W77: =IF(V77>=100%,"Cumple","No Cumple") -> No Cumple | X77: =+IF(V77=100%,U77,0) -> 0 | Y77: =IF(L77>=60%,"SI","NO") -> SI | Z77: =+IF(Y77="SI",P77+T77+X77,0) -> 185000
B78: REGIONAL ATLANTICO | C78: SOLEDAD_1 | D78: KELLY DE LA TORRE | E78: OSPINO ARAUJO ALEXANDER | F78: PEREZ ZAGARRA AUGUSTO EDUARDO | G78: =IF(L78>=80%,250000,IF(AND(L78>=60%,L78<80%),150000,0)) -> 250000 | H78: =+VLOOKUP(C78,Indicadores!B:C,2,FALSE) -> 1 | I78: =IF(H78>=60%,"Cumple","No Cumple") -> Cumple | J78: =+VLOOKUP(C78,Indicadores!B:F,5,FALSE) -> 1 | K78: =IF(J78>=60%,"Cumple","No Cumple") -> Cumple | L78: =+AVERAGE(H78,J78) -> 1 | M78: =+G78*$M$3 -> 150000 | N78: =+VLOOKUP(C78,Indicadores!B:M,12,FALSE) -> 0.65045189 | O78: =IF(N78>=60%,"Cumple","No Cumple") -> Cumple | P78: =IF(N78>80%,M78*100%,IF(AND(N78>=60%,N78<=79%),M78*60%,0)) -> 90000 | Q78: =+$G$6*$Q$3 -> 50000 | R78: =+IFERROR(VLOOKUP(C78,Indicadores!B:N,13,FALSE),0%) -> 1.231504 | S78: =IF(R78>=70%,"Cumple","No Cumple") -> Cumple | T78: =IF(R78=80%,Q78*70%,IF(AND(R78>=81%,R78<=90%),Q78*80%,IF(AND(R78>=91%,R78<=95%),Q78*90%,IF(R78=96%,Q78*96%,IF(R78=97%,Q78*97%,IF(R78=98%,Q78*98%,IF(R78=99%,Q78*99%,IF(R78>=100%,Q78,0)))))))) -> 50000 | U78: =+G78*$U$3 -> 50000 | V78: =+VLOOKUP(C78,Indicadores!B:S,18,FALSE) -> 0.5 | W78: =IF(V78>=100%,"Cumple","No Cumple") -> No Cumple | X78: =+IF(V78=100%,U78,0) -> 0 | Y78: =IF(L78>=60%,"SI","NO") -> SI | Z78: =+IF(Y78="SI",P78+T78+X78,0) -> 140000
B79: REGIONAL PERIFERIA | C79: VIJ_1 | D79: FANNY FERNANDEZ | E79: ANYI MAYERLIE ORJUELA | F79: GONZALEZ BARRANTES EDWIN JESSID | G79: =IF(L79>=80%,250000,IF(AND(L79>=60%,L79<80%),150000,0)) -> 250000 | H79: =+VLOOKUP(C79,Indicadores!B:C,2,FALSE) -> 0.9047619 | I79: =IF(H79>=60%,"Cumple","No Cumple") -> Cumple | J79: =+VLOOKUP(C79,Indicadores!B:F,5,FALSE) -> 0.85714286 | K79: =IF(J79>=60%,"Cumple","No Cumple") -> Cumple | L79: =+AVERAGE(H79,J79) -> 0.88095238 | M79: =+G79*$M$3 -> 150000 | N79: =+VLOOKUP(C79,Indicadores!B:M,12,FALSE) -> 0.85878489 | O79: =IF(N79>=60%,"Cumple","No Cumple") -> Cumple | P79: =IF(N79>80%,M79*100%,IF(AND(N79>=60%,N79<=79%),M79*60%,0)) -> 150000 | Q79: =+$G$6*$Q$3 -> 50000 | R79: =+IFERROR(VLOOKUP(C79,Indicadores!B:N,13,FALSE),0%) -> 1.1405554 | S79: =IF(R79>=70%,"Cumple","No Cumple") -> Cumple | T79: =IF(R79=80%,Q79*70%,IF(AND(R79>=81%,R79<=90%),Q79*80%,IF(AND(R79>=91%,R79<=95%),Q79*90%,IF(R79=96%,Q79*96%,IF(R79=97%,Q79*97%,IF(R79=98%,Q79*98%,IF(R79=99%,Q79*99%,IF(R79>=100%,Q79,0)))))))) -> 50000 | U79: =+G79*$U$3 -> 50000 | V79: =+VLOOKUP(C79,Indicadores!B:S,18,FALSE) -> 0.96428571 | W79: =IF(V79>=100%,"Cumple","No Cumple") -> No Cumple | X79: =+IF(V79=100%,U79,0) -> 0 | Y79: =IF(L79>=60%,"SI","NO") -> SI | Z79: =+IF(Y79="SI",P79+T79+X79,0) -> 200000
B80: REGIONAL PERIFERIA | C80: VIJ_10 | D80: MIGUEL ARTURO ROMERO | E80: ANYI MAYERLIE ORJUELA | F80: GONZALEZ BARRANTES EDWIN JESSID | G80: =IF(L80>=80%,250000,IF(AND(L80>=60%,L80<80%),150000,0)) -> 250000 | H80: =+VLOOKUP(C80,Indicadores!B:C,2,FALSE) -> 0.94444444 | I80: =IF(H80>=60%,"Cumple","No Cumple") -> Cumple | J80: =+VLOOKUP(C80,Indicadores!B:F,5,FALSE) -> 1 | K80: =IF(J80>=60%,"Cumple","No Cumple") -> Cumple | L80: =+AVERAGE(H80,J80) -> 0.97222222 | M80: =+G80*$M$3 -> 150000 | N80: =+VLOOKUP(C80,Indicadores!B:M,12,FALSE) -> 0.64814815 | O80: =IF(N80>=60%,"Cumple","No Cumple") -> Cumple | P80: =IF(N80>80%,M80*100%,IF(AND(N80>=60%,N80<=79%),M80*60%,0)) -> 90000 | Q80: =+$G$6*$Q$3 -> 50000 | R80: =+IFERROR(VLOOKUP(C80,Indicadores!B:N,13,FALSE),0%) -> 1.4131856 | S80: =IF(R80>=70%,"Cumple","No Cumple") -> Cumple | T80: =IF(R80=80%,Q80*70%,IF(AND(R80>=81%,R80<=90%),Q80*80%,IF(AND(R80>=91%,R80<=95%),Q80*90%,IF(R80=96%,Q80*96%,IF(R80=97%,Q80*97%,IF(R80=98%,Q80*98%,IF(R80=99%,Q80*99%,IF(R80>=100%,Q80,0)))))))) -> 50000 | U80: =+G80*$U$3 -> 50000 | V80: =+VLOOKUP(C80,Indicadores!B:S,18,FALSE) -> 0.47222222 | W80: =IF(V80>=100%,"Cumple","No Cumple") -> No Cumple | X80: =+IF(V80=100%,U80,0) -> 0 | Y80: =IF(L80>=60%,"SI","NO") -> SI | Z80: =+IF(Y80="SI",P80+T80+X80,0) -> 140000
B81: REGIONAL PERIFERIA | C81: VIJ_11 | D81: MIGUEL ARTURO ROMERO | E81: ANYI MAYERLIE ORJUELA | F81: GONZALEZ BARRANTES EDWIN JESSID | G81: =IF(L81>=80%,250000,IF(AND(L81>=60%,L81<80%),150000,0)) -> 250000 | H81: =+VLOOKUP(C81,Indicadores!B:C,2,FALSE) -> 1 | I81: =IF(H81>=60%,"Cumple","No Cumple") -> Cumple | J81: =+VLOOKUP(C81,Indicadores!B:F,5,FALSE) -> 1 | K81: =IF(J81>=60%,"Cumple","No Cumple") -> Cumple | L81: =+AVERAGE(H81,J81) -> 1 | M81: =+G81*$M$3 -> 150000 | N81: =+VLOOKUP(C81,Indicadores!B:M,12,FALSE) -> 1 | O81: =IF(N81>=60%,"Cumple","No Cumple") -> Cumple | P81: =IF(N81>80%,M81*100%,IF(AND(N81>=60%,N81<=79%),M81*60%,0)) -> 150000 | Q81: =+$G$6*$Q$3 -> 50000 | R81: =+IFERROR(VLOOKUP(C81,Indicadores!B:N,13,FALSE),0%) -> 1.0888504 | S81: =IF(R81>=70%,"Cumple","No Cumple") -> Cumple | T81: =IF(R81=80%,Q81*70%,IF(AND(R81>=81%,R81<=90%),Q81*80%,IF(AND(R81>=91%,R81<=95%),Q81*90%,IF(R81=96%,Q81*96%,IF(R81=97%,Q81*97%,IF(R81=98%,Q81*98%,IF(R81=99%,Q81*99%,IF(R81>=100%,Q81,0)))))))) -> 50000 | U81: =+G81*$U$3 -> 50000 | V81: =+VLOOKUP(C81,Indicadores!B:S,18,FALSE) -> 1 | W81: =IF(V81>=100%,"Cumple","No Cumple") -> Cumple | X81: =+IF(V81=100%,U81,0) -> 50000 | Y81: =IF(L81>=60%,"SI","NO") -> SI | Z81: =+IF(Y81="SI",P81+T81+X81,0) -> 250000
B82: REGIONAL PERIFERIA | C82: VIJ_12 | D82: MIGUEL ARTURO ROMERO | E82: ANYI MAYERLIE ORJUELA | F82: GONZALEZ BARRANTES EDWIN JESSID | G82: =IF(L82>=80%,250000,IF(AND(L82>=60%,L82<80%),150000,0)) -> 250000 | H82: =+VLOOKUP(C82,Indicadores!B:C,2,FALSE) -> 1 | I82: =IF(H82>=60%,"Cumple","No Cumple") -> Cumple | J82: =+VLOOKUP(C82,Indicadores!B:F,5,FALSE) -> 1 | K82: =IF(J82>=60%,"Cumple","No Cumple") -> Cumple | L82: =+AVERAGE(H82,J82) -> 1 | M82: =+G82*$M$3 -> 150000 | N82: =+VLOOKUP(C82,Indicadores!B:M,12,FALSE) -> 0.73333333 | O82: =IF(N82>=60%,"Cumple","No Cumple") -> Cumple | P82: =IF(N82>80%,M82*100%,IF(AND(N82>=60%,N82<=79%),M82*60%,0)) -> 90000 | Q82: =+$G$6*$Q$3 -> 50000 | R82: =+IFERROR(VLOOKUP(C82,Indicadores!B:N,13,FALSE),0%) -> 0.781692 | S82: =IF(R82>=80%,"Cumple","No Cumple") -> No Cumple | T82: =IF(R82>=70%,Q82*70%,IF(AND(R82>=81%,R82<=90%),Q82*80%,IF(AND(R82>=91%,R82<=95%),Q82*90%,IF(R82=96%,Q82*96%,IF(R82=97%,Q82*97%,IF(R82=98%,Q82*98%,IF(R82=99%,Q82*99%,IF(R82>=100%,Q82,0)))))))) -> 35000 | U82: =+G82*$U$3 -> 50000 | V82: =+VLOOKUP(C82,Indicadores!B:S,18,FALSE) -> 1 | W82: =IF(V82>=100%,"Cumple","No Cumple") -> Cumple | X82: =+IF(V82=100%,U82,0) -> 50000 | Y82: =IF(L82>=60%,"SI","NO") -> SI | Z82: =+IF(Y82="SI",P82+T82+X82,0) -> 175000
B83: REGIONAL PERIFERIA | C83: VIJ_13 | D83: MIGUEL ARTURO ROMERO | E83: ANYI MAYERLIE ORJUELA | F83: GONZALEZ BARRANTES EDWIN JESSID | G83: =IF(L83>=80%,250000,IF(AND(L83>=60%,L83<80%),150000,0)) -> 250000 | H83: =+VLOOKUP(C83,Indicadores!B:C,2,FALSE) -> 1 | I83: =IF(H83>=60%,"Cumple","No Cumple") -> Cumple | J83: =+VLOOKUP(C83,Indicadores!B:F,5,FALSE) -> 1 | K83: =IF(J83>=60%,"Cumple","No Cumple") -> Cumple | L83: =+AVERAGE(H83,J83) -> 1 | M83: =+G83*$M$3 -> 150000 | N83: =+VLOOKUP(C83,Indicadores!B:M,12,FALSE) -> 1 | O83: =IF(N83>=60%,"Cumple","No Cumple") -> Cumple | P83: =IF(N83>80%,M83*100%,IF(AND(N83>=60%,N83<=79%),M83*60%,0)) -> 150000 | Q83: =+$G$6*$Q$3 -> 50000 | R83: =+IFERROR(VLOOKUP(C83,Indicadores!B:N,13,FALSE),0%) -> 1.0009206 | S83: =IF(R83>=70%,"Cumple","No Cumple") -> Cumple | T83: =IF(R83=80%,Q83*70%,IF(AND(R83>=81%,R83<=90%),Q83*80%,IF(AND(R83>=91%,R83<=95%),Q83*90%,IF(R83=96%,Q83*96%,IF(R83=97%,Q83*97%,IF(R83=98%,Q83*98%,IF(R83=99%,Q83*99%,IF(R83>=100%,Q83,0)))))))) -> 50000 | U83: =+G83*$U$3 -> 50000 | V83: =+VLOOKUP(C83,Indicadores!B:S,18,FALSE) -> 1 | W83: =IF(V83>=100%,"Cumple","No Cumple") -> Cumple | X83: =+IF(V83=100%,U83,0) -> 50000 | Y83: =IF(L83>=60%,"SI","NO") -> SI | Z83: =+IF(Y83="SI",P83+T83+X83,0) -> 250000
B84: REGIONAL PERIFERIA | C84: VIJ_14 | D84: MIGUEL ARTURO ROMERO | E84: ANYI MAYERLIE ORJUELA | F84: GONZALEZ BARRANTES EDWIN JESSID | G84: =IF(L84>=80%,250000,IF(AND(L84>=60%,L84<80%),150000,0)) -> 250000 | H84: =+VLOOKUP(C84,Indicadores!B:C,2,FALSE) -> 0.91666667 | I84: =IF(H84>=60%,"Cumple","No Cumple") -> Cumple | J84: =+VLOOKUP(C84,Indicadores!B:F,5,FALSE) -> 0.91666667 | K84: =IF(J84>=60%,"Cumple","No Cumple") -> Cumple | L84: =+AVERAGE(H84,J84) -> 0.91666667 | M84: =+G84*$M$3 -> 150000 | N84: =+VLOOKUP(C84,Indicadores!B:M,12,FALSE) -> 0.94444444 | O84: =IF(N84>=60%,"Cumple","No Cumple") -> Cumple | P84: =IF(N84>80%,M84*100%,IF(AND(N84>=60%,N84<=79%),M84*60%,0)) -> 150000 | Q84: =+$G$6*$Q$3 -> 50000 | R84: =+IFERROR(VLOOKUP(C84,Indicadores!B:N,13,FALSE),0%) -> 0.98760283 | S84: =IF(R84>=70%,"Cumple","No Cumple") -> Cumple | T84: =IF(R84=80%,Q84*70%,IF(AND(R84>=81%,R84<=90%),Q84*80%,IF(AND(R84>=91%,R84<=95%),Q84*90%,IF(R84=96%,Q84*96%,IF(R84=97%,Q84*97%,IF(R84>=98%,Q84*98%,IF(R84=99%,Q84*99%,IF(R84>=100%,Q84,0)))))))) -> 49000 | U84: =+G84*$U$3 -> 50000 | V84: =+VLOOKUP(C84,Indicadores!B:S,18,FALSE) -> 0.91666667 | W84: =IF(V84>=100%,"Cumple","No Cumple") -> No Cumple | X84: =+IF(V84=100%,U84,0) -> 0 | Y84: =IF(L84>=60%,"SI","NO") -> SI | Z84: =+IF(Y84="SI",P84+T84+X84,0) -> 199000
B85: REGIONAL PERIFERIA | C85: VIJ_15 | D85: MIGUEL ARTURO ROMERO | E85: ANYI MAYERLIE ORJUELA | F85: GONZALEZ BARRANTES EDWIN JESSID | G85: =IF(L85>=80%,250000,IF(AND(L85>=60%,L85<80%),150000,0)) -> 250000 | H85: =+VLOOKUP(C85,Indicadores!B:C,2,FALSE) -> 1 | I85: =IF(H85>=60%,"Cumple","No Cumple") -> Cumple | J85: =+VLOOKUP(C85,Indicadores!B:F,5,FALSE) -> 1 | K85: =IF(J85>=60%,"Cumple","No Cumple") -> Cumple | L85: =+AVERAGE(H85,J85) -> 1 | M85: =+G85*$M$3 -> 150000 | N85: =+VLOOKUP(C85,Indicadores!B:M,12,FALSE) -> 1 | O85: =IF(N85>=60%,"Cumple","No Cumple") -> Cumple | P85: =IF(N85>80%,M85*100%,IF(AND(N85>=60%,N85<=79%),M85*60%,0)) -> 150000 | Q85: =+$G$6*$Q$3 -> 50000 | R85: =+IFERROR(VLOOKUP(C85,Indicadores!B:N,13,FALSE),0%) -> 1.1743987 | S85: =IF(R85>=70%,"Cumple","No Cumple") -> Cumple | T85: =IF(R85=80%,Q85*70%,IF(AND(R85>=81%,R85<=90%),Q85*80%,IF(AND(R85>=91%,R85<=95%),Q85*90%,IF(R85=96%,Q85*96%,IF(R85=97%,Q85*97%,IF(R85=98%,Q85*98%,IF(R85=99%,Q85*99%,IF(R85>=100%,Q85,0)))))))) -> 50000 | U85: =+G85*$U$3 -> 50000 | V85: =+VLOOKUP(C85,Indicadores!B:S,18,FALSE) -> 1 | W85: =IF(V85>=100%,"Cumple","No Cumple") -> Cumple | X85: =+IF(V85=100%,U85,0) -> 50000 | Y85: =IF(L85>=60%,"SI","NO") -> SI | Z85: =+IF(Y85="SI",P85+T85+X85,0) -> 250000
B86: REGIONAL PERIFERIA | C86: VIJ_16 | D86: MIGUEL ARTURO ROMERO | E86: ANYI MAYERLIE ORJUELA | F86: GONZALEZ BARRANTES EDWIN JESSID | G86: =IF(L86>=80%,250000,IF(AND(L86>=60%,L86<80%),150000,0)) -> 250000 | H86: =+VLOOKUP(C86,Indicadores!B:C,2,FALSE) -> 0.93333333 | I86: =IF(H86>=60%,"Cumple","No Cumple") -> Cumple | J86: =+VLOOKUP(C86,Indicadores!B:F,5,FALSE) -> 0.93333333 | K86: =IF(J86>=60%,"Cumple","No Cumple") -> Cumple | L86: =+AVERAGE(H86,J86) -> 0.93333333 | M86: =+G86*$M$3 -> 150000 | N86: =+VLOOKUP(C86,Indicadores!B:M,12,FALSE) -> 0.9308642 | O86: =IF(N86>=60%,"Cumple","No Cumple") -> Cumple | P86: =IF(N86>80%,M86*100%,IF(AND(N86>=60%,N86<=79%),M86*60%,0)) -> 150000 | Q86: =+$G$6*$Q$3 -> 50000 | R86: =+IFERROR(VLOOKUP(C86,Indicadores!B:N,13,FALSE),0%) -> 1.4460715 | S86: =IF(R86>=70%,"Cumple","No Cumple") -> Cumple | T86: =IF(R86=80%,Q86*70%,IF(AND(R86>=81%,R86<=90%),Q86*80%,IF(AND(R86>=91%,R86<=95%),Q86*90%,IF(R86=96%,Q86*96%,IF(R86=97%,Q86*97%,IF(R86=98%,Q86*98%,IF(R86=99%,Q86*99%,IF(R86>=100%,Q86,0)))))))) -> 50000 | U86: =+G86*$U$3 -> 50000 | V86: =+VLOOKUP(C86,Indicadores!B:S,18,FALSE) -> 0.46666667 | W86: =IF(V86>=100%,"Cumple","No Cumple") -> No Cumple | X86: =+IF(V86=100%,U86,0) -> 0 | Y86: =IF(L86>=60%,"SI","NO") -> SI | Z86: =+IF(Y86="SI",P86+T86+X86,0) -> 200000
B87: REGIONAL PERIFERIA | C87: VIJ_17 | D87: NA | E87: ANYI MAYERLIE ORJUELA | F87: GONZALEZ BARRANTES EDWIN JESSID | G87: =IF(L87>=80%,250000,IF(AND(L87>=60%,L87<80%),150000,0)) -> 250000 | H87: =+VLOOKUP(C87,Indicadores!B:C,2,FALSE) -> 0.87179487 | I87: =IF(H87>=60%,"Cumple","No Cumple") -> Cumple | J87: =+VLOOKUP(C87,Indicadores!B:F,5,FALSE) -> 0.84615385 | K87: =IF(J87>=60%,"Cumple","No Cumple") -> Cumple | L87: =+AVERAGE(H87,J87) -> 0.85897436 | M87: =+G87*$M$3 -> 150000 | N87: =+VLOOKUP(C87,Indicadores!B:M,12,FALSE) -> 0.78974359 | O87: =IF(N87>=60%,"Cumple","No Cumple") -> Cumple | P87: =IF(N87>80%,M87*100%,IF(AND(N87>=60%,N87<=79%),M87*60%,0)) -> 90000 | Q87: =+$G$6*$Q$3 -> 50000 | R87: =+IFERROR(VLOOKUP(C87,Indicadores!B:N,13,FALSE),0%) -> 1.0383875 | S87: =IF(R87>=70%,"Cumple","No Cumple") -> Cumple | T87: =IF(R87=80%,Q87*70%,IF(AND(R87>=81%,R87<=90%),Q87*80%,IF(AND(R87>=91%,R87<=95%),Q87*90%,IF(R87=96%,Q87*96%,IF(R87=97%,Q87*97%,IF(R87=98%,Q87*98%,IF(R87=99%,Q87*99%,IF(R87>=100%,Q87,0)))))))) -> 50000 | U87: =+G87*$U$3 -> 50000 | V87: =+VLOOKUP(C87,Indicadores!B:S,18,FALSE) -> 0.42307692 | W87: =IF(V87>=100%,"Cumple","No Cumple") -> No Cumple | X87: =+IF(V87=100%,U87,0) -> 0 | Y87: =IF(L87>=60%,"SI","NO") -> SI | Z87: =+IF(Y87="SI",P87+T87+X87,0) -> 140000
B88: REGIONAL PERIFERIA | C88: VIJ_2 | D88: FANNY FERNANDEZ | E88: ANYI MAYERLIE ORJUELA | F88: GONZALEZ BARRANTES EDWIN JESSID | G88: =IF(L88>=80%,250000,IF(AND(L88>=60%,L88<80%),150000,0)) -> 250000 | H88: =+VLOOKUP(C88,Indicadores!B:C,2,FALSE) -> 1 | I88: =IF(H88>=60%,"Cumple","No Cumple") -> Cumple | J88: =+VLOOKUP(C88,Indicadores!B:F,5,FALSE) -> 1 | K88: =IF(J88>=60%,"Cumple","No Cumple") -> Cumple | L88: =+AVERAGE(H88,J88) -> 1 | M88: =+G88*$M$3 -> 150000 | N88: =+VLOOKUP(C88,Indicadores!B:M,12,FALSE) -> 1 | O88: =IF(N88>=60%,"Cumple","No Cumple") -> Cumple | P88: =IF(N88>80%,M88*100%,IF(AND(N88>=60%,N88<=79%),M88*60%,0)) -> 150000 | Q88: =+$G$6*$Q$3 -> 50000 | R88: 0.9 | S88: =IF(R88>=70%,"Cumple","No Cumple") -> Cumple | T88: =IF(R88=80%,Q88*70%,IF(AND(R88>=81%,R88<=90%),Q88*80%,IF(AND(R88>=91%,R88<=95%),Q88*90%,IF(R88>=96%,Q88*96%,IF(R88>=97%,Q88*97%,IF(R88>=98%,Q88*98%,IF(R88=99%,Q88*99%,IF(R88>=100%,Q88,0)))))))) -> 40000 | U88: =+G88*$U$3 -> 50000 | V88: =+VLOOKUP(C88,Indicadores!B:S,18,FALSE) -> 0.5 | W88: =IF(V88>=100%,"Cumple","No Cumple") -> No Cumple | X88: =+IF(V88=100%,U88,0) -> 0 | Y88: =IF(L88>=60%,"SI","NO") -> SI | Z88: =+IF(Y88="SI",P88+T88+X88,0) -> 190000
B89: REGIONAL PERIFERIA | C89: VIJ_3 | D89: FANNY FERNANDEZ | E89: ANYI MAYERLIE ORJUELA | F89: GONZALEZ BARRANTES EDWIN JESSID | G89: =IF(L89>=80%,250000,IF(AND(L89>=60%,L89<80%),150000,0)) -> 250000 | H89: =+VLOOKUP(C89,Indicadores!B:C,2,FALSE) -> 1 | I89: =IF(H89>=60%,"Cumple","No Cumple") -> Cumple | J89: =+VLOOKUP(C89,Indicadores!B:F,5,FALSE) -> 1 | K89: =IF(J89>=60%,"Cumple","No Cumple") -> Cumple | L89: =+AVERAGE(H89,J89) -> 1 | M89: =+G89*$M$3 -> 150000 | N89: =+VLOOKUP(C89,Indicadores!B:M,12,FALSE) -> 1 | O89: =IF(N89>=60%,"Cumple","No Cumple") -> Cumple | P89: =IF(N89>80%,M89*100%,IF(AND(N89>=60%,N89<=79%),M89*60%,0)) -> 150000 | Q89: =+$G$6*$Q$3 -> 50000 | R89: =+IFERROR(VLOOKUP(C89,Indicadores!B:N,13,FALSE),0%) -> 1.049226 | S89: =IF(R89>=70%,"Cumple","No Cumple") -> Cumple | T89: =IF(R89=80%,Q89*70%,IF(AND(R89>=81%,R89<=90%),Q89*80%,IF(AND(R89>=91%,R89<=95%),Q89*90%,IF(R89=96%,Q89*96%,IF(R89=97%,Q89*97%,IF(R89=98%,Q89*98%,IF(R89=99%,Q89*99%,IF(R89>=100%,Q89,0)))))))) -> 50000 | U89: =+G89*$U$3 -> 50000 | V89: =+VLOOKUP(C89,Indicadores!B:S,18,FALSE) -> 1 | W89: =IF(V89>=100%,"Cumple","No Cumple") -> Cumple | X89: =+IF(V89=100%,U89,0) -> 50000 | Y89: =IF(L89>=60%,"SI","NO") -> SI | Z89: =+IF(Y89="SI",P89+T89+X89,0) -> 250000
B90: REGIONAL PERIFERIA | C90: VIJ_4 | D90: FANNY FERNANDEZ | E90: ANYI MAYERLIE ORJUELA | F90: GONZALEZ BARRANTES EDWIN JESSID | G90: =IF(L90>=80%,250000,IF(AND(L90>=60%,L90<80%),150000,0)) -> 250000 | H90: =+VLOOKUP(C90,Indicadores!B:C,2,FALSE) -> 1 | I90: =IF(H90>=60%,"Cumple","No Cumple") -> Cumple | J90: =+VLOOKUP(C90,Indicadores!B:F,5,FALSE) -> 1 | K90: =IF(J90>=60%,"Cumple","No Cumple") -> Cumple | L90: =+AVERAGE(H90,J90) -> 1 | M90: =+G90*$M$3 -> 150000 | N90: =+VLOOKUP(C90,Indicadores!B:M,12,FALSE) -> 0.92753623 | O90: =IF(N90>=60%,"Cumple","No Cumple") -> Cumple | P90: =IF(N90>80%,M90*100%,IF(AND(N90>=60%,N90<=79%),M90*60%,0)) -> 150000 | Q90: =+$G$6*$Q$3 -> 50000 | R90: =+IFERROR(VLOOKUP(C90,Indicadores!B:N,13,FALSE),0%) -> 1.318021 | S90: =IF(R90>=70%,"Cumple","No Cumple") -> Cumple | T90: =IF(R90=80%,Q90*70%,IF(AND(R90>=81%,R90<=90%),Q90*80%,IF(AND(R90>=91%,R90<=95%),Q90*90%,IF(R90=96%,Q90*96%,IF(R90=97%,Q90*97%,IF(R90=98%,Q90*98%,IF(R90=99%,Q90*99%,IF(R90>=100%,Q90,0)))))))) -> 50000 | U90: =+G90*$U$3 -> 50000 | V90: =+VLOOKUP(C90,Indicadores!B:S,18,FALSE) -> 1 | W90: =IF(V90>=100%,"Cumple","No Cumple") -> Cumple | X90: =+IF(V90=100%,U90,0) -> 50000 | Y90: =IF(L90>=60%,"SI","NO") -> SI | Z90: =+IF(Y90="SI",P90+T90+X90,0) -> 250000
B91: REGIONAL PERIFERIA | C91: VIJ_5 | D91: FANNY FERNANDEZ | E91: ANYI MAYERLIE ORJUELA | F91: GONZALEZ BARRANTES EDWIN JESSID | G91: =IF(L91>=80%,250000,IF(AND(L91>=60%,L91<80%),150000,0)) -> 250000 | H91: =+VLOOKUP(C91,Indicadores!B:C,2,FALSE) -> 1 | I91: =IF(H91>=60%,"Cumple","No Cumple") -> Cumple | J91: =+VLOOKUP(C91,Indicadores!B:F,5,FALSE) -> 0.92307692 | K91: =IF(J91>=60%,"Cumple","No Cumple") -> Cumple | L91: =+AVERAGE(H91,J91) -> 0.96153846 | M91: =+G91*$M$3 -> 150000 | N91: =+VLOOKUP(C91,Indicadores!B:M,12,FALSE) -> 0.87660256 | O91: =IF(N91>=60%,"Cumple","No Cumple") -> Cumple | P91: =IF(N91>80%,M91*100%,IF(AND(N91>=60%,N91<=79%),M91*60%,0)) -> 150000 | Q91: =+$G$6*$Q$3 -> 50000 | R91: =+IFERROR(VLOOKUP(C91,Indicadores!B:N,13,FALSE),0%) -> 0.9108022 | S91: =IF(R91>=70%,"Cumple","No Cumple") -> Cumple | T91: =IF(R91=80%,Q91*70%,IF(AND(R91>=81%,R91<=90%),Q91*80%,IF(AND(R91>=91%,R91<=95%),Q91*90%,IF(R91=96%,Q91*96%,IF(R91=97%,Q91*97%,IF(R91=98%,Q91*98%,IF(R91=99%,Q91*99%,IF(R91>=100%,Q91,0)))))))) -> 45000 | U91: =+G91*$U$3 -> 50000 | V91: =+VLOOKUP(C91,Indicadores!B:S,18,FALSE) -> 0.5 | W91: =IF(V91>=100%,"Cumple","No Cumple") -> No Cumple | X91: =+IF(V91=100%,U91,0) -> 0 | Y91: =IF(L91>=60%,"SI","NO") -> SI | Z91: =+IF(Y91="SI",P91+T91+X91,0) -> 195000
B92: REGIONAL PERIFERIA | C92: VIJ_6 | D92: FANNY FERNANDEZ | E92: ANYI MAYERLIE ORJUELA | F92: GONZALEZ BARRANTES EDWIN JESSID | G92: =IF(L92>=80%,250000,IF(AND(L92>=60%,L92<80%),150000,0)) -> 250000 | H92: =+VLOOKUP(C92,Indicadores!B:C,2,FALSE) -> 1 | I92: =IF(H92>=60%,"Cumple","No Cumple") -> Cumple | J92: =+VLOOKUP(C92,Indicadores!B:F,5,FALSE) -> 1 | K92: =IF(J92>=60%,"Cumple","No Cumple") -> Cumple | L92: =+AVERAGE(H92,J92) -> 1 | M92: =+G92*$M$3 -> 150000 | N92: =+VLOOKUP(C92,Indicadores!B:M,12,FALSE) -> 1 | O92: =IF(N92>=60%,"Cumple","No Cumple") -> Cumple | P92: =IF(N92>80%,M92*100%,IF(AND(N92>=60%,N92<=79%),M92*60%,0)) -> 150000 | Q92: =+$G$6*$Q$3 -> 50000 | R92: =+IFERROR(VLOOKUP(C92,Indicadores!B:N,13,FALSE),0%) -> 0.99862811 | S92: =IF(R92>=70%,"Cumple","No Cumple") -> Cumple | T92: =IF(R92=80%,Q92*70%,IF(AND(R92>=81%,R92<=90%),Q92*80%,IF(AND(R92>=91%,R92<=95%),Q92*90%,IF(R92=96%,Q92*96%,IF(R92=97%,Q92*97%,IF(R92>=98%,Q92*98%,IF(R92=99%,Q92*99%,IF(R92>=100%,Q92,0)))))))) -> 49000 | U92: =+G92*$U$3 -> 50000 | V92: =+VLOOKUP(C92,Indicadores!B:S,18,FALSE) -> 1 | W92: =IF(V92>=100%,"Cumple","No Cumple") -> Cumple | X92: =+IF(V92=100%,U92,0) -> 50000 | Y92: =IF(L92>=60%,"SI","NO") -> SI | Z92: =+IF(Y92="SI",P92+T92+X92,0) -> 249000
B93: REGIONAL PERIFERIA | C93: VIJ_7 | D93: FANNY FERNANDEZ | E93: ANYI MAYERLIE ORJUELA | F93: GONZALEZ BARRANTES EDWIN JESSID | G93: =IF(L93>=80%,250000,IF(AND(L93>=60%,L93<80%),150000,0)) -> 250000 | H93: =+VLOOKUP(C93,Indicadores!B:C,2,FALSE) -> 1 | I93: =IF(H93>=60%,"Cumple","No Cumple") -> Cumple | J93: =+VLOOKUP(C93,Indicadores!B:F,5,FALSE) -> 1 | K93: =IF(J93>=60%,"Cumple","No Cumple") -> Cumple | L93: =+AVERAGE(H93,J93) -> 1 | M93: =+G93*$M$3 -> 150000 | N93: =+VLOOKUP(C93,Indicadores!B:M,12,FALSE) -> 0.9002849 | O93: =IF(N93>=60%,"Cumple","No Cumple") -> Cumple | P93: =IF(N93>80%,M93*100%,IF(AND(N93>=60%,N93<=79%),M93*60%,0)) -> 150000 | Q93: =+$G$6*$Q$3 -> 50000 | R93: =+IFERROR(VLOOKUP(C93,Indicadores!B:N,13,FALSE),0%) -> 1.1778604 | S93: =IF(R93>=70%,"Cumple","No Cumple") -> Cumple | T93: =IF(R93=80%,Q93*70%,IF(AND(R93>=81%,R93<=90%),Q93*80%,IF(AND(R93>=91%,R93<=95%),Q93*90%,IF(R93=96%,Q93*96%,IF(R93=97%,Q93*97%,IF(R93=98%,Q93*98%,IF(R93=99%,Q93*99%,IF(R93>=100%,Q93,0)))))))) -> 50000 | U93: =+G93*$U$3 -> 50000 | V93: =+VLOOKUP(C93,Indicadores!B:S,18,FALSE) -> 1 | W93: =IF(V93>=100%,"Cumple","No Cumple") -> Cumple | X93: =+IF(V93=100%,U93,0) -> 50000 | Y93: =IF(L93>=60%,"SI","NO") -> SI | Z93: =+IF(Y93="SI",P93+T93+X93,0) -> 250000
B94: REGIONAL PERIFERIA | C94: VIJ_8 | D94: FANNY FERNANDEZ | E94: ANYI MAYERLIE ORJUELA | F94: GONZALEZ BARRANTES EDWIN JESSID | G94: =IF(L94>=80%,250000,IF(AND(L94>=60%,L94<80%),150000,0)) -> 250000 | H94: =+VLOOKUP(C94,Indicadores!B:C,2,FALSE) -> 1 | I94: =IF(H94>=60%,"Cumple","No Cumple") -> Cumple | J94: =+VLOOKUP(C94,Indicadores!B:F,5,FALSE) -> 1 | K94: =IF(J94>=60%,"Cumple","No Cumple") -> Cumple | L94: =+AVERAGE(H94,J94) -> 1 | M94: =+G94*$M$3 -> 150000 | N94: =+VLOOKUP(C94,Indicadores!B:M,12,FALSE) -> 0.71111111 | O94: =IF(N94>=60%,"Cumple","No Cumple") -> Cumple | P94: =IF(N94>80%,M94*100%,IF(AND(N94>=60%,N94<=79%),M94*60%,0)) -> 90000 | Q94: =+$G$6*$Q$3 -> 50000 | R94: =+IFERROR(VLOOKUP(C94,Indicadores!B:N,13,FALSE),0%) -> 0.96749338 | S94: =IF(R94>=70%,"Cumple","No Cumple") -> Cumple | T94: =IF(R94=80%,Q94*70%,IF(AND(R94>=81%,R94<=90%),Q94*80%,IF(AND(R94>=91%,R94<=95%),Q94*90%,IF(R94>=96%,Q94*96%,IF(R94>=97%,Q94*97%,IF(R94>=98%,Q94*98%,IF(R94=99%,Q94*99%,IF(R94>=100%,Q94,0)))))))) -> 48000 | U94: =+G94*$U$3 -> 50000 | V94: =+VLOOKUP(C94,Indicadores!B:S,18,FALSE) -> 1 | W94: =IF(V94>=100%,"Cumple","No Cumple") -> Cumple | X94: =+IF(V94=100%,U94,0) -> 50000 | Y94: =IF(L94>=60%,"SI","NO") -> SI | Z94: =+IF(Y94="SI",P94+T94+X94,0) -> 188000
B95: REGIONAL PERIFERIA | C95: VIJ_9 | D95: FANNY FERNANDEZ | E95: ANYI MAYERLIE ORJUELA | F95: GONZALEZ BARRANTES EDWIN JESSID | G95: =IF(L95>=80%,250000,IF(AND(L95>=60%,L95<80%),150000,0)) -> 250000 | H95: =+VLOOKUP(C95,Indicadores!B:C,2,FALSE) -> 1 | I95: =IF(H95>=60%,"Cumple","No Cumple") -> Cumple | J95: =+VLOOKUP(C95,Indicadores!B:F,5,FALSE) -> 1 | K95: =IF(J95>=60%,"Cumple","No Cumple") -> Cumple | L95: =+AVERAGE(H95,J95) -> 1 | M95: =+G95*$M$3 -> 150000 | N95: =+VLOOKUP(C95,Indicadores!B:M,12,FALSE) -> 0.91666667 | O95: =IF(N95>=60%,"Cumple","No Cumple") -> Cumple | P95: =IF(N95>80%,M95*100%,IF(AND(N95>=60%,N95<=79%),M95*60%,0)) -> 150000 | Q95: =+$G$6*$Q$3 -> 50000 | R95: =+IFERROR(VLOOKUP(C95,Indicadores!B:N,13,FALSE),0%) -> 1.1807246 | S95: =IF(R95>=70%,"Cumple","No Cumple") -> Cumple | T95: =IF(R95=80%,Q95*70%,IF(AND(R95>=81%,R95<=90%),Q95*80%,IF(AND(R95>=91%,R95<=95%),Q95*90%,IF(R95=96%,Q95*96%,IF(R95=97%,Q95*97%,IF(R95=98%,Q95*98%,IF(R95=99%,Q95*99%,IF(R95>=100%,Q95,0)))))))) -> 50000 | U95: =+G95*$U$3 -> 50000 | V95: =+VLOOKUP(C95,Indicadores!B:S,18,FALSE) -> 1 | W95: =IF(V95>=100%,"Cumple","No Cumple") -> Cumple | X95: =+IF(V95=100%,U95,0) -> 50000 | Y95: =IF(L95>=60%,"SI","NO") -> SI | Z95: =+IF(Y95="SI",P95+T95+X95,0) -> 250000
B96: REGIONAL EJE | C96: ARMENIA_1 | D96: LEIDY GAVIRIA | E96: NATHALY AGUILAR | F96: CAMPUZANO IRLET ANDREA | G96: =IF(L96>=80%,250000,IF(AND(L96>=60%,L96<80%),150000,0)) -> 250000 | H96: =+VLOOKUP(C96,Indicadores!B:C,2,FALSE) -> 1 | I96: =IF(H96>=60%,"Cumple","No Cumple") -> Cumple | J96: =+VLOOKUP(C96,Indicadores!B:F,5,FALSE) -> 1 | K96: =IF(J96>=60%,"Cumple","No Cumple") -> Cumple | L96: =+AVERAGE(H96,J96) -> 1 | M96: =+G96*$M$3 -> 150000 | N96: =+VLOOKUP(C96,Indicadores!B:M,12,FALSE) -> 0.94166667 | O96: =IF(N96>=60%,"Cumple","No Cumple") -> Cumple | P96: =IF(N96>80%,M96*100%,IF(AND(N96>=60%,N96<=79%),M96*60%,0)) -> 150000 | Q96: =+$G$6*$Q$3 -> 50000 | R96: =+IFERROR(VLOOKUP(C96,Indicadores!B:N,13,FALSE),0%) -> 1.0927891 | S96: =IF(R96>=70%,"Cumple","No Cumple") -> Cumple | T96: =IF(R96=80%,Q96*70%,IF(AND(R96>=81%,R96<=90%),Q96*80%,IF(AND(R96>=91%,R96<=95%),Q96*90%,IF(R96=96%,Q96*96%,IF(R96=97%,Q96*97%,IF(R96=98%,Q96*98%,IF(R96=99%,Q96*99%,IF(R96>=100%,Q96,0)))))))) -> 50000 | U96: =+G96*$U$3 -> 50000 | V96: =+VLOOKUP(C96,Indicadores!B:S,18,FALSE) -> 0.5 | W96: =IF(V96>=100%,"Cumple","No Cumple") -> No Cumple | X96: =+IF(V96=100%,U96,0) -> 0 | Y96: =IF(L96>=60%,"SI","NO") -> SI | Z96: =+IF(Y96="SI",P96+T96+X96,0) -> 200000
B97: REGIONAL EJE | C97: ARMENIA_2 | D97: LEIDY GAVIRIA | E97: NATHALY AGUILAR | F97: CAMPUZANO IRLET ANDREA | G97: =IF(L97>=80%,250000,IF(AND(L97>=60%,L97<80%),150000,0)) -> 250000 | H97: =+VLOOKUP(C97,Indicadores!B:C,2,FALSE) -> 1 | I97: =IF(H97>=60%,"Cumple","No Cumple") -> Cumple | J97: =+VLOOKUP(C97,Indicadores!B:F,5,FALSE) -> 1 | K97: =IF(J97>=60%,"Cumple","No Cumple") -> Cumple | L97: =+AVERAGE(H97,J97) -> 1 | M97: =+G97*$M$3 -> 150000 | N97: =+VLOOKUP(C97,Indicadores!B:M,12,FALSE) -> 0.92046784 | O97: =IF(N97>=60%,"Cumple","No Cumple") -> Cumple | P97: =IF(N97>80%,M97*100%,IF(AND(N97>=60%,N97<=79%),M97*60%,0)) -> 150000 | Q97: =+$G$6*$Q$3 -> 50000 | R97: =+IFERROR(VLOOKUP(C97,Indicadores!B:N,13,FALSE),0%) -> 0.86136963 | S97: =IF(R97>=70%,"Cumple","No Cumple") -> Cumple | T97: =IF(R97=80%,Q97*70%,IF(AND(R97>=81%,R97<=90%),Q97*80%,IF(AND(R97>=91%,R97<=95%),Q97*90%,IF(R97=96%,Q97*96%,IF(R97=97%,Q97*97%,IF(R97=98%,Q97*98%,IF(R97=99%,Q97*99%,IF(R97>=100%,Q97,0)))))))) -> 40000 | U97: =+G97*$U$3 -> 50000 | V97: =+VLOOKUP(C97,Indicadores!B:S,18,FALSE) -> 0.5 | W97: =IF(V97>=100%,"Cumple","No Cumple") -> No Cumple | X97: =+IF(V97=100%,U97,0) -> 0 | Y97: =IF(L97>=60%,"SI","NO") -> SI | Z97: =+IF(Y97="SI",P97+T97+X97,0) -> 190000
B98: REGIONAL EJE | C98: CARTAGO_1 | D98: LEIDY GAVIRIA | E98: NATHALY AGUILAR | F98: CAMPUZANO IRLET ANDREA | G98: =IF(L98>=80%,250000,IF(AND(L98>=60%,L98<80%),150000,0)) -> 250000 | H98: =+VLOOKUP(C98,Indicadores!B:C,2,FALSE) -> 1 | I98: =IF(H98>=60%,"Cumple","No Cumple") -> Cumple | J98: =+VLOOKUP(C98,Indicadores!B:F,5,FALSE) -> 1 | K98: =IF(J98>=60%,"Cumple","No Cumple") -> Cumple | L98: =+AVERAGE(H98,J98) -> 1 | M98: =+G98*$M$3 -> 150000 | N98: =+VLOOKUP(C98,Indicadores!B:M,12,FALSE) -> 0.90792839 | O98: =IF(N98>=60%,"Cumple","No Cumple") -> Cumple | P98: =IF(N98>80%,M98*100%,IF(AND(N98>=60%,N98<=79%),M98*60%,0)) -> 150000 | Q98: =+$G$6*$Q$3 -> 50000 | R98: =+IFERROR(VLOOKUP(C98,Indicadores!B:N,13,FALSE),0%) -> 1.1447375 | S98: =IF(R98>=70%,"Cumple","No Cumple") -> Cumple | T98: =IF(R98=80%,Q98*70%,IF(AND(R98>=81%,R98<=90%),Q98*80%,IF(AND(R98>=91%,R98<=95%),Q98*90%,IF(R98=96%,Q98*96%,IF(R98=97%,Q98*97%,IF(R98=98%,Q98*98%,IF(R98=99%,Q98*99%,IF(R98>=100%,Q98,0)))))))) -> 50000 | U98: =+G98*$U$3 -> 50000 | V98: =+VLOOKUP(C98,Indicadores!B:S,18,FALSE) -> 0.5 | W98: =IF(V98>=100%,"Cumple","No Cumple") -> No Cumple | X98: =+IF(V98=100%,U98,0) -> 0 | Y98: =IF(L98>=60%,"SI","NO") -> SI | Z98: =+IF(Y98="SI",P98+T98+X98,0) -> 200000
B99: REGIONAL EJE | C99: DOSQUEBRADAS_1 | D99: LEIDY GAVIRIA | E99: NATHALY AGUILAR | F99: CAMPUZANO IRLET ANDREA | G99: =IF(L99>=80%,250000,IF(AND(L99>=60%,L99<80%),150000,0)) -> 250000 | H99: =+VLOOKUP(C99,Indicadores!B:C,2,FALSE) -> 1 | I99: =IF(H99>=60%,"Cumple","No Cumple") -> Cumple | J99: =+VLOOKUP(C99,Indicadores!B:F,5,FALSE) -> 1 | K99: =IF(J99>=60%,"Cumple","No Cumple") -> Cumple | L99: =+AVERAGE(H99,J99) -> 1 | M99: =+G99*$M$3 -> 150000 | N99: =+VLOOKUP(C99,Indicadores!B:M,12,FALSE) -> 1 | O99: =IF(N99>=60%,"Cumple","No Cumple") -> Cumple | P99: =IF(N99>80%,M99*100%,IF(AND(N99>=60%,N99<=79%),M99*60%,0)) -> 150000 | Q99: =+$G$6*$Q$3 -> 50000 | R99: =+IFERROR(VLOOKUP(C99,Indicadores!B:N,13,FALSE),0%) -> 1.1493266 | S99: =IF(R99>=70%,"Cumple","No Cumple") -> Cumple | T99: =IF(R99=80%,Q99*70%,IF(AND(R99>=81%,R99<=90%),Q99*80%,IF(AND(R99>=91%,R99<=95%),Q99*90%,IF(R99=96%,Q99*96%,IF(R99=97%,Q99*97%,IF(R99=98%,Q99*98%,IF(R99=99%,Q99*99%,IF(R99>=100%,Q99,0)))))))) -> 50000 | U99: =+G99*$U$3 -> 50000 | V99: =+VLOOKUP(C99,Indicadores!B:S,18,FALSE) -> 1 | W99: =IF(V99>=100%,"Cumple","No Cumple") -> Cumple | X99: =+IF(V99=100%,U99,0) -> 50000 | Y99: =IF(L99>=60%,"SI","NO") -> SI | Z99: =+IF(Y99="SI",P99+T99+X99,0) -> 250000
B100: REGIONAL EJE | C100: DOSQUEBRADAS_2 | D100: LEIDY GAVIRIA | E100: NATHALY AGUILAR | F100: CAMPUZANO IRLET ANDREA | G100: =IF(L100>=80%,250000,IF(AND(L100>=60%,L100<80%),150000,0)) -> 250000 | H100: =+VLOOKUP(C100,Indicadores!B:C,2,FALSE) -> 0.85416667 | I100: =IF(H100>=60%,"Cumple","No Cumple") -> Cumple | J100: =+VLOOKUP(C100,Indicadores!B:F,5,FALSE) -> 0.875 | K100: =IF(J100>=60%,"Cumple","No Cumple") -> Cumple | L100: =+AVERAGE(H100,J100) -> 0.86458333 | M100: =+G100*$M$3 -> 150000 | N100: =+VLOOKUP(C100,Indicadores!B:M,12,FALSE) -> 0.6548913 | O100: =IF(N100>=60%,"Cumple","No Cumple") -> Cumple | P100: =IF(N100>80%,M100*100%,IF(AND(N100>=60%,N100<=79%),M100*60%,0)) -> 90000 | Q100: =+$G$6*$Q$3 -> 50000 | R100: =+IFERROR(VLOOKUP(C100,Indicadores!B:N,13,FALSE),0%) -> 1.3067738 | S100: =IF(R100>=70%,"Cumple","No Cumple") -> Cumple | T100: =IF(R100=80%,Q100*70%,IF(AND(R100>=81%,R100<=90%),Q100*80%,IF(AND(R100>=91%,R100<=95%),Q100*90%,IF(R100=96%,Q100*96%,IF(R100=97%,Q100*97%,IF(R100=98%,Q100*98%,IF(R100=99%,Q100*99%,IF(R100>=100%,Q100,0)))))))) -> 50000 | U100: =+G100*$U$3 -> 50000 | V100: =+VLOOKUP(C100,Indicadores!B:S,18,FALSE) -> 0.4375 | W100: =IF(V100>=100%,"Cumple","No Cumple") -> No Cumple | X100: =+IF(V100=100%,U100,0) -> 0 | Y100: =IF(L100>=60%,"SI","NO") -> SI | Z100: =+IF(Y100="SI",P100+T100+X100,0) -> 140000
...

Sheet Indicadores
A1: LIDER | B1: RUTA | C1: % CAPTURA | D1: OBJ COBERTURA | E1: COBERTURA | F1: % COBERTURA | G1: FECHAS CORTAS % | H1: Agotados % | I1: Participación % | J1: ACTIVIDADES % | K1: PLANES COMERCIALES | L1: DEVOLUCIONES % | M1: TIENDA PERFECTA | N1: VENTA | O1: FECHAS CORTAS | P1: pdv devoluciones | Q1: % Devoluciones | R1: DEVOLUCIONES | S1: FC & DEV
A2: =+VLOOKUP(B2,'INDICADORES CAPTURA'!C:E,3,FALSE) -> JUAN PABLO GIL ALMANZA | B2: SOR_4 | C2: =+AVERAGE(G2,H2,L2) -> 1 | D2: 5 | E2: 5 | F2: =+E2/D2 -> 1 | G2: 1 | H2: 1 | I2: 1 | J2: 1 | K2: 1 | L2: 1 | M2: =+AVERAGE(I2,J2,K2) -> 1 | N2: 1.0741337 | O2: =+G2 -> 1 | P2: 0 | Q2: 0.016222669 | R2: =+IF(Q2<3%,100%,0) -> 1 | S2: =+AVERAGE(O2,R2) -> 1
A3: =+VLOOKUP(B3,'INDICADORES CAPTURA'!C:E,3,FALSE) -> GONZALEZ BARRANTES EDWIN JESSID | B3: VIJ_2 | C3: =+AVERAGE(G3,H3,L3) -> 1 | D3: 1 | E3: 1 | F3: =+E3/D3 -> 1 | G3: 1 | H3: 1 | I3: 1 | J3: 1 | K3: 1 | L3: 1 | M3: =+AVERAGE(I3,J3,K3) -> 1 | N3: 0.90429252 | O3: =+G3 -> 1 | P3: 0 | Q3: 0.033197086 | R3: =+IF(Q3<3%,100%,0) -> 0 | S3: =+AVERAGE(O3,R3) -> 0.5
A4: =+VLOOKUP(B4,'INDICADORES CAPTURA'!C:E,3,FALSE) -> JUAN PABLO GIL ALMANZA | B4: SOR_6 | C4: =+AVERAGE(G4,H4,L4) -> 1 | D4: 5 | E4: 5 | F4: =+E4/D4 -> 1 | G4: 1 | H4: 1 | I4: 1 | J4: 1 | K4: 1 | L4: 1 | M4: =+AVERAGE(I4,J4,K4) -> 1 | N4: 0.97915641 | O4: =+G4 -> 1 | P4: 0 | Q4: 0.0089678621 | R4: =+IF(Q4<3%,100%,0) -> 1 | S4: =+AVERAGE(O4,R4) -> 1
A5: =+VLOOKUP(B5,'INDICADORES CAPTURA'!C:E,3,FALSE) -> MELISA MARTINEZ | B5: NOC_15 | C5: =+AVERAGE(G5,H5,L5) -> 1 | D5: 2 | E5: 2 | F5: =+E5/D5 -> 1 | G5: 1 | H5: 1 | I5: 0.5 | J5: 1 | K5: 1 | L5: 1 | M5: =+AVERAGE(I5,J5,K5) -> 0.83333333 | N5: 0.91248682 | O5: =+G5 -> 1 | P5: 0 | Q5: 0.0019765242 | R5: =+IF(Q5<3%,100%,0) -> 1 | S5: =+AVERAGE(O5,R5) -> 1
A6: =+VLOOKUP(B6,'INDICADORES CAPTURA'!C:E,3,FALSE) -> JUAN PABLO GIL ALMANZA | B6: SOR_11 | C6: =+AVERAGE(G6,H6,L6) -> 1 | D6: 16 | E6: 16 | F6: =+E6/D6 -> 1 | G6: 1 | H6: 1 | I6: 0.9375 | J6: 1 | K6: 1 | L6: 1 | M6: =+AVERAGE(I6,J6,K6) -> 0.97916667 | N6: 0.93665487 | O6: =+G6 -> 1 | P6: 0 | Q6: 0.0086442053 | R6: =+IF(Q6<3%,100%,0) -> 1 | S6: =+O6 -> 1
A7: =+VLOOKUP(B7,'INDICADORES CAPTURA'!C:E,3,FALSE) -> JUAN PABLO GIL ALMANZA | B7: SOR_3 | C7: =+AVERAGE(G7,H7,L7) -> 1 | D7: 6 | E7: 6 | F7: =+E7/D7 -> 1 | G7: 1 | H7: 1 | I7: 1 | J7: 1 | K7: 1 | L7: 1 | M7: =+AVERAGE(I7,J7,K7) -> 1 | N7: 0.92267607 | O7: =+G7 -> 1 | P7: 0 | Q7: 0.016839255 | R7: =+IF(Q7<3%,100%,0) -> 1 | S7: =+AVERAGE(O7,R7) -> 1
A8: =+VLOOKUP(B8,'INDICADORES CAPTURA'!C:E,3,FALSE) -> MEJÍA BLANDÓN ASTRID KARINA | B8: MEDELLIN_1 | C8: =+AVERAGE(G8,H8,L8) -> 1 | D8: 9 | E8: 9 | F8: =+E8/D8 -> 1 | G8: 1 | H8: 1 | I8: 0.33333333 | J8: 1 | K8: 1 | L8: 1 | M8: =+AVERAGE(I8,J8,K8) -> 0.77777778 | N8: 1.0043917 | O8: =+G8 -> 1 | P8: 0 | Q8: 0.033637568 | R8: =+IF(Q8<3%,100%,0) -> 0 | S8: =+O8 -> 1
A9: =+VLOOKUP(B9,'INDICADORES CAPTURA'!C:E,3,FALSE) -> SUSANA SILVA MENDOZA | B9: CTR_1 | C9: =+AVERAGE(G9,H9,L9) -> 1 | D9: 9 | E9: 9 | F9: =+E9/D9 -> 1 | G9: 1 | H9: 1 | I9: 1 | J9: 1 | K9: 1 | L9: 1 | M9: =+AVERAGE(I9,J9,K9) -> 1 | N9: 1.0926436 | O9: =+G9 -> 1 | P9: 0 | Q9: 0.023162623 | R9: =+IF(Q9<3%,100%,0) -> 1 | S9: =+AVERAGE(O9,R9) -> 1
A10: =+VLOOKUP(B10,'INDICADORES CAPTURA'!C:E,3,FALSE) -> GONZALEZ BARRANTES EDWIN JESSID | B10: VIJ_6 | C10: =+AVERAGE(G10,H10,L10) -> 1 | D10: 7 | E10: 7 | F10: =+E10/D10 -> 1 | G10: 1 | H10: 1 | I10: 1 | J10: 1 | K10: 1 | L10: 1 | M10: =+AVERAGE(I10,J10,K10) -> 1 | N10: 0.99862811 | O10: =+G10 -> 1 | P10: 0 | Q10: 0.015531685 | R10: =+IF(Q10<3%,100%,0) -> 1 | S10: =+AVERAGE(O10,R10) -> 1
A11: =+VLOOKUP(B11,'INDICADORES CAPTURA'!C:E,3,FALSE) -> JUAN PABLO GIL ALMANZA | B11: SOR_2 | C11: =+AVERAGE(G11,H11,L11) -> 1 | D11: 5 | E11: 5 | F11: =+E11/D11 -> 1 | G11: 1 | H11: 1 | I11: 1 | J11: 1 | K11: 1 | L11: 1 | M11: =+AVERAGE(I11,J11,K11) -> 1 | N11: 0.63770592 | O11: =+G11 -> 1 | P11: 0 | Q11: 0.031977815 | R11: =+IF(Q11<3%,100%,0) -> 0 | S11: =+AVERAGE(O11,R11) -> 0.5
A12: =+VLOOKUP(B12,'INDICADORES CAPTURA'!C:E,3,FALSE) -> JUAN PABLO GIL ALMANZA | B12: SOR_16 | C12: =+AVERAGE(G12,H12,L12) -> 1 | D12: 10 | E12: 10 | F12: =+E12/D12 -> 1 | G12: 1 | H12: 1 | I12: 1 | J12: 1 | K12: 1 | L12: 1 | M12: =+AVERAGE(I12,J12,K12) -> 1 | N12: 0.98077537 | O12: =+G12 -> 1 | P12: 0 | Q12: 0.012397447 | R12: =+IF(Q12<3%,100%,0) -> 1 | S12: =+AVERAGE(O12,R12) -> 1
A13: =+VLOOKUP(B13,'INDICADORES CAPTURA'!C:E,3,FALSE) -> MARTINEZ VARGAS CHRISTAN RICARDO | B13: POPAYAN_1 | C13: =+AVERAGE(G13,H13,L13) -> 1 | D13: 9 | E13: 9 | F13: =+E13/D13 -> 1 | G13: 1 | H13: 1 | I13: 1 | J13: 1 | K13: 0.61538462 | L13: 1 | M13: =+AVERAGE(I13,J13,K13) -> 0.87179487 | N13: 1.0777236 | O13: =+G13 -> 1 | P13: 0 | Q13: 0.034693593 | R13: =+IF(Q13<3%,100%,0) -> 0 | S13: =+AVERAGE(O13,R13) -> 0.5
A14: =+VLOOKUP(B14,'INDICADORES CAPTURA'!C:E,3,FALSE) -> MEJÍA BLANDÓN ASTRID KARINA | B14: SABANETA_1 | C14: =+AVERAGE(G14,H14,L14) -> 0.77777778 | D14: 9 | E14: 7 | F14: =+E14/D14 -> 0.77777778 | G14: 0.77777778 | H14: 0.77777778 | I14: 0.77777778 | J14: 0.77777778 | K14: 1 | L14: 0.77777778 | M14: =+AVERAGE(I14,J14,K14) -> 0.85185185 | N14: 0.9048119 | O14: =+G14 -> 0.77777778 | P14: 0 | Q14: 0.023455156 | R14: =+IF(Q14<3%,100%,0) -> 1 | S14: =+AVERAGE(O14,R14) -> 0.88888889
A15: =+VLOOKUP(B15,'INDICADORES CAPTURA'!C:E,3,FALSE) -> JUAN PABLO GIL ALMANZA | B15: SOR_9 | C15: =+AVERAGE(G15,H15,L15) -> 1 | D15: 8 | E15: 8 | F15: =+E15/D15 -> 1 | G15: 1 | H15: 1 | I15: 1 | J15: 1 | K15: 1 | L15: 1 | M15: =+AVERAGE(I15,J15,K15) -> 1 | N15: 1.1548936 | O15: =+G15 -> 1 | P15: 0 | Q15: 0.017774148 | R15: =+IF(Q15<3%,100%,0) -> 1 | S15: =+AVERAGE(O15,R15) -> 1
A16: =+VLOOKUP(B16,'INDICADORES CAPTURA'!C:E,3,FALSE) -> MELISA MARTINEZ | B16: SOC_12 | C16: =+AVERAGE(G16,H16,L16) -> 0.66666667 | D16: 1 | E16: 1 | F16: =+E16/D16 -> 1 | G16: 1 | H16: 1 | I16: 1 | J16: 0 | K16: 1 | L16: 0 | M16: =+AVERAGE(I16,J16,K16) -> 0.66666667 | N16: 0.91248682 | O16: =+G16 -> 1 | P16: 0 | Q16: 0.0019765242 | R16: =+IF(Q16<3%,100%,0) -> 1 | S16: =+AVERAGE(O16,R16) -> 1
A17: =+VLOOKUP(B17,'INDICADORES CAPTURA'!C:E,3,FALSE) -> PEREZ ZAGARRA AUGUSTO EDUARDO | B17: BARRANQUILLA_3 | C17: =+AVERAGE(G17,H17,L17) -> 0.94444444 | D17: 24 | E17: 22 | F17: =+E17/D17 -> 0.91666667 | G17: 0.95833333 | H17: 0.91666667 | I17: 0.91666667 | J17: 0.95833333 | K17: 0.96666667 | L17: 0.95833333 | M17: =+AVERAGE(I17,J17,K17) -> 0.94722222 | N17: 1.1022421 | O17: =+G17 -> 0.95833333 | P17: 0 | Q17: 0.077544827 | R17: =+IF(Q17<3%,100%,0) -> 0 | S17: =+AVERAGE(O17,R17) -> 0.47916667
A18: =+VLOOKUP(B18,'INDICADORES CAPTURA'!C:E,3,FALSE) -> MEJÍA BLANDÓN ASTRID KARINA | B18: MEDELLIN_3 | C18: =+AVERAGE(G18,H18,L18) -> 0.83333333 | D18: 1 | E18: 1 | F18: =+E18/D18 -> 1 | G18: 1 | H18: 1 | I18: 1 | J18: 1 | K18: 1 | L18: 0.5 | M18: =+AVERAGE(I18,J18,K18) -> 1 | N18: 1.1155377 | O18: =+G18 -> 1 | P18: 0 | Q18: 0.010592086 | R18: =+IF(Q18<3%,100%,0) -> 1 | S18: =+AVERAGE(O18,R18) -> 1
A19: =+VLOOKUP(B19,'INDICADORES CAPTURA'!C:E,3,FALSE) -> PIÑEROS MONTAÑA LAURA ESTEPHANIA | B19: SOC_4 | C19: =+AVERAGE(G19,H19,L19) -> 1 | D19: 17 | E19: 17 | F19: =+E19/D19 -> 1 | G19: 1 | H19: 1 | I19: 1 | J19: 1 | K19: 0.92857143 | L19: 1 | M19: =+AVERAGE(I19,J19,K19) -> 0.97619048 | N19: 1.2520587 | O19: =+G19 -> 1 | P19: 0 | Q19: 0.014402311 | R19: =+IF(Q19<3%,100%,0) -> 1 | S19: =+AVERAGE(O19,R19) -> 1
A20: =+VLOOKUP(B20,'INDICADORES CAPTURA'!C:E,3,FALSE) -> CAMPUZANO IRLET ANDREA | B20: MANIZALES_1 | C20: =+AVERAGE(G20,H20,L20) -> 1 | D20: 18 | E20: 18 | F20: =+E20/D20 -> 1 | G20: 1 | H20: 1 | I20: 1 | J20: 1 | K20: 0.95833333 | L20: 1 | M20: =+AVERAGE(I20,J20,K20) -> 0.98611111 | N20: 0.94401311 | O20: =+G20 -> 1 | P20: 0 | Q20: 0.033953153 | R20: =+IF(Q20<3%,100%,0) -> 0 | S20: =+AVERAGE(O20,R20) -> 0.5
... A23: =+VLOOKUP(B23,'INDICADORES CAPTURA'!C:E,3,FALSE) -> JUAN PABLO GIL ALMANZA | B23: SOR_15 | C23: =+AVERAGE(G23,H23,L23) -> 0.94444444 | D23: 18 | E23: 18 | F23: =+E23/D23 -> 1 | G23: 0.94444444 | H23: 0.94444444 | I23: 0.94444444 | J23: 1 | K23: 1 | L23: 0.94444444 | M23: =+AVERAGE(I23,J23,K23) -> 0.98148148 | N23: 1.0407577 | O23: =+G23 -> 0.94444444 | P23: 0 | Q23: 0.01693458 | R23: =+IF(Q23<3%,100%,0) -> 1 | S23: =+AVERAGE(O23,R23) -> 0.97222222
A24: =+VLOOKUP(B24,'INDICADORES CAPTURA'!C:E,3,FALSE) -> MELISA MARTINEZ | B24: NOC_14 | C24: =+AVERAGE(G24,H24,L24) -> 1 | D24: 1 | E24: 1 | F24: =+E24/D24 -> 1 | G24: 1 | H24: 1 | I24: 1 | J24: 1 | K24: 1 | L24: 1 | M24: =+AVERAGE(I24,J24,K24) -> 1 | N24: 1.3033164 | O24: =+G24 -> 1 | P24: 0 | Q24: 0.026013657 | R24: =+IF(Q24<3%,100%,0) -> 1 | S24: =+O24 -> 1
A25: =+VLOOKUP(B25,'INDICADORES CAPTURA'!C:E,3,FALSE) -> GONZALEZ BARRANTES EDWIN JESSID | B25: VIJ_11 | C25: =+AVERAGE(G25,H25,L25) -> 1 | D25: 9 | E25: 9 | F25: =+E25/D25 -> 1 | G25: 1 | H25: 1 | I25: 1 | J25: 1 | K25: 1 | L25: 1 | M25: =+AVERAGE(I25,J25,K25) -> 1 | N25: 1.0888504 | O25: =+G25 -> 1 | P25: 0 | Q25: 0.02382827 | R25: =+IF(Q25<3%,100%,0) -> 1 | S25: =+AVERAGE(O25,R25) -> 1
A26: =+VLOOKUP(B26,'INDICADORES CAPTURA'!C:E,3,FALSE) -> SÁNCHEZ ZAMBRANO LEIDY NICOLE VANESSA | B26: BARRANCABERMEJA_1 | C26: =+AVERAGE(G26,H26,L26) -> 1 | D26: 5 | E26: 4 | F26: =+E26/D26 -> 0.8 | G26: 1 | H26: 1 | I26: 0.8 | J26: 1 | K26: 0.81818182 | L26: 1 | M26: =+AVERAGE(I26,J26,K26) -> 0.87272727 | N26: 0 | O26: =+G26 -> 1 | P26: 0 | Q26: 0.0254 | R26: =+IF(Q26<3%,100%,0) -> 1 | S26: =+AVERAGE(O26,R26) -> 1
A27: =+VLOOKUP(B27,'INDICADORES CAPTURA'!C:E,3,FALSE) -> PIÑEROS MONTAÑA LAURA ESTEPHANIA | B27: SOC_10 | C27: =+AVERAGE(G27,H27,L27) -> 1 | D27: 12 | E27: 12 | F27: =+E27/D27 -> 1 | G27: 1 | H27: 1 | I27: 1 | J27: 1 | K27: 1 | L27: 1 | M27: =+AVERAGE(I27,J27,K27) -> 1 | N27: 1.1554252 | O27: =+G27 -> 1 | P27: 0 | Q27: 0.030155386 | R27: =+IF(Q27<3%,100%,0) -> 0 | S27: =+AVERAGE(O27,R27) -> 0.5
A28: =+VLOOKUP(B28,'INDICADORES CAPTURA'!C:E,3,FALSE) -> PIÑEROS MONTAÑA LAURA ESTEPHANIA | B28: SOC_13 | C28: =+AVERAGE(G28,H28,L28) -> 1 | D28: 9 | E28: 9 | F28: =+E28/D28 -> 1 | G28: 1 | H28: 1 | I28: 1 | J28: 1 | K28: 1 | L28: 1 | M28: =+AVERAGE(I28,J28,K28) -> 1 | N28: 0.8405048 | O28: =+G28 -> 1 | P28: 0 | Q28: 0.02471696 | R28: =+IF(Q28<3%,100%,0) -> 1 | S28: =+AVERAGE(O28,R28) -> 1
A29: =+VLOOKUP(B29,'INDICADORES CAPTURA'!C:E,3,FALSE) -> MARTINEZ VARGAS CHRISTAN RICARDO | B29: CALI_10 | C29: =+AVERAGE(G29,H29,L29) -> 0.85714286 | D29: 7 | E29: 6 | F29: =+E29/D29 -> 0.85714286 | G29: 0.85714286 | H29: 0.85714286 | I29: 0.85714286 | J29: 0.85714286 | K29: 0.53846154 | L29: 0.85714286 | M29: =+AVERAGE(I29,J29,K29) -> 0.75091575 | N29: 0.50399389 | O29: =+G29 -> 0.85714286 | P29: 0 | Q29: 0.092226844 | R29: =+IF(Q29<3%,100%,0) -> 0 | S29: =+AVERAGE(O29,R29) -> 0.42857143
A30: =+VLOOKUP(B30,'INDICADORES CAPTURA'!C:E,3,FALSE) -> PIÑEROS MONTAÑA LAURA ESTEPHANIA | B30: SOC_15 | C30: =+AVERAGE(G30,H30,L30) -> 1 | D30: 7 | E30: 7 | F30: =+E30/D30 -> 1 | G30: 1 | H30: 1 | I30: 1 | J30: 1 | K30: 0.84615385 | L30: 1 | M30: =+AVERAGE(I30,J30,K30) -> 0.94871795 | N30: 0.90050536 | O30: =+G30 -> 1 | P30: 0 | Q30: 0.013899348 | R30: =+IF(Q30<3%,100%,0) -> 1 | S30: =+AVERAGE(O30,R30) -> 1
A31: =+VLOOKUP(B31,'INDICADORES CAPTURA'!C:E,3,FALSE) -> PEREZ ZAGARRA AUGUSTO EDUARDO | B31: SANTA MARTA_2 | C31: =+AVERAGE(G31,H31,L31) -> 0.98245614 | D31: 19 | E31: 19 | F31: =+E31/D31 -> 1 | G31: 0.94736842 | H31: 1 | I31: 1 | J31: 1 | K31: 1 | L31: 1 | M31: =+AVERAGE(I31,J31,K31) -> 1 | N31: 0.76111264 | O31: =+G31 -> 0.94736842 | P31: 0 | Q31: 0.11624359 | R31: =+IF(Q31<3%,100%,0) -> 0 | S31: =+AVERAGE(O31,R31) -> 0.47368421
A32: =+VLOOKUP(B32,'INDICADORES CAPTURA'!C:E,3,FALSE) -> MELISA MARTINEZ | B32: NTE_3 | C32: =+AVERAGE(G32,H32,L32) -> 1 | D32: 1 | E32: 1 | F32: =+E32/D32 -> 1 | G32: 1 | H32: 1 | I32: 0 | J32: 1 | K32: 1 | L32: 1 | M32: =+AVERAGE(I32,J32,K32) -> 0.66666667 | N32: 1.1219719 | O32: =+G32 -> 1 | P32: 0 | Q32: 0.019292829 | R32: =+IF(Q32<3%,100%,0) -> 1 | S32: =+AVERAGE(O32,R32) -> 1
A33: =+VLOOKUP(B33,'INDICADORES CAPTURA'!C:E,3,FALSE) -> PIÑEROS MONTAÑA LAURA ESTEPHANIA | B33: SOC_9 | C33: =+AVERAGE(G33,H33,L33) -> 1 | D33: 8 | E33: 8 | F33: =+E33/D33 -> 1 | G33: 1 | H33: 1 | I33: 1 | J33: 1 | K33: 1 | L33: 1 | M33: =+AVERAGE(I33,J33,K33) -> 1 | N33: 1.3021514 | O33: =+G33 -> 1 | P33: 0 | Q33: 0.033649692 | R33: =+IF(Q33<3%,100%,0) -> 0 | S33: =+AVERAGE(O33,R33) -> 0.5
A34: =+VLOOKUP(B34,'INDICADORES CAPTURA'!C:E,3,FALSE) -> MEJÍA BLANDÓN ASTRID KARINA | B34: MEDELLIN_7 | C34: =+AVERAGE(G34,H34,L34) -> 0.77777778 | D34: 1 | E34: 1 | F34: =+E34/D34 -> 1 | G34: 1 | H34: 1 | I34: 1 | J34: 1 | K34: 1 | L34: 0.33333333 | M34: =+AVERAGE(I34,J34,K34) -> 1 | N34: 0.99284686 | O34: =+G34 -> 1 | P34: 0 | Q34: 0.086272007 | R34: =+IF(Q34<3%,100%,0) -> 0 | S34: =+AVERAGE(O34,R34) -> 0.5
A35: =+VLOOKUP(B35,'INDICADORES CAPTURA'!C:E,3,FALSE) -> MELISA MARTINEZ | B35: NOC_6 | C35: =+AVERAGE(G35,H35,L35) -> 1 | D35: 9 | E35: 9 | F35: =+E35/D35 -> 1 | G35: 1 | H35: 1 | I35: 1 | J35: 1 | K35: 1 | L35: 1 | M35: =+AVERAGE(I35,J35,K35) -> 1 | N35: 0.89061568 | O35: =+G35 -> 1 | P35: 0 | Q35: 0.0075956438 | R35: =+IF(Q35<3%,100%,0) -> 1 | S35: =+AVERAGE(O35,R35) -> 1
A36: =+VLOOKUP(B36,'INDICADORES CAPTURA'!C:E,3,FALSE) -> PIÑEROS MONTAÑA LAURA ESTEPHANIA | B36: SOC_16 | C36: =+AVERAGE(G36,H36,L36) -> 1 | D36: 1 | E36: 1 | F36: =+E36/D36 -> 1 | G36: 1 | H36: 1 | I36: 1 | J36: 1 | K36: 1 | L36: 1 | M36: =+AVERAGE(I36,J36,K36) -> 1 | N36: 0.86907069 | O36: =+G36 -> 1 | P36: 0 | Q36: 0.020457327 | R36: =+IF(Q36<3%,100%,0) -> 1 | S36: =+AVERAGE(O36,R36) -> 1
... A46: =+VLOOKUP(B46,'INDICADORES CAPTURA'!C:E,3,FALSE) -> PIÑEROS MONTAÑA LAURA ESTEPHANIA | B46: SOC_14 | C46: =+AVERAGE(G46,H46,L46) -> 1 | D46: 16 | E46: 16 | F46: =+E46/D46 -> 1 | G46: 1 | H46: 1 | I46: 0.9375 | J46: 1 | K46: 0.91666667 | L46: 1 | M46: =+AVERAGE(I46,J46,K46) -> 0.95138889 | N46: 0.9116454 | O46: =+G46 -> 1 | P46: 0 | Q46: 0.043701673 | R46: =+IF(Q46<3%,100%,0) -> 0 | S46: =+AVERAGE(O46,R46) -> 0.5
A47: =+VLOOKUP(B47,'INDICADORES CAPTURA'!C:E,3,FALSE) -> SUSANA SILVA MENDOZA | B47: CTR_4 | C47: =+AVERAGE(G47,H47,L47) -> 1 | D47: 2 | E47: 2 | F47: =+E47/D47 -> 1 | G47: 1 | H47: 1 | I47: 0 | J47: 1 | K47: 0.75 | L47: 1 | M47: =+AVERAGE(I47,J47,K47) -> 0.58333333 | N47: 1.5777985 | O47: =+G47 -> 1 | P47: 0 | Q47: 0.014739558 | R47: =+IF(Q47<3%,100%,0) -> 1 | S47: =+O47 -> 1
A48: =+VLOOKUP(B48,'INDICADORES CAPTURA'!C:E,3,FALSE) -> MEJÍA BLANDÓN ASTRID KARINA | B48: ENVIGADO_1 | C48: =+AVERAGE(G48,H48,L48) -> 1 | D48: 2 | E48: 2 | F48: =+E48/D48 -> 1 | G48: 1 | H48: 1 | I48: 1 | J48: 1 | K48: 0.75 | L48: 1 | M48: =+AVERAGE(I48,J48,K48) -> 0.91666667 | N48: 1.2388963 | O48: =+G48 -> 1 | P48: 0 | Q48: 0.0069404484 | R48: =+IF(Q48<3%,100%,0) -> 1 | S48: =+AVERAGE(O48,R48) -> 1
A49: =+VLOOKUP(B49,'INDICADORES CAPTURA'!C:E,3,FALSE) -> MELISA MARTINEZ | B49: NOC_16 | C49: =+AVERAGE(G49,H49,L49) -> 1 | D49: 10 | E49: 10 | F49: =+E49/D49 -> 1 | G49: 1 | H49: 1 | I49: 1 | J49: 1 | K49: 1 | L49: 1 | M49: =+AVERAGE(I49,J49,K49) -> 1 | N49: 0.87276123 | O49: =+G49 -> 1 | P49: 0 | Q49: 0.018126571 | R49: =+IF(Q49<3%,100%,0) -> 1 | S49: =+AVERAGE(O49,R49) -> 1
A50: =+VLOOKUP(B50,'INDICADORES CAPTURA'!C:E,3,FALSE) -> SÁNCHEZ ZAMBRANO LEIDY NICOLE VANESSA | B50: BUCARAMANGA_9 | C50: =+AVERAGE(G50,H50,L50) -> 0.93333333 | D50: 10 | E50: 10 | F50: =+E50/D50 -> 1 | G50: 0.9 | H50: 0.9 | I50: 0.9 | J50: 1 | K50: 0.94736842 | L50: 1 | M50: =+AVERAGE(I50,J50,K50) -> 0.94912281 | N50: 0 | O50: =+G50 -> 0.9 | P50: 0 | Q50: 0.0254 | R50: =+IF(Q50<3%,100%,0) -> 1 | S50: =+AVERAGE(O50,R50) -> 0.95
A51: =+VLOOKUP(B51,'INDICADORES CAPTURA'!C:E,3,FALSE) -> SUSANA SILVA MENDOZA | B51: CTR_13 | C51: =+AVERAGE(G51,H51,L51) -> 1 | D51: 2 | E51: 2 | F51: =+E51/D51 -> 1 | G51: 1 | H51: 1 | I51: 1 | J51: 1 | K51: 1 | L51: 1 | M51: =+AVERAGE(I51,J51,K51) -> 1 | N51: 1.1378459 | O51: =+G51 -> 1 | P51: 0 | Q51: 0.0287163 | R51: =+IF(Q51<3%,100%,0) -> 1 | S51: =+O51 -> 1
A52: =+VLOOKUP(B52,'INDICADORES CAPTURA'!C:E,3,FALSE) -> OSSA TABARES JAZMIN BERNARDA | B52: MEDELLIN_11 | C52: =+AVERAGE(G52,H52,L52) -> 1 | D52: 16 | E52: 16 | F52: =+E52/D52 -> 1 | G52: 1 | H52: 1 | I52: 1 | J52: 1 | K52: 1 | L52: 1 | M52: =+AVERAGE(I52,J52,K52) -> 1 | N52: 1.0459483 | O52: =+G52 -> 1 | P52: 0 | Q52: 0.017710933 | R52: =+IF(Q52<3%,100%,0) -> 1 | S52: =+AVERAGE(O52,R52) -> 1
A53: =+VLOOKUP(B53,'INDICADORES CAPTURA'!C:E,3,FALSE) -> PEREZ ZAGARRA AUGUSTO EDUARDO | B53: SANTA MARTA_1 | C53: =+AVERAGE(G53,H53,L53) -> 1 | D53: 18 | E53: 18 | F53: =+E53/D53 -> 1 | G53: 1 | H53: 1 | I53: 1 | J53: 1 | K53: 1 | L53: 1 | M53: =+AVERAGE(I53,J53,K53) -> 1 | N53: 1.1574482 | O53: =+G53 -> 1 | P53: 0 | Q53: 0.07464614 | R53: =+IF(Q53<3%,100%,0) -> 0 | S53: =+AVERAGE(O53,R53) -> 0.5
A54: =+VLOOKUP(B54,'INDICADORES CAPTURA'!C:E,3,FALSE) -> JUAN PABLO GIL ALMANZA | B54: SOR_1 | C54: =+AVERAGE(G54,H54,L54) -> 1 | D54: 14 | E54: 14 | F54: =+E54/D54 -> 1 | G54: 1 | H54: 1 | I54: 1 | J54: 1 | K54: 1 | L54: 1 | M54: =+AVERAGE(I54,J54,K54) -> 1 | N54: 1.1783685 | O54: =+G54 -> 1 | P54: 0 | Q54: 0.01464773 | R54: =+IF(Q54<3%,100%,0) -> 1 | S54: =+AVERAGE(O54,R54) -> 1
A55: =+VLOOKUP(B55,'INDICADORES CAPTURA'!C:E,3,FALSE) -> SUSANA SILVA MENDOZA | B55: CTR_15 | C55: =+AVERAGE(G55,H55,L55) -> 1 | D55: 15 | E55: 15 | F55: =+E55/D55 -> 1 | G55: 1 | H55: 1 | I55: 0.86666667 | J55: 1 | K55: 1 | L55: 1 | M55: =+AVERAGE(I55,J55,K55) -> 0.95555556 | N55: 1.1243968 | O55: =+G55 -> 1 | P55: 0 | Q55: 0.034225242 | R55: =+IF(Q55<3%,100%,0) -> 0 | S55: =+AVERAGE(O55,R55) -> 0.5
A56: =+VLOOKUP(B56,'INDICADORES CAPTURA'!C:E,3,FALSE) -> PIÑEROS MONTAÑA LAURA ESTEPHANIA | B56: SOC_1 | C56: =+AVERAGE(G56,H56,L56) -> 1 | D56: 4 | E56: 4 | F56: =+E56/D56 -> 1 | G56: 1 | H56: 1 | I56: 1 | J56: 1 | K56: 0.77777778 | L56: 1 | M56: =+AVERAGE(I56,J56,K56) -> 0.92592593 | N56: 1.1074848 | O56: =+G56 -> 1 | P56: 0 | Q56: 0.0099603788 | R56: =+IF(Q56<3%,100%,0) -> 1 | S56: =+AVERAGE(O56,R56) -> 1
A57: =+VLOOKUP(B57,'INDICADORES CAPTURA'!C:E,3,FALSE) -> SÁNCHEZ ZAMBRANO LEIDY NICOLE VANESSA | B57: BUCARAMANGA_6 | C57: =+AVERAGE(G57,H57,L57) -> 0.87179487 | D57: 13 | E57: 13 | F57: =+E57/D57 -> 1 | G57: 0.76923077 | H57: 0.84615385 | I57: 0.84615385 | J57: 1 | K57: 1 | L57: 1 | M57: =+AVERAGE(I57,J57,K57) -> 0.94871795 | N57: 0 | O57: =+G57 -> 0.76923077 | P57: 0 | Q57: 0.0254 | R57: =+IF(Q57<3%,100%,0) -> 1 | S57: =+AVERAGE(O57,R57) -> 0.88461538
A58: =+VLOOKUP(B58,'INDICADORES CAPTURA'!C:E,3,FALSE) -> SUSANA SILVA MENDOZA | B58: CTR_9 | C58: =+AVERAGE(G58,H58,L58) -> 1 | D58: 5 | E58: 5 | F58: =+E58/D58 -> 1 | G58: 1 | H58: 1 | I58: 1 | J58: 1 | K58: 1 | L58: 1 | M58: =+AVERAGE(I58,J58,K58) -> 1 | N58: 0.75218714 | O58: =+G58 -> 1 | P58: 0 | Q58: 0.0088962317 | R58: =+IF(Q58<3%,100%,0) -> 1 | S58: =+AVERAGE(O58,R58) -> 1
A59: =+VLOOKUP(B59,'INDICADORES CAPTURA'!C:E,3,FALSE) -> GONZALEZ BARRANTES EDWIN JESSID | B59: VIJ_7 | C59: =+AVERAGE(G59,H59,L59) -> 1 | D59: 13 | E59: 13 | F59: =+E59/D59 -> 1 | G59: 1 | H59: 1 | I59: 0.92307692 | J59: 1 | K59: 0.77777778 | L59: 1 | M59: =+AVERAGE(I59,J59,K59) -> 0.9002849 | N59: 1.1778604 | O59: =+G59 -> 1 | P59: 0 | Q59: 0.023315666 | R59: =+IF(Q59<3%,100%,0) -> 1 | S59: =+AVERAGE(O59,R59) -> 1
A60: =+VLOOKUP(B60,'INDICADORES CAPTURA'!C:E,3,FALSE) -> PIÑEROS MONTAÑA LAURA ESTEPHANIA | B60: SOC_17 | C60: =+AVERAGE(G60,H60,L60) -> 1 | D60: 18 | E60: 18 | F60: =+E60/D60 -> 1 | G60: 1 | H60: 1 | I60: 1 | J60: 1 | K60: 0.90909091 | L60: 1 | M60: =+AVERAGE(I60,J60,K60) -> 0.96969697 | N60: 1.1709952 | O60: =+G60 -> 1 | P60: 0 | Q60: 0.020768817 | R60: =+IF(Q60<3%,100%,0) -> 1 | S60: =+AVERAGE(O60,R60) -> 1
A61: =+VLOOKUP(B61,'INDICADORES CAPTURA'!C:E,3,FALSE) -> JUAN PABLO GIL ALMANZA | B61: SOR_12 | C61: =+AVERAGE(G61,H61,L61) -> 1 | D61: 15 | E61: 15 | F61: =+E61/D61 -> 1 | G61: 1 | H61: 1 | I61: 1 | J61: 1 | K61: 1 | L61: 1 | M61: =+AVERAGE(I61,J61,K61) -> 1 | N61: 1.0490627 | O61: =+G61 -> 1 | P61: 0 | Q61: 0.024540321 | R61: =+IF(Q61<3%,100%,0) -> 1 | S61: =+AVERAGE(O61,R61) -> 1
A62: =+VLOOKUP(B62,'INDICADORES CAPTURA'!C:E,3,FALSE) -> PIÑEROS MONTAÑA LAURA ESTEPHANIA | B62: SOC_11 | C62: =+AVERAGE(G62,H62,L62) -> 1 | D62: 7 | E62: 7 | F62: =+E62/D62 -> 1 | G62: 1 | H62: 1 | I62: 1 | J62: 1 | K62: 1 | L62: 1 | M62: =+AVERAGE(I62,J62,K62) -> 1 | N62: 1.0321854 | O62: =+G62 -> 1 | P62: 0 | Q62: 0.017602778 | R62: =+IF(Q62<3%,100%,0) -> 1 | S62: =+AVERAGE(O62,R62) -> 1
A63: =+VLOOKUP(B63,'INDICADORES CAPTURA'!C:E,3,FALSE) -> MEJÍA BLANDÓN ASTRID KARINA | B63: RIONEGRO_1 | C63: =+AVERAGE(G63,H63,L63) -> 0.875 | D63: 8 | E63: 7 | F63: =+E63/D63 -> 0.875 | G63: 0.875 | H63: 0.875 | I63: 0.25 | J63: 0.875 | K63: 0.52941176 | L63: 0.875 | M63: =+AVERAGE(I63,J63,K63) -> 0.55147059 | N63: 1.024128 | O63: =+G63 -> 0.875 | P63: 0 | Q63: 0.011951254 | R63: =+IF(Q63<3%,100%,0) -> 1 | S63: =+AVERAGE(O63,R63) -> 0.9375
... A65: =+VLOOKUP(B65,'INDICADORES CAPTURA'!C:E,3,FALSE) -> SÁNCHEZ ZAMBRANO LEIDY NICOLE VANESSA | B65: BARRANCABERMEJA_2 | C65: =+AVERAGE(G65,H65,L65) -> 1 | D65: 1 | E65: 1 | F65: =+E65/D65 -> 1 | G65: 1 | H65: 1 | I65: 1 | J65: 1 | K65: 1 | L65: 1 | M65: =+AVERAGE(I65,J65,K65) -> 1 | N65: 0 | O65: =+G65 -> 1 | P65: 0 | Q65: 0.0254 | R65: =+IF(Q65<3%,100%,0) -> 1 | S65: =+AVERAGE(O65,R65) -> 1
A66: =+VLOOKUP(B66,'INDICADORES CAPTURA'!C:E,3,FALSE) -> SUSANA SILVA MENDOZA | B66: CTR_5 | C66: =+AVERAGE(G66,H66,L66) -> 0.66666667 | D66: 1 | E66: 1 | F66: =+E66/D66 -> 1 | G66: 1 | H66: 1 | I66: 1 | J66: 0 | K66: 1 | L66: 0 | M66: =+AVERAGE(I66,J66,K66) -> 0.66666667 | N66: 1.5777985 | O66: =+G66 -> 1 | P66: 0 | Q66: 0.014739558 | R66: =+IF(Q66<3%,100%,0) -> 1 | S66: =+O66 -> 1
A67: =+VLOOKUP(B67,'INDICADORES CAPTURA'!C:E,3,FALSE) -> MARTINEZ VARGAS CHRISTAN RICARDO | B67: CALI_13 | C67: =+AVERAGE(G67,H67,L67) -> 1 | D67: 7 | E67: 7 | F67: =+E67/D67 -> 1 | G67: 1 | H67: 1 | I67: 0 | J67: 1 | K67: 1 | L67: 1 | M67: =+AVERAGE(I67,J67,K67) -> 0.66666667 | N67: 0.86802056 | O67: =+G67 -> 1 | P67: 0 | Q67: 0.065233602 | R67: =+IF(Q67<3%,100%,0) -> 0 | S67: =+O67 -> 1
A68: =+VLOOKUP(B68,'INDICADORES CAPTURA'!C:E,3,FALSE) -> SÁNCHEZ ZAMBRANO LEIDY NICOLE VANESSA | B68: BUCARAMANGA_2 | C68: =+AVERAGE(G68,H68,L68) -> 1 | D68: 4 | E68: 4 | F68: =+E68/D68 -> 1 | G68: 1 | H68: 1 | I68: 0.5 | J68: 1 | K68: 0.92307692 | L68: 1 | M68: =+AVERAGE(I68,J68,K68) -> 0.80769231 | N68: 0 | O68: =+G68 -> 1 | P68: 0 | Q68: 0.0254 | R68: =+IF(Q68<3%,100%,0) -> 1 | S68: =+AVERAGE(O68,R68) -> 1
A69: =+VLOOKUP(B69,'INDICADORES CAPTURA'!C:E,3,FALSE) -> PIÑEROS MONTAÑA LAURA ESTEPHANIA | B69: SOC_6 | C69: =+AVERAGE(G69,H69,L69) -> 1 | D69: 16 | E69: 16 | F69: =+E69/D69 -> 1 | G69: 1 | H69: 1 | I69: 1 | J69: 1 | K69: 0.66666667 | L69: 1 | M69: =+AVERAGE(I69,J69,K69) -> 0.88888889 | N69: 1.0301859 | O69: =+G69 -> 1 | P69: 0 | Q69: 0.013672897 | R69: =+IF(Q69<3%,100%,0) -> 1 | S69: =+AVERAGE(O69,R69) -> 1
A70: =+VLOOKUP(B70,'INDICADORES CAPTURA'!C:E,3,FALSE) -> JUAN PABLO GIL ALMANZA | B70: SOR_8 | C70: =+AVERAGE(G70,H70,L70) -> 1 | D70: 5 | E70: 5 | F70: =+E70/D70 -> 1 | G70: 1 | H70: 1 | I70: 1 | J70: 1 | K70: 1 | L70: 1 | M70: =+AVERAGE(I70,J70,K70) -> 1 | N70: 1.1790921 | O70: =+G70 -> 1 | P70: 0 | Q70: 0.015048185 | R70: =+IF(Q70<3%,100%,0) -> 1 | S70: =+AVERAGE(O70,R70) -> 1
A71: =+VLOOKUP(B71,'INDICADORES CAPTURA'!C:E,3,FALSE) -> MARTINEZ VARGAS CHRISTAN RICARDO | B71: CALI_11 | C71: =+AVERAGE(G71,H71,L71) -> 1 | D71: 14 | E71: 14 | F71: =+E71/D71 -> 1 | G71: 1 | H71: 1 | I71: 0.92857143 | J71: 1 | K71: 0.26086957 | L71: 1 | M71: =+AVERAGE(I71,J71,K71) -> 0.72981366 | N71: 0.82308367 | O71: =+G71 -> 1 | P71: 0 | Q71: 0.12150248 | R71: =+IF(Q71<3%,100%,0) -> 0 | S71: =+AVERAGE(O71,R71) -> 0.5
A72: =+VLOOKUP(B72,'INDICADORES CAPTURA'!C:E,3,FALSE) -> MEJÍA BLANDÓN ASTRID KARINA | B72: MEDELLIN_14 | C72: =+AVERAGE(G72,H72,L72) -> 0.87878788 | D72: 11 | E72: 10 | F72: =+E72/D72 -> 0.90909091 | G72: 0.81818182 | H72: 0.90909091 | I72: 0.63636364 | J72: 0.90909091 | K72: 0.76470588 | L72: 0.90909091 | M72: =+AVERAGE(I72,J72,K72) -> 0.77005348 | N72: 1.0386505 | O72: =+G72 -> 0.81818182 | P72: 0 | Q72: 0.023589739 | R72: =+IF(Q72<3%,100%,0) -> 1 | S72: =+O72 -> 0.81818182
A73: =+VLOOKUP(B73,'INDICADORES CAPTURA'!C:E,3,FALSE) -> MELISA MARTINEZ | B73: NOC_7 | C73: =+AVERAGE(G73,H73,L73) -> 1 | D73: 4 | E73: 4 | F73: =+E73/D73 -> 1 | G73: 1 | H73: 1 | I73: 1 | J73: 1 | K73: 0.88888889 | L73: 1 | M73: =+AVERAGE(I73,J73,K73) -> 0.96296296 | N73: 1.0858986 | O73: =+G73 -> 1 | P73: 0 | Q73: 0.0094538235 | R73: =+IF(Q73<3%,100%,0) -> 1 | S73: =+AVERAGE(O73,R73) -> 1
A74: =+VLOOKUP(B74,'INDICADORES CAPTURA'!C:E,3,FALSE) -> SUSANA SILVA MENDOZA | B74: CTR_10 | C74: =+AVERAGE(G74,H74,L74) -> 1 | D74: 16 | E74: 16 | F74: =+E74/D74 -> 1 | G74: 1 | H74: 1 | I74: 1 | J74: 1 | K74: 1 | L74: 1 | M74: =+AVERAGE(I74,J74,K74) -> 1 | N74: 2.6859172 | O74: =+G74 -> 1 | P74: 0 | Q74: 0.16982596 | R74: =+IF(Q74<3%,100%,0) -> 0 | S74: =+O74 -> 1
A75: =+VLOOKUP(B75,'INDICADORES CAPTURA'!C:E,3,FALSE) -> GIL MARTINEZ JENNIFER STEFANNIE | B75: NTE_14 | C75: =+AVERAGE(G75,H75,L75) -> 1 | D75: 4 | E75: 4 | F75: =+E75/D75 -> 1 | G75: 1 | H75: 1 | I75: 1 | J75: 1 | K75: 1 | L75: 1 | M75: =+AVERAGE(I75,J75,K75) -> 1 | N75: 1.5073077 | O75: =+G75 -> 1 | P75: 0 | Q75: 0.0090971424 | R75: =+IF(Q75<3%,100%,0) -> 1 | S75: =+AVERAGE(O75,R75) -> 1
A76: =+VLOOKUP(B76,'INDICADORES CAPTURA'!C:E,3,FALSE) -> MELISA MARTINEZ | B76: NOC_1 | C76: =+AVERAGE(G76,H76,L76) -> 1 | D76: 7 | E76: 7 | F76: =+E76/D76 -> 1 | G76: 1 | H76: 1 | I76: 1 | J76: 1 | K76: 1 | L76: 1 | M76: =+AVERAGE(I76,J76,K76) -> 1 | N76: 1.1734626 | O76: =+G76 -> 1 | P76: 0 | Q76: 0.095530747 | R76: =+IF(Q76<3%,100%,0) -> 0 | S76: =+O76 -> 1
A77: =+VLOOKUP(B77,'INDICADORES CAPTURA'!C:E,3,FALSE) -> BOLAÑOS QUEVEDO ALEXIS | B77: CALI_14 | C77: =+AVERAGE(G77,H77,L77) -> 0.97222222 | D77: 12 | E77: 12 | F77: =+E77/D77 -> 1 | G77: 0.91666667 | H77: 1 | I77: 0.41666667 | J77: 1 | K77: 0.85714286 | L77: 1 | M77: =+AVERAGE(I77,J77,K77) -> 0.75793651 | N77: 1.0891888 | O77: =+G77 -> 0.91666667 | P77: 0 | Q77: 0.031965489 | R77: =+IF(Q77<3%,100%,0) -> 0 | S77: =+AVERAGE(O77,R77) -> 0.45833333
A78: =+VLOOKUP(B78,'INDICADORES CAPTURA'!C:E,3,FALSE) -> OSSA TABARES JAZMIN BERNARDA | B78: MEDELLIN_12 | C78: =+AVERAGE(G78,H78,L78) -> 0.80555556 | D78: 12 | E78: 10 | F78: =+E78/D78 -> 0.83333333 | G78: 0.75 | H78: 0.83333333 | I78: 0.83333333 | J78: 0.83333333 | K78: 0.35 | L78: 0.83333333 | M78: =+AVERAGE(I78,J78,K78) -> 0.67222222 | N78: 1.0267242 | O78: =+G78 -> 0.75 | P78: 0 | Q78: 0.030302701 | R78: =+IF(Q78<3%,100%,0) -> 0 | S78: =+AVERAGE(O78,R78) -> 0.375
A79: =+VLOOKUP(B79,'INDICADORES CAPTURA'!C:E,3,FALSE) -> MELISA MARTINEZ | B79: NOC_9 | C79: =+AVERAGE(G79,H79,L79) -> 1 | D79: 13 | E79: 13 | F79: =+E79/D79 -> 1 | G79: 1 | H79: 1 | I79: 0.84615385 | J79: 1 | K79: 1 | L79: 1 | M79: =+AVERAGE(I79,J79,K79) -> 0.94871795 | N79: 1.0448137 | O79: =+G79 -> 1 | P79: 0 | Q79: 0.027435996 | R79: =+IF(Q79<3%,100%,0) -> 1 | S79: =+AVERAGE(O79,R79) -> 1
A80: =+VLOOKUP(B80,'INDICADORES CAPTURA'!C:E,3,FALSE) -> OSSA TABARES JAZMIN BERNARDA | B80: BELLO_2 | C80: =+AVERAGE(G80,H80,L80) -> 1 | D80: 5 | E80: 5 | F80: =+E80/D80 -> 1 | G80: 1 | H80: 1 | I80: 1 | J80: 1 | K80: 1 | L80: 1 | M80: =+AVERAGE(I80,J80,K80) -> 1 | N80: 0.96476294 | O80: =+G80 -> 1 | P80: 0 | Q80: 0.018048675 | R80: =+IF(Q80<3%,100%,0) -> 1 | S80: =+AVERAGE(O80,R80) -> 1
A81: =+VLOOKUP(B81,'INDICADORES CAPTURA'!C:E,3,FALSE) -> SUSANA SILVA MENDOZA | B81: CTR_6 | C81: =+AVERAGE(G81,H81,L81) -> 1 | D81: 5 | E81: 4 | F81: =+E81/D81 -> 0.8 | G81: 1 | H81: 1 | I81: 0.8 | J81: 1 | K81: 1 | L81: 1 | M81: =+AVERAGE(I81,J81,K81) -> 0.93333333 | N81: 0.98928991 | O81: =+G81 -> 1 | P81: 0 | Q81: 0.011910746 | R81: =+IF(Q81<3%,100%,0) -> 1 | S81: =+AVERAGE(O81,R81) -> 1
A82: =+VLOOKUP(B82,'INDICADORES CAPTURA'!C:E,3,FALSE) -> SÁNCHEZ ZAMBRANO LEIDY NICOLE VANESSA | B82: BUCARAMANGA_1 | C82: =+AVERAGE(G82,H82,L82) -> 0.83333333 | D82: 4 | E82: 4 | F82: =+E82/D82 -> 1 | G82: 0.75 | H82: 0.75 | I82: 0.5 | J82: 1 | K82: 1 | L82: 1 | M82: =+AVERAGE(I82,J82,K82) -> 0.83333333 | N82: 0 | O82: =+G82 -> 0.75 | P82: 0 | Q82: 0.0254 | R82: =+IF(Q82<3%,100%,0) -> 1 | S82: =+AVERAGE(O82,R82) -> 0.875
A83: =+VLOOKUP(B83,'INDICADORES CAPTURA'!C:E,3,FALSE) -> CAMPUZANO IRLET ANDREA | B83: CARTAGO_1 | C83: =+AVERAGE(G83,H83,L83) -> 1 | D83: 17 | E83: 17 | F83: =+E83/D83 -> 1 | G83: 1 | H83: 1 | I83: 0.94117647 | J83: 1 | K83: 0.7826087 | L83: 1 | M83: =+AVERAGE(I83,J83,K83) -> 0.90792839 | N83: 1.1447375 | O83: =+G83 -> 1 | P83: 0 | Q83: 0.032685649 | R83: =+IF(Q83<3%,100%,0) -> 0 | S83: =+AVERAGE(O83,R83) -> 0.5
A84: =+VLOOKUP(B84,'INDICADORES CAPTURA'!C:E,3,FALSE) -> MELISA MARTINEZ | B84: NOC_5 | C84: =+AVERAGE(G84,H84,L84) -> 1 | D84: 3 | E84: 3 | F84: =+E84/D84 -> 1 | G84: 1 | H84: 1 | I84: 1 | J84: 1 | K84: 1 | L84: 1 | M84: =+AVERAGE(I84,J84,K84) -> 1 | N84: 1.0418462 | O84: =+G84 -> 1 | P84: 0 | Q84: 0.012262797 | R84: =+IF(Q84<3%,100%,0) -> 1 | S84: =+O84 -> 1
A85: =+VLOOKUP(B85,'INDICADORES CAPTURA'!C:E,3,FALSE) -> JUAN PABLO GIL ALMANZA | B85: SOR_10 | C85: =+AVERAGE(G85,H85,L85) -> 1 | D85: 16 | E85: 16 | F85: =+E85/D85 -> 1 | G85: 1 | H85: 1 | I85: 0.625 | J85: 1 | K85: 1 | L85: 1 | M85: =+AVERAGE(I85,J85,K85) -> 0.875 | N85: 1.0265769 | O85: =+G85 -> 1 | P85: 0 | Q85: 0.0055750738 | R85: =+IF(Q85<3%,100%,0) -> 1 | S85: =+O85 -> 1
A86: =+VLOOKUP(B86,'INDICADORES CAPTURA'!C:E,3,FALSE) -> PEREZ ZAGARRA AUGUSTO EDUARDO | B86: BARRANQUILLA_1 | C86: =+AVERAGE(G86,H86,L86) -> 1 | D86: 19 | E86: 19 | F86: =+E86/D86 -> 1 | G86: 1 | H86: 1 | I86: 1 | J86: 1 | K86: 0.80769231 | L86: 1 | M86: =+AVERAGE(I86,J86,K86) -> 0.93589744 | N86: 1.0046021 | O86: =+G86 -> 1 | P86: 0 | Q86: 0.080080627 | R86: =+IF(Q86<3%,100%,0) -> 0 | S86: =+AVERAGE(O86,R86) -> 0.5
A87: =+VLOOKUP(B87,'INDICADORES CAPTURA'!C:E,3,FALSE) -> CAMPUZANO IRLET ANDREA | B87: PEREIRA_2 | C87: =+AVERAGE(G87,H87,L87) -> 0.96969697 | D87: 11 | E87: 11 | F87: =+E87/D87 -> 1 | G87: 0.90909091 | H87: 1 | I87: 0.81818182 | J87: 1 | K87: 0.91666667 | L87: 1 | M87: =+AVERAGE(I87,J87,K87) -> 0.91161616 | N87: 1.1204992 | O87: =+G87 -> 0.90909091 | P87: 0 | Q87: 0.016023394 | R87: =+IF(Q87<3%,100%,0) -> 1 | S87: =+AVERAGE(O87,R87) -> 0.95454545
A88: =+VLOOKUP(B88,'INDICADORES CAPTURA'!C:E,3,FALSE) -> MELISA MARTINEZ | B88: NOC_4 | C88: =+AVERAGE(G88,H88,L88) -> 1 | D88: 15 | E88: 15 | F88: =+E88/D88 -> 1 | G88: 1 | H88: 1 | I88: 0.93333333 | J88: 1 | K88: 1 | L88: 1 | M88: =+AVERAGE(I88,J88,K88) -> 0.97777778 | N88: 0.98320594 | O88: =+G88 -> 1 | P88: 0 | Q88: 0.017804094 | R88: =+IF(Q88<3%,100%,0) -> 1 | S88: =+AVERAGE(O88,R88) -> 1
A89: =+VLOOKUP(B89,'INDICADORES CAPTURA'!C:E,3,FALSE) -> PIÑEROS MONTAÑA LAURA ESTEPHANIA | B89: SOC_2 | C89: =+AVERAGE(G89,H89,L89) -> 1 | D89: 4 | E89: 4 | F89: =+E89/D89 -> 1 | G89: 1 | H89: 1 | I89: 1 | J89: 1 | K89: 1 | L89: 1 | M89: =+AVERAGE(I89,J89,K89) -> 1 | N89: 0.92064877 | O89: =+G89 -> 1 | P89: 0 | Q89: 0.039665413 | R89: =+IF(Q89<3%,100%,0) -> 0 | S89: =+AVERAGE(O89,R89) -> 0.5
A90: =+VLOOKUP(B90,'INDICADORES CAPTURA'!C:E,3,FALSE) -> GONZALEZ BARRANTES EDWIN JESSID | B90: VIJ_1 | C90: =+AVERAGE(G90,H90,L90) -> 0.9047619 | D90: 14 | E90: 12 | F90: =+E90/D90 -> 0.85714286 | G90: 0.92857143 | H90: 0.85714286 | I90: 0.78571429 | J90: 0.92857143 | K90: 0.86206897 | L90: 0.92857143 | M90: =+AVERAGE(I90,J90,K90) -> 0.85878489 | N90: 1.1405554 | O90: =+G90 -> 0.92857143 | P90: 0 | Q90: 0.023175372 | R90: =+IF(Q90<3%,100%,0) -> 1 | S90: =+AVERAGE(O90,R90) -> 0.96428571
A91: =+VLOOKUP(B91,'INDICADORES CAPTURA'!C:E,3,FALSE) -> JUAN PABLO GIL ALMANZA | B91: SOR_7 | C91: =+AVERAGE(G91,H91,L91) -> 1 | D91: 14 | E91: 14 | F91: =+E91/D91 -> 1 | G91: 1 | H91: 1 | I91: 1 | J91: 1 | K91: 1 | L91: 1 | M91: =+AVERAGE(I91,J91,K91) -> 1 | N91: 1.0518477 | O91: =+G91 -> 1 | P91: 0 | Q91: 0.032843345 | R91: =+IF(Q91<3%,100%,0) -> 0 | S91: =+AVERAGE(O91,R91) -> 0.5
A92: =+VLOOKUP(B92,'INDICADORES CAPTURA'!C:E,3,FALSE) -> OSSA TABARES JAZMIN BERNARDA | B92: BELLO_1 | C92: =+AVERAGE(G92,H92,L92) -> 1 | D92: 16 | E92: 16 | F92: =+E92/D92 -> 1 | G92: 1 | H92: 1 | I92: 0.875 | J92: 1 | K92: 1 | L92: 1 | M92: =+AVERAGE(I92,J92,K92) -> 0.95833333 | N92: 1.0584517 | O92: =+G92 -> 1 | P92: 0 | Q92: 0.024937467 | R92: =+IF(Q92<3%,100%,0) -> 1 | S92: =+AVERAGE(O92,R92) -> 1
A93: =+VLOOKUP(B93,'INDICADORES CAPTURA'!C:E,3,FALSE) -> #N/A | B93: GIRÓN_1 | C93: =+AVERAGE(G93,H93,L93) -> 1 | D93: 13 | E93: 13 | F93: =+E93/D93 -> 1 | G93: 1 | H93: 1 | I93: 1 | J93: 1 | K93: 0.92 | L93: 1 | M93: =+AVERAGE(I93,J93,K93) -> 0.97333333 | N93: 0 | O93: =+G93 -> 1 | P93: 0 | Q93: 0 | R93: =+IF(Q93<3%,100%,0) -> 1 | S93: =+AVERAGE(O93,R93) -> 1
A94: =+VLOOKUP(B94,'INDICADORES CAPTURA'!C:E,3,FALSE) -> JUAN PABLO GIL ALMANZA | B94: SOR_5 | C94: =+AVERAGE(G94,H94,L94) -> 1 | D94: 5 | E94: 5 | F94: =+E94/D94 -> 1 | G94: 1 | H94: 1 | I94: 1 | J94: 1 | K94: 1 | L94: 1 | M94: =+AVERAGE(I94,J94,K94) -> 1 | N94: 1.114458 | O94: =+G94 -> 1 | P94: 0 | Q94: 0.010464532 | R94: =+IF(Q94<3%,100%,0) -> 1 | S94: =+AVERAGE(O94,R94) -> 1
A95: =+VLOOKUP(B95,'INDICADORES CAPTURA'!C:E,3,FALSE) -> CAMPUZANO IRLET ANDREA | B95: MANIZALES_3 | C95: =+AVERAGE(G95,H95,L95) -> 0.875 | D95: 16 | E95: 14 | F95: =+E95/D95 -> 0.875 | G95: 0.875 | H95: 0.875 | I95: 0.75 | J95: 0.875 | K95: 0.63636364 | L95: 0.875 | M95: =+AVERAGE(I95,J95,K95) -> 0.75378788 | N95: 1.0708685 | O95: =+G95 -> 0.875 | P95: 0 | Q95: 0.016850606 | R95: =+IF(Q95<3%,100%,0) -> 1 | S95: =+O95 -> 0.875
A96: =+VLOOKUP(B96,'INDICADORES CAPTURA'!C:E,3,FALSE) -> OSSA TABARES JAZMIN BERNARDA | B96: MEDELLIN_10 | C96: =+AVERAGE(G96,H96,L96) -> 1 | D96: 15 | E96: 15 | F96: =+E96/D96 -> 1 | G96: 1 | H96: 1 | I96: 0.93333333 | J96: 1 | K96: 0.73333333 | L96: 1 | M96: =+AVERAGE(I96,J96,K96) -> 0.88888889 | N96: 1.0020663 | O96: =+G96 -> 1 | P96: 0 | Q96: 0.015395606 | R96: =+IF(Q96<3%,100%,0) -> 1 | S96: =+AVERAGE(O96,R96) -> 1
A97: =+VLOOKUP(B97,'INDICADORES CAPTURA'!C:E,3,FALSE) -> PEREZ ZAGARRA AUGUSTO EDUARDO | B97: CARTAGENA_3 | C97: =+AVERAGE(G97,H97,L97) -> 1 | D97: 22 | E97: 20 | F97: =+E97/D97 -> 0.90909091 | G97: 1 | H97: 1 | I97: 0.90909091 | J97: 1 | K97: 0.27659574 | L97: 1 | M97: =+AVERAGE(I97,J97,K97) -> 0.72856222 | N97: 0.85339122 | O97: =+G97 -> 1 | P97: 0 | Q97: 0.063959842 | R97: =+IF(Q97<3%,100%,0) -> 0 | S97: =+AVERAGE(O97,R97) -> 0.5
A98: =+VLOOKUP(B98,'INDICADORES CAPTURA'!C:E,3,FALSE) -> CAMPUZANO IRLET ANDREA | B98: PEREIRA_1 | C98: =+AVERAGE(G98,H98,L98) -> 1 | D98: 19 | E98: 19 | F98: =+E98/D98 -> 1 | G98: 1 | H98: 1 | I98: 0.84210526 | J98: 1 | K98: 0.74193548 | L98: 1 | M98: =+AVERAGE(I98,J98,K98) -> 0.86134692 | N98: 1.1008927 | O98: =+G98 -> 1 | P98: 0 | Q98: 0.031129834 | R98: =+IF(Q98<3%,100%,0) -> 0 | S98: =+AVERAGE(O98,R98) -> 0.5
A99: =+VLOOKUP(B99,'INDICADORES CAPTURA'!C:E,3,FALSE) -> OSSA TABARES JAZMIN BERNARDA | B99: MEDELLIN_8 | C99: =+AVERAGE(G99,H99,L99) -> 0.91666667 | D99: 12 | E99: 11 | F99: =+E99/D99 -> 0.91666667 | G99: 0.91666667 | H99: 0.91666667 | I99: 0.91666667 | J99: 0.91666667 | K99: 0.90909091 | L99: 0.91666667 | M99: =+AVERAGE(I99,J99,K99) -> 0.91414141 | N99: 1.1832045 | O99: =+G99 -> 0.91666667 | P99: 0 | Q99: 0.038960939 | R99: =+IF(Q99<3%,100%,0) -> 0 | S99: =+AVERAGE(O99,R99) -> 0.45833333
A100: =+VLOOKUP(B100,'INDICADORES CAPTURA'!C:E,3,FALSE) -> GIL MARTINEZ JENNIFER STEFANNIE | B100: NTE_1 | C100: =+AVERAGE(G100,H100,L100) -> 1 | D100: 11 | E100: 11 | F100: =+E100/D100 -> 1 | G100: 1 | H100: 1 | I100: 1 | J100: 1 | K100: 1 | L100: 1 | M100: =+AVERAGE(I100,J100,K100) -> 1 | N100: 0.76333245 | O100: =+G100 -> 1 | P100: 0 | Q100: 0.018343675 | R100: =+IF(Q100<3%,100%,0) -> 1 | S100: =+AVERAGE(O100,R100) -> 1
A101: =+VLOOKUP(B101,'INDICADORES CAPTURA'!C:E,3,FALSE) -> MARTINEZ VARGAS CHRISTAN RICARDO | B101: CALI_16 | C101: =+AVERAGE(G101,H101,L101) -> 0.88888889 | D101: 9 | E101: 8 | F101: =+E101/D101 -> 0.88888889 | G101: 0.88888889 | H101: 0.88888889 | I101: 0.77777778 | J101: 0.88888889 | K101: 0.28571429 | L101: 0.88888889 | M101: =+AVERAGE(I101,J101,K101) -> 0.65079365 | N101: 1.1540772 | O101: =+G101 -> 0.88888889 | P101: 0 | Q101: 0.032221439 | R101: =+IF(Q101<3%,100%,0) -> 0 | S101: =+O101 -> 0.88888889
A102: =+VLOOKUP(B102,'INDICADORES CAPTURA'!C:E,3,FALSE) -> GONZALEZ BARRANTES EDWIN JESSID | B102: VIJ_17 | C102: =+AVERAGE(G102,H102,L102) -> 0.87179487 | D102: 13 | E102: 11 | F102: =+E102/D102 -> 0.84615385 | G102: 0.84615385 | H102: 0.84615385 | I102: 0.84615385 | J102: 0.92307692 | K102: 0.6 | L102: 0.92307692 | M102: =+AVERAGE(I102,J102,K102) -> 0.78974359 | N102: 1.0383875 | O102: =+G102 -> 0.84615385 | P102: 0 | Q102: 0.046041184 | R102: =+IF(Q102<3%,100%,0) -> 0 | S102: =+AVERAGE(O102,R102) -> 0.42307692
A103: =+VLOOKUP(B103,'INDICADORES CAPTURA'!C:E,3,FALSE) -> SÁNCHEZ ZAMBRANO LEIDY NICOLE VANESSA | B103: BUCARAMANGA_7 | C103: =+AVERAGE(G103,H103,L103) -> 1 | D103: 9 | E103: 9 | F103: =+E103/D103 -> 1 | G103: 1 | H103: 1 | I103: 0.66666667 | J103: 1 | K103: 0.95652174 | L103: 1 | M103: =+AVERAGE(I103,J103,K103) -> 0.87439614 | N103: 0 | O103: =+G103 -> 1 | P103: 0 | Q103: 0.0254 | R103: =+IF(Q103<3%,100%,0) -> 1 | S103: =+AVERAGE(O103,R103) -> 1
A104: =+VLOOKUP(B104,'INDICADORES CAPTURA'!C:E,3,FALSE) -> CAMPUZANO IRLET ANDREA | B104: ARMENIA_1 | C104: =+AVERAGE(G104,H104,L104) -> 1 | D104: 22 | E104: 22 | F104: =+E104/D104 -> 1 | G104: 1 | H104: 1 | I104: 1 | J104: 1 | K104: 0.825 | L104: 1 | M104: =+AVERAGE(I104,J104,K104) -> 0.94166667 | N104: 1.0927891 | O104: =+G104 -> 1 | P104: 0 | Q104: 0.035190159 | R104: =+IF(Q104<3%,100%,0) -> 0 | S104: =+AVERAGE(O104,R104) -> 0.5
A105: =+VLOOKUP(B105,'INDICADORES CAPTURA'!C:E,3,FALSE) -> PEREZ ZAGARRA AUGUSTO EDUARDO | B105: CARTAGENA_1 | C105: =+AVERAGE(G105,H105,L105) -> 0.65333333 | D105: 25 | E105: 16 | F105: =+E105/D105 -> 0.64 | G105: 0.64 | H105: 0.64 | I105: 0.64 | J105: 0.68 | K105: 0.30232558 | L105: 0.68 | M105: =+AVERAGE(I105,J105,K105) -> 0.54077519 | N105: 0.89122277 | O105: =+G105 -> 0.64 | P105: 0 | Q105: 0.084508742 | R105: =+IF(Q105<3%,100%,0) -> 0 | S105: =+AVERAGE(O105,R105) -> 0.32
A106: =+VLOOKUP(B106,'INDICADORES CAPTURA'!C:E,3,FALSE) -> BOLAÑOS QUEVEDO ALEXIS | B106: CALI_5 | C106: =+AVERAGE(G106,H106,L106) -> 1 | D106: 16 | E106: 16 | F106: =+E106/D106 -> 1 | G106: 1 | H106: 1 | I106: 1 | J106: 1 | K106: 0.14285714 | L106: 1 | M106: =+AVERAGE(I106,J106,K106) -> 0.71428571 | N106: 0.95912082 | O106: =+G106 -> 1 | P106: 0 | Q106: 0.014623031 | R106: =+IF(Q106<3%,100%,0) -> 1 | S106: =+AVERAGE(O106,R106) -> 1
A107: =+VLOOKUP(B107,'INDICADORES CAPTURA'!C:E,3,FALSE) -> PEREZ ZAGARRA AUGUSTO EDUARDO | B107: CARTAGENA_2 | C107: =+AVERAGE(G107,H107,L107) -> 1 | D107: 24 | E107: 24 | F107: =+E107/D107 -> 1 | G107: 1 | H107: 1 | I107: 1 | J107: 1 | K107: 0.17391304 | L107: 1 | M107: =+AVERAGE(I107,J107,K107) -> 0.72463768 | N107: 1.034718 | O107: =+G107 -> 1 | P107: 0 | Q107: 0.06108554 | R107: =+IF(Q107<3%,100%,0) -> 0 | S107: =+AVERAGE(O107,R107) -> 0.5
A108: =+VLOOKUP(B108,'INDICADORES CAPTURA'!C:E,3,FALSE) -> MELISA MARTINEZ | B108: NOC_12 | C108: =+AVERAGE(G108,H108,L108) -> 1 | D108: 20 | E108: 20 | F108: =+E108/D108 -> 1 | G108: 1 | H108: 1 | I108: 0.7 | J108: 1 | K108: 1 | L108: 1 | M108: =+AVERAGE(I108,J108,K108) -> 0.9 | N108: 0.88482229 | O108: =+G108 -> 1 | P108: 0 | Q108: 0.026106303 | R108: =+IF(Q108<3%,100%,0) -> 1 | S108: =+AVERAGE(O108,R108) -> 1
A109: =+VLOOKUP(B109,'INDICADORES CAPTURA'!C:E,3,FALSE) -> SÁNCHEZ ZAMBRANO LEIDY NICOLE VANESSA | B109: BUCARAMANGA_5 | C109: =+AVERAGE(G109,H109,L109) -> 0.8974359 | D109: 13 | E109: 13 | F109: =+E109/D109 -> 1 | G109: 0.84615385 | H109: 0.84615385 | I109: 0.84615385 | J109: 1 | K109: 1 | L109: 1 | M109: =+AVERAGE(I109,J109,K109) -> 0.94871795 | N109: 0.87333086 | O109: =+G109 -> 0.84615385 | P109: 0 | Q109: 0.0254 | R109: =+IF(Q109<3%,100%,0) -> 1 | S109: =+AVERAGE(O109,R109) -> 0.92307692
A110: =+VLOOKUP(B110,'INDICADORES CAPTURA'!C:E,3,FALSE) -> BOLAÑOS QUEVEDO ALEXIS | B110: PALMIRA_1 | C110: =+AVERAGE(G110,H110,L110) -> 1 | D110: 12 | E110: 12 | F110: =+E110/D110 -> 1 | G110: 1 | H110: 1 | I110: 0 | J110: 1 | K110: 0 | L110: 1 | M110: =+AVERAGE(I110,J110,K110) -> 0.33333333 | N110: 1.1169146 | O110: =+G110 -> 1 | P110: 0 | Q110: 0.057488716 | R110: =+IF(Q110<3%,100%,0) -> 0 | S110: =+O110 -> 1
A111: =+VLOOKUP(B111,'INDICADORES CAPTURA'!C:E,3,FALSE) -> MARTINEZ VARGAS CHRISTAN RICARDO | B111: CALI_19 | C111: =+AVERAGE(G111,H111,L111) -> 0.91666667 | D111: 12 | E111: 11 | F111: =+E111/D111 -> 0.91666667 | G111: 0.91666667 | H111: 0.91666667 | I111: 0.91666667 | J111: 0.91666667 | K111: 0.80645161 | L111: 0.91666667 | M111: =+AVERAGE(I111,J111,K111) -> 0.87992832 | N111: 0.92570135 | O111: =+G111 -> 0.91666667 | P111: 0 | Q111: 0.030788972 | R111: =+IF(Q111<3%,100%,0) -> 0 | S111: =+AVERAGE(O111,R111) -> 0.45833333
A112: =+VLOOKUP(B112,'INDICADORES CAPTURA'!C:E,3,FALSE) -> SÁNCHEZ ZAMBRANO LEIDY NICOLE VANESSA | B112: BUCARAMANGA_4 | C112: =+AVERAGE(G112,H112,L112) -> 0.85185185 | D112: 9 | E112: 9 | F112: =+E112/D112 -> 1 | G112: 0.77777778 | H112: 0.77777778 | I112: 0.22222222 | J112: 1 | K112: 0.95 | L112: 1 | M112: =+AVERAGE(I112,J112,K112) -> 0.72407407 | N112: 0 | O112: =+G112 -> 0.77777778 | P112: 0 | Q112: 0.0254 | R112: =+IF(Q112<3%,100%,0) -> 1 | S112: =+O112 -> 0.77777778
...

Sheet INDICADORES CAPTURA
A1: Posición | B1: ID del Colaborador | C1: Nombre del Colaborador | D1: Tipo de Atención | E1: Supervisor | F1: Líder | G1: PDV Programados | H1: PDV Visitados | I1: Cobertura % | J1: Agotados % | K1: Precios % | L1: Participación % | M1: Inventarios % | N1: Planes Comerciales % | O1: Devoluciones % | P1: Fechas Cortas % | Q1: Runcal 2.0 % | R1: Actividades % | S1: Recolección de Cestillos % | T1: Objetivo de Planes | U1: Implementaciones Cumplidas | V1: Cumplimiento de Planes %
A2: 1 | B2: 17150 | C2: SOR_4 | D2: Exclusivo | E2: JUAN PABLO GIL ALMANZA | F2: ANYI MAYERLIE ORJUELA | G2: 5 | H2: 5 | I2: 1 | J2: 1 | K2: 1 | L2: 1 | M2: 0.4 | N2: 1 | O2: 1 | P2: 1 | Q2: 1 | R2: 1 | S2: 1 | T2: 6 | U2: 6 | V2: =+U2/T2 -> 1
A3: 2 | B3: 17165 | C3: VIJ_2 | D3: Exclusivo | E3: GONZALEZ BARRANTES EDWIN JESSID | F3: ANYI MAYERLIE ORJUELA | G3: 1 | H3: 1 | I3: 1 | J3: 1 | K3: 1 | L3: 1 | M3: 1 | N3: 1 | O3: 1 | P3: 1 | Q3: 1 | R3: 1 | S3: 1 | T3: 6 | U3: 6 | V3: =+U3/T3 -> 1
A4: 3 | B4: 17152 | C4: SOR_6 | D4: Exclusivo | E4: JUAN PABLO GIL ALMANZA | F4: ANYI MAYERLIE ORJUELA | G4: 5 | H4: 5 | I4: 1 | J4: 1 | K4: 1 | L4: 1 | M4: 0 | N4: 1 | O4: 1 | P4: 1 | Q4: 1 | R4: 1 | S4: 1 | T4: 9 | U4: 9 | V4: =+U4/T4 -> 1
A5: 4 | B5: 17096 | C5: NOC_15 | D5: Exclusivo | E5: MELISA MARTINEZ | F5: ANYI MAYERLIE ORJUELA | G5: 2 | H5: 2 | I5: 1 | J5: 1 | K5: 1 | L5: 0.5 | M5: 1 | N5: 1 | O5: 1 | P5: 1 | Q5: 1 | R5: 1 | S5: 1 | T5: 5 | U5: 5 | V5: =+U5/T5 -> 1
A6: 5 | B6: 17142 | C6: SOR_11 | D6: Exclusivo | E6: JUAN PABLO GIL ALMANZA | F6: ANYI MAYERLIE ORJUELA | G6: 16 | H6: 16 | I6: 1 | J6: 1 | K6: 1 | L6: 0.9375 | M6: 0 | N6: 1 | O6: 1 | P6: 1 | Q6: 1 | R6: 1 | S6: 1 | T6: 18 | U6: 18 | V6: =+U6/T6 -> 1
A7: 6 | B7: 17149 | C7: SOR_3 | D7: Exclusivo | E7: JUAN PABLO GIL ALMANZA | F7: ANYI MAYERLIE ORJUELA | G7: 6 | H7: 6 | I7: 1 | J7: 1 | K7: 1 | L7: 1 | M7: 0.16666667 | N7: 1 | O7: 1 | P7: 1 | Q7: 1 | R7: 1 | S7: 1 | T7: 7 | U7: 7 | V7: =+U7/T7 -> 1
A8: 7 | B8: 16819 | C8: MEDELLIN_1 | D8: Exclusivo | E8: MEJÍA BLANDÓN ASTRID KARINA | F8: OSPINO ARAUJO ALEXANDER | G8: 9 | H8: 9 | I8: 1 | J8: 1 | K8: 0.22222222 | L8: 0.33333333 | M8: 0.33333333 | N8: 1 | O8: 1 | P8: 1 | Q8: 1 | R8: 1 | S8: 1 | T8: 13 | U8: 13 | V8: =+U8/T8 -> 1
A9: 8 | B9: 17074 | C9: CTR_1 | D9: Exclusivo | E9: SUSANA SILVA MENDOZA | F9: ANYI MAYERLIE ORJUELA | G9: 9 | H9: 9 | I9: 1 | J9: 1 | K9: 0.88888889 | L9: 1 | M9: 0.77777778 | N9: 1 | O9: 1 | P9: 1 | Q9: 1 | R9: 1 | S9: 1 | T9: 31 | U9: 31 | V9: =+U9/T9 -> 1
A10: 9 | B10: 17169 | C10: VIJ_6 | D10: Exclusivo | E10: GONZALEZ BARRANTES EDWIN JESSID | F10: ANYI MAYERLIE ORJUELA | G10: 7 | H10: 7 | I10: 1 | J10: 1 | K10: 1 | L10: 1 | M10: 0 | N10: 1 | O10: 1 | P10: 1 | Q10: 1 | R10: 1 | S10: 1 | T10: 15 | U10: 15 | V10: =+U10/T10 -> 1
A11: 11 | B11: 17148 | C11: SOR_2 | D11: Exclusivo | E11: JUAN PABLO GIL ALMANZA | F11: ANYI MAYERLIE ORJUELA | G11: 5 | H11: 5 | I11: 1 | J11: 1 | K11: 1 | L11: 1 | M11: 0 | N11: 1 | O11: 1 | P11: 1 | Q11: 1 | R11: 1 | S11: 1 | T11: 8 | U11: 8 | V11: =+U11/T11 -> 1
A12: 12 | B12: 17147 | C12: SOR_16 | D12: Exclusivo | E12: JUAN PABLO GIL ALMANZA | F12: ANYI MAYERLIE ORJUELA | G12: 10 | H12: 10 | I12: 1 | J12: 1 | K12: 1 | L12: 1 | M12: 0.5 | N12: 1 | O12: 1 | P12: 1 | Q12: 1 | R12: 1 | S12: 1 | T12: 8 | U12: 8 | V12: =+U12/T12 -> 1
A13: 13 | B13: 16842 | C13: POPAYAN_1 | D13: Exclusivo | E13: MARTINEZ VARGAS CHRISTAN RICARDO | F13: NATHALY AGUILAR | G13: 9 | H13: 9 | I13: 1 | J13: 1 | K13: 1 | L13: 1 | M13: 0.77777778 | N13: 0.61538462 | O13: 1 | P13: 1 | Q13: 1 | R13: 1 | S13: 1 | T13: 39 | U13: 24 | V13: =+U13/T13 -> 0.61538462
... A15: 15 | B15: 17155 | C15: SOR_9 | D15: Exclusivo | E15: JUAN PABLO GIL ALMANZA | F15: ANYI MAYERLIE ORJUELA | G15: 8 | H15: 8 | I15: 1 | J15: 1 | K15: 1 | L15: 1 | M15: 0.125 | N15: 1 | O15: 1 | P15: 1 | Q15: 1 | R15: 1 | S15: 1 | T15: 17 | U15: 17 | V15: =+U15/T15 -> 1
A16: 16 | B16: 17125 | C16: SOC_12 | D16: Exclusivo | E16: MELISA MARTINEZ | F16: ANYI MAYERLIE ORJUELA | G16: 1 | H16: 1 | I16: 1 | J16: 1 | K16: 1 | L16: 1 | M16: 1 | N16: 1 | O16: 0 | P16: 1 | Q16: 0 | R16: 0 | S16: 0 | T16: 0 | U16: 0 | V16: 1
A17: 17 | B17: 16691 | C17: BARRANQUILLA_3 | D17: Exclusivo | E17: PEREZ ZAGARRA AUGUSTO EDUARDO | F17: OSPINO ARAUJO ALEXANDER | G17: 24 | H17: 22 | I17: 0.91666667 | J17: 0.91666667 | K17: 0.25 | L17: 0.91666667 | M17: 0.95833333 | N17: 0.96666667 | O17: 0.95833333 | P17: 0.95833333 | Q17: 0.95833333 | R17: 0.95833333 | S17: 0.95833333 | T17: 60 | U17: 58 | V17: =+U17/T17 -> 0.96666667
A18: 18 | B18: 16821 | C18: MEDELLIN_3 | D18: Exclusivo | E18: MEJÍA BLANDÓN ASTRID KARINA | F18: OSPINO ARAUJO ALEXANDER | G18: 2 | H18: 1 | I18: 0.5 | J18: 0.5 | K18: 0.5 | L18: 0.5 | M18: 0 | N18: 1 | O18: 0.5 | P18: 0.5 | Q18: 0.5 | R18: 0.5 | S18: 0.5 | T18: 2 | U18: 2 | V18: =+U18/T18 -> 1
A19: 19 | B19: 17134 | C19: SOC_4 | D19: Exclusivo | E19: PIÑEROS MONTAÑA LAURA ESTEPHANIA | F19: ANYI MAYERLIE ORJUELA | G19: 17 | H19: 17 | I19: 1 | J19: 1 | K19: 1 | L19: 1 | M19: 0.058823529 | N19: 0.92857143 | O19: 1 | P19: 1 | Q19: 1 | R19: 1 | S19: 1 | T19: 14 | U19: 13 | V19: =+U19/T19 -> 0.92857143
A20: 20 | B20: 16816 | C20: MANIZALES_1 | D20: Exclusivo | E20: CAMPUZANO IRLET ANDREA | F20: NATHALY AGUILAR | G20: 18 | H20: 18 | I20: 1 | J20: 1 | K20: 0.94444444 | L20: 1 | M20: 0.55555556 | N20: 0.95833333 | O20: 1 | P20: 1 | Q20: 1 | R20: 1 | S20: 1 | T20: 24 | U20: 23 | V20: =+U20/T20 -> 0.95833333
A21: 21 | B21: 17094 | C21: NOC_13 | D21: Exclusivo | E21: MELISA MARTINEZ | F21: ANYI MAYERLIE ORJUELA | G21: 11 | H21: 11 | I21: 1 | J21: 1 | K21: 1 | L21: 0.63636364 | M21: 0.18181818 | N21: 1 | O21: 1 | P21: 1 | Q21: 1 | R21: 1 | S21: 1 | T21: 16 | U21: 16 | V21: =+U21/T21 -> 1
A22: 22 | B22: 16814 | C22: ITAGUI_1 | D22: Exclusivo | E22: MEJÍA BLANDÓN ASTRID KARINA | F22: OSPINO ARAUJO ALEXANDER | G22: 18 | H22: 18 | I22: 1 | J22: 1 | K22: 0.27777778 | L22: 0.33333333 | M22: 0.16666667 | N22: 0.40909091 | O22: 1 | P22: 1 | Q22: 1 | R22: 1 | S22: 1 | T22: 22 | U22: 9 | V22: =+U22/T22 -> 0.40909091
A23: 23 | B23: 17146 | C23: SOR_15 | D23: Exclusivo | E23: JUAN PABLO GIL ALMANZA | F23: ANYI MAYERLIE ORJUELA | G23: 18 | H23: 18 | I23: 1 | J23: 0.94444444 | K23: 0.66666667 | L23: 0.94444444 | M23: 0 | N23: 1 | O23: 0.94444444 | P23: 0.94444444 | Q23: 0.94444444 | R23: 1 | S23: 0.94444444 | T23: 8 | U23: 8 | V23: =+U23/T23 -> 1
A24: 24 | B24: 17095 | C24: NOC_14 | D24: Exclusivo | E24: MELISA MARTINEZ | F24: ANYI MAYERLIE ORJUELA | G24: 1 | H24: 1 | I24: 1 | J24: 1 | K24: 1 | L24: 1 | M24: 1 | N24: 1 | O24: 1 | P24: 1 | Q24: 1 | R24: 1 | S24: 1 | T24: 4 | U24: 4 | V24: =+U24/T24 -> 1
A25: 25 | B25: 17158 | C25: VIJ_11 | D25: Exclusivo | E25: GONZALEZ BARRANTES EDWIN JESSID | F25: ANYI MAYERLIE ORJUELA | G25: 9 | H25: 9 | I25: 1 | J25: 1 | K25: 1 | L25: 1 | M25: 0.22222222 | N25: 1 | O25: 1 | P25: 1 | Q25: 1 | R25: 1 | S25: 1 | T25: 8 | U25: 8 | V25: =+U25/T25 -> 1
A26: 26 | B26: 16894 | C26: BARRANCABERMEJA_1 | D26: Exclusivo | E26: SÁNCHEZ ZAMBRANO LEIDY NICOLE VANESSA | F26: OSPINO ARAUJO ALEXANDER | G26: 5 | H26: 4 | I26: 0.8 | J26: 1 | K26: 0.6 | L26: 0.8 | M26: 0.8 | N26: 0.81818182 | O26: 1 | P26: 1 | Q26: 1 | R26: 1 | S26: 1 | T26: 11 | U26: 9 | V26: =+U26/T26 -> 0.81818182
A27: 27 | B27: 17123 | C27: SOC_10 | D27: Exclusivo | E27: PIÑEROS MONTAÑA LAURA ESTEPHANIA | F27: ANYI MAYERLIE ORJUELA | G27: 12 | H27: 12 | I27: 1 | J27: 1 | K27: 1 | L27: 1 | M27: 0.41666667 | N27: 1 | O27: 1 | P27: 1 | Q27: 1 | R27: 1 | S27: 1 | T27: 13 | U27: 13 | V27: =+U27/T27 -> 1
A28: 28 | B28: 17126 | C28: SOC_13 | D28: Exclusivo | E28: PIÑEROS MONTAÑA LAURA ESTEPHANIA | F28: ANYI MAYERLIE ORJUELA | G28: 9 | H28: 9 | I28: 1 | J28: 1 | K28: 0.33333333 | L28: 1 | M28: 0.22222222 | N28: 1 | O28: 1 | P28: 1 | Q28: 1 | R28: 1 | S28: 1 | T28: 12 | U28: 12 | V28: =+U28/T28 -> 1
... A30: 31 | B30: 17128 | C30: SOC_15 | D30: Exclusivo | E30: PIÑEROS MONTAÑA LAURA ESTEPHANIA | F30: ANYI MAYERLIE ORJUELA | G30: 7 | H30: 7 | I30: 1 | J30: 1 | K30: 0.42857143 | L30: 1 | M30: 0.57142857 | N30: 0.84615385 | O30: 1 | P30: 1 | Q30: 1 | R30: 1 | S30: 1 | T30: 13 | U30: 11 | V30: =+U30/T30 -> 0.84615385
A31: 32 | B31: 16847 | C31: SANTA MARTA_2 | D31: Exclusivo | E31: PEREZ ZAGARRA AUGUSTO EDUARDO | F31: OSPINO ARAUJO ALEXANDER | G31: 19 | H31: 19 | I31: 1 | J31: 1 | K31: 0.73684211 | L31: 1 | M31: 0.89473684 | N31: 1 | O31: 1 | P31: 0.94736842 | Q31: 1 | R31: 1 | S31: 1 | T31: 0 | U31: 0 | V31: 1
A32: 34 | B32: 17115 | C32: NTE_3 | D32: Exclusivo | E32: MELISA MARTINEZ | F32: ANYI MAYERLIE ORJUELA | G32: 1 | H32: 1 | I32: 1 | J32: 1 | K32: 1 | L32: 0 | M32: 1 | N32: 1 | O32: 1 | P32: 1 | Q32: 1 | R32: 1 | S32: 1 | T32: 5 | U32: 5 | V32: =+U32/T32 -> 1
A33: 35 | B33: 17139 | C33: SOC_9 | D33: Exclusivo | E33: PIÑEROS MONTAÑA LAURA ESTEPHANIA | F33: ANYI MAYERLIE ORJUELA | G33: 8 | H33: 8 | I33: 1 | J33: 1 | K33: 1 | L33: 1 | M33: 0.5 | N33: 1 | O33: 1 | P33: 1 | Q33: 1 | R33: 1 | S33: 1 | T33: 7 | U33: 7 | V33: =+U33/T33 -> 1
A34: 36 | B34: 16825 | C34: MEDELLIN_7 | D34: Exclusivo | E34: MEJÍA BLANDÓN ASTRID KARINA | F34: OSPINO ARAUJO ALEXANDER | G34: 3 | H34: 1 | I34: 0.33333333 | J34: 0.33333333 | K34: 0.33333333 | L34: 0.33333333 | M34: 0.33333333 | N34: 1 | O34: 0.33333333 | P34: 0.33333333 | Q34: 0.33333333 | R34: 0.33333333 | S34: 0.33333333 | T34: 4 | U34: 4 | V34: =+U34/T34 -> 1
A35: 37 | B35: 17102 | C35: NOC_6 | D35: Exclusivo | E35: MELISA MARTINEZ | F35: ANYI MAYERLIE ORJUELA | G35: 9 | H35: 9 | I35: 1 | J35: 1 | K35: 1 | L35: 1 | M35: 0.55555556 | N35: 1 | O35: 1 | P35: 1 | Q35: 1 | R35: 1 | S35: 1 | T35: 11 | U35: 11 | V35: =+U35/T35 -> 1
A36: 38 | B36: 17129 | C36: SOC_16 | D36: Exclusivo | E36: PIÑEROS MONTAÑA LAURA ESTEPHANIA | F36: ANYI MAYERLIE ORJUELA | G36: 1 | H36: 1 | I36: 1 | J36: 1 | K36: 1 | L36: 1 | M36: 1 | N36: 1 | O36: 1 | P36: 1 | Q36: 1 | R36: 1 | S36: 1 | T36: 7 | U36: 7 | V36: =+U36/T36 -> 1
A37: 39 | B37: 16903 | C37: BUCARAMANGA_8 | D37: Exclusivo | E37: SÁNCHEZ ZAMBRANO LEIDY NICOLE VANESSA | F37: OSPINO ARAUJO ALEXANDER | G37: 8 | H37: 8 | I37: 1 | J37: 1 | K37: 1 | L37: 1 | M37: 0.25 | N37: 1 | O37: 1 | P37: 1 | Q37: 1 | R37: 1 | S37: 1 | T37: 18 | U37: 18 | V37: =+U37/T37 -> 1
A38: 40 | B38: 16782 | C38: CALI_8 | D38: Exclusivo | E38: MARTINEZ VARGAS CHRISTAN RICARDO | F38: NATHALY AGUILAR | G38: 9 | H38: 9 | I38: 1 | J38: 1 | K38: 1 | L38: 1 | M38: 0.33333333 | N38: 0.33333333 | O38: 1 | P38: 1 | Q38: 1 | R38: 1 | S38: 1 | T38: 15 | U38: 5 | V38: =+U38/T38 -> 0.33333333
A39: 41 | B39: 17104 | C39: NOC_8 | D39: Exclusivo | E39: MELISA MARTINEZ | F39: ANYI MAYERLIE ORJUELA | G39: 5 | H39: 5 | I39: 1 | J39: 1 | K39: 0.8 | L39: 1 | M39: 0.6 | N39: 0.81818182 | O39: 1 | P39: 1 | Q39: 1 | R39: 1 | S39: 1 | T39: 11 | U39: 9 | V39: =+U39/T39 -> 0.81818182
A40: 42 | B40: 17135 | C40: SOC_5 | D40: Exclusivo | E40: PIÑEROS MONTAÑA LAURA ESTEPHANIA | F40: ANYI MAYERLIE ORJUELA | G40: 8 | H40: 8 | I40: 1 | J40: 1 | K40: 1 | L40: 1 | M40: 0.125 | N40: 1 | O40: 1 | P40: 1 | Q40: 1 | R40: 1 | S40: 1 | T40: 5 | U40: 5 | V40: =+U40/T40 -> 1
A41: 43 | B41: 16776 | C41: CALI_2 | D41: Exclusivo | E41: MARTINEZ VARGAS CHRISTAN RICARDO | F41: NATHALY AGUILAR | G41: 1 | H41: 1 | I41: 1 | J41: 1 | K41: 1 | L41: 1 | M41: 0 | N41: 1 | O41: 1 | P41: 1 | Q41: 1 | R41: 1 | S41: 1 | T41: 3 | U41: 3 | V41: =+U41/T41 -> 1
A42: 44 | B42: 17131 | C42: SOC_18 | D42: Exclusivo | E42: PIÑEROS MONTAÑA LAURA ESTEPHANIA | F42: ANYI MAYERLIE ORJUELA | G42: 17 | H42: 17 | I42: 1 | J42: 1 | K42: 1 | L42: 1 | M42: 0.058823529 | N42: 0.95833333 | O42: 1 | P42: 1 | Q42: 1 | R42: 1 | S42: 1 | T42: 24 | U42: 23 | V42: =+U42/T42 -> 0.95833333
A43: 45 | B43: 17116 | C43: NTE_4 | D43: Exclusivo | E43: GIL MARTINEZ JENNIFER STEFANNIE | F43: ANYI MAYERLIE ORJUELA | G43: 18 | H43: 18 | I43: 1 | J43: 1 | K43: 1 | L43: 1 | M43: 0.94444444 | N43: 0.93333333 | O43: 1 | P43: 1 | Q43: 1 | R43: 1 | S43: 1 | T43: 30 | U43: 28 | V43: =+U43/T43 -> 0.93333333
... A52: 57 | B52: 16829 | C52: MEDELLIN_11 | D52: Exclusivo | E52: OSSA TABARES JAZMIN BERNARDA | F52: OSPINO ARAUJO ALEXANDER | G52: 16 | H52: 16 | I52: 1 | J52: 1 | K52: 0.8125 | L52: 1 | M52: 0 | N52: 1 | O52: 1 | P52: 1 | Q52: 1 | R52: 1 | S52: 1 | T52: 16 | U52: 16 | V52: =+U52/T52 -> 1
A53: 58 | B53: 16846 | C53: SANTA MARTA_1 | D53: Exclusivo | E53: PEREZ ZAGARRA AUGUSTO EDUARDO | F53: OSPINO ARAUJO ALEXANDER | G53: 18 | H53: 18 | I53: 1 | J53: 1 | K53: 0.94444444 | L53: 1 | M53: 0.44444444 | N53: 1 | O53: 1 | P53: 1 | Q53: 1 | R53: 1 | S53: 1 | T53: 0 | U53: 0 | V53: 1
A54: 59 | B54: 17140 | C54: SOR_1 | D54: Exclusivo | E54: JUAN PABLO GIL ALMANZA | F54: ANYI MAYERLIE ORJUELA | G54: 14 | H54: 14 | I54: 1 | J54: 1 | K54: 1 | L54: 1 | M54: 0.64285714 | N54: 1 | O54: 1 | P54: 1 | Q54: 1 | R54: 1 | S54: 1 | T54: 12 | U54: 12 | V54: =+U54/T54 -> 1
A55: 60 | B55: 17080 | C55: CTR_15 | D55: Exclusivo | E55: SUSANA SILVA MENDOZA | F55: ANYI MAYERLIE ORJUELA | G55: 15 | H55: 15 | I55: 1 | J55: 1 | K55: 1 | L55: 0.86666667 | M55: 0.2 | N55: 1 | O55: 1 | P55: 1 | Q55: 1 | R55: 1 | S55: 1 | T55: 23 | U55: 23 | V55: =+U55/T55 -> 1
A56: 61 | B56: 17122 | C56: SOC_1 | D56: Exclusivo | E56: PIÑEROS MONTAÑA LAURA ESTEPHANIA | F56: ANYI MAYERLIE ORJUELA | G56: 4 | H56: 4 | I56: 1 | J56: 1 | K56: 1 | L56: 1 | M56: 0 | N56: 0.77777778 | O56: 1 | P56: 1 | Q56: 1 | R56: 1 | S56: 1 | T56: 9 | U56: 7 | V56: =+U56/T56 -> 0.77777778
A57: 62 | B57: 16901 | C57: BUCARAMANGA_6 | D57: Exclusivo | E57: SÁNCHEZ ZAMBRANO LEIDY NICOLE VANESSA | F57: OSPINO ARAUJO ALEXANDER | G57: 13 | H57: 13 | I57: 1 | J57: 0.84615385 | K57: 0.84615385 | L57: 0.84615385 | M57: 0.46153846 | N57: 1 | O57: 1 | P57: 0.76923077 | Q57: 1 | R57: 1 | S57: 1 | T57: 18 | U57: 18 | V57: =+U57/T57 -> 1
A58: 63 | B58: 17089 | C58: CTR_9 | D58: Exclusivo | E58: SUSANA SILVA MENDOZA | F58: ANYI MAYERLIE ORJUELA | G58: 5 | H58: 5 | I58: 1 | J58: 1 | K58: 0.8 | L58: 1 | M58: 0.8 | N58: 1 | O58: 1 | P58: 1 | Q58: 1 | R58: 1 | S58: 1 | T58: 6 | U58: 6 | V58: =+U58/T58 -> 1
A59: 64 | B59: 17170 | C59: VIJ_7 | D59: Exclusivo | E59: GONZALEZ BARRANTES EDWIN JESSID | F59: ANYI MAYERLIE ORJUELA | G59: 13 | H59: 13 | I59: 1 | J59: 1 | K59: 0.30769231 | L59: 0.92307692 | M59: 0.076923077 | N59: 0.77777778 | O59: 1 | P59: 1 | Q59: 1 | R59: 1 | S59: 1 | T59: 18 | U59: 14 | V59: =+U59/T59 -> 0.77777778
A60: 65 | B60: 17130 | C60: SOC_17 | D60: Exclusivo | E60: PIÑEROS MONTAÑA LAURA ESTEPHANIA | F60: ANYI MAYERLIE ORJUELA | G60: 18 | H60: 18 | I60: 1 | J60: 1 | K60: 1 | L60: 1 | M60: 0.27777778 | N60: 0.90909091 | O60: 1 | P60: 1 | Q60: 1 | R60: 1 | S60: 1 | T60: 22 | U60: 20 | V60: =+U60/T60 -> 0.90909091
A61: 66 | B61: 17143 | C61: SOR_12 | D61: Exclusivo | E61: JUAN PABLO GIL ALMANZA | F61: ANYI MAYERLIE ORJUELA | G61: 15 | H61: 15 | I61: 1 | J61: 1 | K61: 1 | L61: 1 | M61: 0.93333333 | N61: 1 | O61: 1 | P61: 1 | Q61: 1 | R61: 1 | S61: 1 | T61: 9 | U61: 9 | V61: =+U61/T61 -> 1
A62: 67 | B62: 17124 | C62: SOC_11 | D62: Exclusivo | E62: PIÑEROS MONTAÑA LAURA ESTEPHANIA | F62: ANYI MAYERLIE ORJUELA | G62: 7 | H62: 7 | I62: 1 | J62: 1 | K62: 1 | L62: 1 | M62: 0.28571429 | N62: 1 | O62: 1 | P62: 1 | Q62: 1 | R62: 1 | S62: 1 | T62: 12 | U62: 12 | V62: =+U62/T62 -> 1
A63: 68 | B63: 16843 | C63: RIONEGRO_1 | D63: Exclusivo | E63: MEJÍA BLANDÓN ASTRID KARINA | F63: OSPINO ARAUJO ALEXANDER | G63: 8 | H63: 7 | I63: 0.875 | J63: 0.875 | K63: 0.25 | L63: 0.25 | M63: 0 | N63: 0.52941176 | O63: 0.875 | P63: 0.875 | Q63: 0.875 | R63: 0.875 | S63: 0.875 | T63: 17 | U63: 9 | V63: =+U63/T63 -> 0.52941176
A64: 69 | B64: 16692 | C64: BARRANQUILLA_4 | D64: Exclusivo | E64: PEREZ ZAGARRA AUGUSTO EDUARDO | F64: OSPINO ARAUJO ALEXANDER | G64: 24 | H64: 22 | I64: 0.91666667 | J64: 0.70833333 | K64: 0.75 | L64: 0.83333333 | M64: 0.79166667 | N64: 0.96202532 | O64: 0.875 | P64: 0.875 | Q64: 0.875 | R64: 0.875 | S64: 0.875 | T64: 79 | U64: 76 | V64: =+U64/T64 -> 0.96202532
A65: 70 | B65: 16895 | C65: BARRANCABERMEJA_2 | D65: Exclusivo | E65: SÁNCHEZ ZAMBRANO LEIDY NICOLE VANESSA | F65: OSPINO ARAUJO ALEXANDER | G65: 1 | H65: 1 | I65: 1 | J65: 1 | K65: 0 | L65: 1 | M65: 0 | N65: 1 | O65: 1 | P65: 1 | Q65: 1 | R65: 1 | S65: 1 | T65: 3 | U65: 3 | V65: =+U65/T65 -> 1
A66: 71 | B66: 17085 | C66: CTR_5 | D66: Exclusivo | E66: SUSANA SILVA MENDOZA | F66: ANYI MAYERLIE ORJUELA | G66: 1 | H66: 1 | I66: 1 | J66: 1 | K66: 0 | L66: 1 | M66: 0 | N66: 1 | O66: 0 | P66: 1 | Q66: 0 | R66: 0 | S66: 0 | T66: 0 | U66: 0 | V66: 1
